Workbook
Name FX_Rate_Entity1: FX_Conversion!$C$4
Name FX_Rate_Entity10: FX_Conversion!$C$13
Name FX_Rate_Entity2: FX_Conversion!$C$5
Name FX_Rate_Entity3: FX_Conversion!$C$6
Name FX_Rate_Entity4: FX_Conversion!$C$7
Name FX_Rate_Entity5: FX_Conversion!$C$8
Name FX_Rate_Entity6: FX_Conversion!$C$9
Name FX_Rate_Entity7: FX_Conversion!$C$10
Name FX_Rate_Entity8: FX_Conversion!$C$11
Name FX_Rate_Entity9: FX_Conversion!$C$12
Name NR_Beta: Valuation!$B$6
Name NR_Client_Currency: Client_Info!$B$6
Name NR_Client_Name: Client_Info!$B$3
Name NR_Cost_of_Debt: Valuation!$B$8
Name NR_Cost_of_Equity: Valuation!$B$12
Name NR_DCF_Value: Valuation!$B$23
Name NR_Debt_Weight: Valuation!$B$10
Name NR_EBITDA_Multiple: "Valuation!B27"
Name NR_EBITDA_Normalized: "Adjustments!B21"
Name NR_Entity_Count: Client_Info!$B$10
Name NR_Equity_Weight: Valuation!$B$11
Name NR_Exit_Multiple: "Valuation!C18"
Name NR_Final_Valuation: Valuation!$B$36
Name NR_FX_Auto: FX_Conversion!$J$8
Name NR_FX_Date: FX_Conversion!$J$6
Name NR_FX_Final: FX_Conversion!$J$9
Name NR_FX_Source: FX_Conversion!$J$5
Name NR_Industry: Client_Info!$B$4
Name NR_List_ContributionType: Client_Info!$N$2:$N$5
Name NR_List_Country: Client_Info!$J$2:$J$11
Name NR_List_Currency: Client_Info!$K$2:$K$11
Name NR_List_Document_Status: Client_Info!$O$8:$R$8
Name NR_List_DocumentStatus: Client_Info!$P$2:$P$4
Name NR_List_Entity: Client_Info!$O$11:$W$11
Name NR_List_FX_Source: Client_Info!$O$6:$P$6
Name NR_List_FXSource: Client_Info!$M$2:$M$3
Name NR_List_JV_Contribution_Type: Client_Info!$O$4:$R$4
Name NR_List_OverrideReason: Client_Info!$R$2:$R$4
Name NR_List_Ownership_Type: Client_Info!$O$3:$R$3
Name NR_List_Rate_Override_Reason: Client_Info!$O$7:$R$7
Name NR_List_Scenario: Client_Info!$O$9:$Q$9
Name NR_List_Waterfall_Tier: Client_Info!$O$5:$R$5
Name NR_List_WaterfallTier: Client_Info!$O$2:$O$5
Name NR_List_Yes_No: Client_Info!$O$10:$P$10
Name NR_List_YesNo: Client_Info!$L$2:$L$3
Name NR_Location: Client_Info!$B$5
Name NR_Market_Risk_Premium: Valuation!$B$7
Name NR_Multiples_Value: "Valuation!D30"
Name NR_PE_Multiple: "Valuation!B29"
Name NR_Revenue_Multiple: "Valuation!B28"
Name NR_RiskFree: Valuation!$B$5
Name NR_Service_Line: Client_Info!$B$8
Name NR_Tax_Rate: Valuation!$B$9
Name NR_Terminal_Growth: "Valuation!B18"
Name NR_Terminal_Value: "Valuation!G19"
Name NR_USD_Rate: FX_Conversion!$J$7
Name NR_Valuation_Date: Client_Info!$B$7
Name NR_Valuation_Type: Client_Info!$B$9
Name NR_WACC: Valuation!$B$13

Sheet Client_Info
A1: CLIENT INFORMATION FORM | J1: Country_List | K1: Currency_List | L1: YesNo_List | M1: FX_Source_List | N1: List_Country | O1: United States | P1: Canada | Q1: United Kingdom | R1: Germany | S1: France | T1: Japan | U1: Australia | V1: Mexico | W1: Entity 10
A2: Field | B2: Input | J2: United States | K2: USD | L2: Yes | M2: Auto | N2: List_Currency | O2: USD | P2: EUR | Q2: GBP | R2: CAD | S2: JPY | T2: AUD | U2: MXN | V2: CHF
A3: Client Name | J3: Canada | K3: EUR | L3: No | M3: Manual | N3: List_Ownership_Type | O3: Subsidiary | P3: JV | Q3: Minority | R3: Branch
A4: Industry (NAICS) | J4: United Kingdom | K4: GBP | N4: List_JV_Contribution_Type | O4: Cash | P4: IP | Q4: Services | R4: Assets
A5: Location | J5: Germany | K5: CAD | N5: List_Waterfall_Tier | O5: Tier 1 | P5: Tier 2 | Q5: Tier 3 | R5: Tier 4
A6: Client Currency | J6: France | K6: JPY | N6: List_FX_Source | O6: Auto | P6: Manual
A7: Valuation Date | J7: India | K7: AUD | N7: List_Rate_Override_Reason | O7: Manual Override | P7: Data Provider Exception | Q7: Historical Adjustment | R7: Management Input
A8: Service Line | J8: Japan | K8: INR | N8: List_Document_Status | O8: Received | P8: Missing | Q8: Requested | R8: Under Review
A9: Valuation Type | J9: Australia | K9: MXN | N9: List_Scenario | O9: Best Case | P9: Base Case | Q9: Worst Case
A10: Entity Count | B10: 10 | J10: Mexico | K10: BRL | N10: List_Yes_No | O10: Yes | P10: No
J11: Brazil | K11: CHF | N11: List_Entity | O11: Entity 1 | P11: Entity 2 | Q11: Entity 3 | R11: Entity 4 | S11: Entity 5 | T11: Entity 6 | U11: Entity 7 | V11: Entity 8

Sheet FX_Conversion
A1: FX CONVERSION - MULTI ENTITY | I1: FX CONTROL PANEL
A3: Entity | B3: Currency | C3: Previous Month-End FX Rate | D3: Source URL | E3: AI_Fetched (Yes/No) | F3: Manual Override (Yes/No) | G3: Notes | I3: Field | J3: Value
A4: Entity 1 | E4: =IF(OR(B4="",D4=""),"","Yes") | G4: =IF(B4="","WARNING: Missing Currency Data",IF(C4="","WARNING: Missing FX Rate","")) -> WARNING: Missing Currency Data | I4: Client Currency | J4: =IF(Client_Info!B6="","",Client_Info!B6)
A5: Entity 2 | E5: =IF(OR(B5="",D5=""),"","Yes") | G5: =IF(B5="","WARNING: Missing Currency Data",IF(C5="","WARNING: Missing FX Rate","")) -> WARNING: Missing Currency Data | I5: FX Rate Source
A6: Entity 3 | E6: =IF(OR(B6="",D6=""),"","Yes") | G6: =IF(B6="","WARNING: Missing Currency Data",IF(C6="","WARNING: Missing FX Rate","")) -> WARNING: Missing Currency Data | I6: FX Historical Date | J6: =EOMONTH(TODAY(),-1) -> 46142
A7: Entity 4 | E7: =IF(OR(B7="",D7=""),"","Yes") | G7: =IF(B7="","WARNING: Missing Currency Data",IF(C7="","WARNING: Missing FX Rate","")) -> WARNING: Missing Currency Data | I7: USD Conversion Rate
A8: Entity 5 | E8: =IF(OR(B8="",D8=""),"","Yes") | G8: =IF(B8="","WARNING: Missing Currency Data",IF(C8="","WARNING: Missing FX Rate","")) -> WARNING: Missing Currency Data | I8: Auto-Fetched FX Rate | J8: =IF($J$4="","",IFERROR(INDEX($C$4:$C$13,MATCH($J$4,$B$4:$B$13,0)),""))
A9: Entity 6 | E9: =IF(OR(B9="",D9=""),"","Yes") | G9: =IF(B9="","WARNING: Missing Currency Data",IF(C9="","WARNING: Missing FX Rate","")) -> WARNING: Missing Currency Data | I9: Final FX Rate Used | J9: =IF(NR_FX_Source="Manual",NR_USD_Rate,NR_FX_Auto)
A10: Entity 7 | E10: =IF(OR(B10="",D10=""),"","Yes") | G10: =IF(B10="","WARNING: Missing Currency Data",IF(C10="","WARNING: Missing FX Rate","")) -> WARNING: Missing Currency Data
A11: Entity 8 | E11: =IF(OR(B11="",D11=""),"","Yes") | G11: =IF(B11="","WARNING: Missing Currency Data",IF(C11="","WARNING: Missing FX Rate","")) -> WARNING: Missing Currency Data
A12: Entity 9 | E12: =IF(OR(B12="",D12=""),"","Yes") | G12: =IF(B12="","WARNING: Missing Currency Data",IF(C12="","WARNING: Missing FX Rate","")) -> WARNING: Missing Currency Data
A13: Entity 10 | E13: =IF(OR(B13="",D13=""),"","Yes") | G13: =IF(B13="","WARNING: Missing Currency Data",IF(C13="","WARNING: Missing FX Rate","")) -> WARNING: Missing Currency Data
A16: Formula Reference
A17: Code
A18: Value_USD = Value_Local * FX_Rate
A19: Policy | B19: All rate lookups must use previous month-end values with manual override allowed.
A20: Warning Rule | B20: If currency is missing, display a warning.

Sheet Fin_Inputs_Entity1
A1: ENTITY 1 FINANCIAL INPUTS
A3: INCOME STATEMENT
A4: Line Item | B4: Year 1 | C4: Year 2 | D4: Year 3 | E4: Year 4 | F4: Year 5
A5: Revenue
A6: COGS
A7: Gross Profit
A8: Operating Expenses
A9: EBITDA
A10: Depreciation
A11: EBIT
A12: Interest
A13: Taxes
A14: Net Income
A16: BALANCE SHEET
A17: Line Item | B17: Year 1 | C17: Year 2 | D17: Year 3 | E17: Year 4 | F17: Year 5
A18: Cash
A19: AR
A20: Inventory
A21: Current Assets
A22: PP&E
A23: Total Assets
A24: AP
A25: Accrued Liabilities
A26: Short-Term Debt
A27: Long-Term Debt
A28: Total Liabilities
A29: Equity
A31: CASH FLOW STATEMENT
A32: Line Item | B32: Year 1 | C32: Year 2 | D32: Year 3 | E32: Year 4 | F32: Year 5
A33: Net Income
A34: Depreciation
A35: Working Capital Changes
A36: Capex
A37: Free Cash Flow

Sheet Fin_Inputs_Entity2
A1: ENTITY 2 FINANCIAL INPUTS
A3: INCOME STATEMENT
A4: Line Item | B4: Year 1 | C4: Year 2 | D4: Year 3 | E4: Year 4 | F4: Year 5
A5: Revenue
A6: COGS
A7: Gross Profit
A8: Operating Expenses
A9: EBITDA
A10: Depreciation
A11: EBIT
A12: Interest
A13: Taxes
A14: Net Income
A16: BALANCE SHEET
A17: Line Item | B17: Year 1 | C17: Year 2 | D17: Year 3 | E17: Year 4 | F17: Year 5
A18: Cash
A19: AR
A20: Inventory
A21: Current Assets
A22: PP&E
A23: Total Assets
A24: AP
A25: Accrued Liabilities
A26: Short-Term Debt
A27: Long-Term Debt
A28: Total Liabilities
A29: Equity
A31: CASH FLOW STATEMENT
A32: Line Item | B32: Year 1 | C32: Year 2 | D32: Year 3 | E32: Year 4 | F32: Year 5
A33: Net Income
A34: Depreciation
A35: Working Capital Changes
A36: Capex
A37: Free Cash Flow

Sheet Fin_Inputs_Entity3
A1: ENTITY 3 FINANCIAL INPUTS
A3: INCOME STATEMENT
A4: Line Item | B4: Year 1 | C4: Year 2 | D4: Year 3 | E4: Year 4 | F4: Year 5
A5: Revenue
A6: COGS
A7: Gross Profit
A8: Operating Expenses
A9: EBITDA
A10: Depreciation
A11: EBIT
A12: Interest
A13: Taxes
A14: Net Income
A16: BALANCE SHEET
A17: Line Item | B17: Year 1 | C17: Year 2 | D17: Year 3 | E17: Year 4 | F17: Year 5
A18: Cash
A19: AR
A20: Inventory
A21: Current Assets
A22: PP&E
A23: Total Assets
A24: AP
A25: Accrued Liabilities
A26: Short-Term Debt
A27: Long-Term Debt
A28: Total Liabilities
A29: Equity
A31: CASH FLOW STATEMENT
A32: Line Item | B32: Year 1 | C32: Year 2 | D32: Year 3 | E32: Year 4 | F32: Year 5
A33: Net Income
A34: Depreciation
A35: Working Capital Changes
A36: Capex
A37: Free Cash Flow

Sheet Adjustments
A1: EBITDA ADJUSTMENTS
A3: SECTION 1: OWNER ADJUSTMENTS
A4: Adjustment Item | B4: Amount | C4: Notes
A5: Owner Salary Normalization
A6: Related Party Transactions
A7: Discretionary Expenses
A8: Subtotal Owner Adjustments | B8: =SUM(B5:B7) -> 0
A10: SECTION 2: NON RECURRING ITEMS
A11: Adjustment Item | B11: Amount | C11: Notes
A12: One Time Legal Fees
A13: Asset Write Offs
A14: Extraordinary Gains/Losses
A15: Subtotal Non Recurring | B15: =SUM(B12:B14) -> 0
A17: SECTION 3: NORMALIZED EBITDA
A18: Item | B18: Amount | C18: Source
A19: EBITDA (from Fin_Inputs) | B19: =Fin_Inputs_Entity1!F9 -> 0 | C19: Fin_Inputs_Entity1!F9
A20: Total Adjustments | B20: =B8+B15 -> 0 | C20: Sum of all adjustments
A21: Normalized EBITDA | B21: =B19+B20 -> 0 | C21: Normalized EBITDA = EBITDA + Total Adjustments

Sheet KPIs
A1: KEY PERFORMANCE INDICATORS
A3: KPI | B3: Formula | C3: Value | D3: Description
A4: Revenue CAGR | B4: {=(Year5/Year1)^(1/4)-1} -> #NAME? | C4: =IF(OR(Fin_Inputs_Entity1!B5=0,Fin_Inputs_Entity1!F5=0),"",(Fin_Inputs_Entity1!F5/Fin_Inputs_Entity1!B5)^(1/4)-1) | D4: 5-Year Compound Annual Growth Rate
A5: Gross Margin | B5: {=Gross Profit / Revenue} -> #NAME? | C5: =IF(Fin_Inputs_Entity1!F5=0,"",Fin_Inputs_Entity1!F7/Fin_Inputs_Entity1!F5) | D5: Profitability after COGS
A6: EBITDA Margin | B6: {=EBITDA / Revenue} -> #NAME? | C6: =IF(Fin_Inputs_Entity1!F5=0,"",Fin_Inputs_Entity1!F9/Fin_Inputs_Entity1!F5) | D6: Operating profitability
A7: Net Margin | B7: {=Net Income / Revenue} -> #NAME? | C7: =IF(Fin_Inputs_Entity1!F5=0,"",Fin_Inputs_Entity1!F14/Fin_Inputs_Entity1!F5) | D7: Bottom line profitability
A8: Working Capital Ratio | B8: {=(Current Assets-AP-Accrued Liabilities) / Revenue} -> #NAME? | C8: =IF(Fin_Inputs_Entity1!F5=0,"",(Fin_Inputs_Entity1!F21-Fin_Inputs_Entity1!F24-Fin_Inputs_Entity1!F25)/Fin_Inputs_Entity1!F5) | D8: WC as % of Revenue
A9: Current Ratio | B9: {=Current Assets / (AP + Accrued Liabilities + Short-Term Debt)} -> #NAME? | C9: =IF((Fin_Inputs_Entity1!F24+Fin_Inputs_Entity1!F25+Fin_Inputs_Entity1!F26)=0,"",Fin_Inputs_Entity1!F21/(Fin_Inputs_Entity1!F24+Fin_Inputs_Entity1!F25+Fin_Inputs_Entity1!F26)) | D9: Short-term liquidity
A10: Quick Ratio | B10: {=(Current Assets-Inventory) / (AP + Accrued Liabilities + Short-Term Debt)} -> #NAME? | C10: =IF((Fin_Inputs_Entity1!F24+Fin_Inputs_Entity1!F25+Fin_Inputs_Entity1!F26)=0,"",(Fin_Inputs_Entity1!F21-Fin_Inputs_Entity1!F20)/(Fin_Inputs_Entity1!F24+Fin_Inputs_Entity1!F25+Fin_Inputs_Entity1!F26)) | D10: Liquidity excl. inventory
A11: Debt/EBITDA | B11: {=Total Debt / EBITDA} -> #NAME? | C11: =IF(Fin_Inputs_Entity1!F9=0,"",(Fin_Inputs_Entity1!F26+Fin_Inputs_Entity1!F27)/Fin_Inputs_Entity1!F9) | D11: Leverage ratio
A12: Interest Coverage | B12: {=EBIT / Interest} -> #NAME? | C12: =IF(Fin_Inputs_Entity1!F12=0,"",Fin_Inputs_Entity1!F11/Fin_Inputs_Entity1!F12) | D12: Ability to service debt
A13: ROA | B13: {=Net Income / Total Assets} -> #NAME? | C13: =IF(Fin_Inputs_Entity1!F23=0,"",Fin_Inputs_Entity1!F14/Fin_Inputs_Entity1!F23) | D13: Return on Assets
A14: ROE | B14: {=Net Income / Equity} -> #NAME? | C14: =IF(Fin_Inputs_Entity1!F29=0,"",Fin_Inputs_Entity1!F14/Fin_Inputs_Entity1!F29) | D14: Return on Equity

Sheet Valuation
A1: VALUATION ANALYSIS
A3: SECTION A: WACC INPUTS
A4: Input | B4: Value | C4: Notes
A5: Risk Free Rate | B5: =Valuation_Entity1!B5 | C5: 10-Year Treasury
A6: Beta | B6: =Valuation_Entity1!B6 | C6: Industry/Company Beta
A7: Market Risk Premium | B7: =Valuation_Entity1!B7 | C7: Equity Risk Premium
A8: Cost of Debt | B8: =Valuation_Entity1!B8 | C8: Pre-tax cost
A9: Tax Rate | B9: =Valuation_Entity1!B9 | C9: Effective tax rate
A10: Debt Weight | B10: =Valuation_Entity1!B10 | C10: D/(D+E)
A11: Equity Weight | B11: =Valuation_Entity1!B11 | C11: E/(D+E)
A12: Cost of Equity | B12: =Valuation_Entity1!B12 | C12: Cost_of_Equity = Risk_Free_Rate + Beta * Market_Risk_Premium
A13: WACC | B13: =Valuation_Entity1!B13 | C13: Weighted Average
A15: SECTION B: DCF MODEL
A16: Item | B16: Year 1 | C16: Year 2 | D16: Year 3 | E16: Year 4 | F16: Year 5 | G16: Terminal
A17: Forecasted FCF | B17: =Valuation_Entity1!B18 | C17: =Valuation_Entity1!C18 | D17: =Valuation_Entity1!D18 | E17: =Valuation_Entity1!E18 | F17: =Valuation_Entity1!F18
A18: Terminal Growth Rate | B18: =Valuation_Entity1!B19 -> 0.02
A19: Terminal Value | G19: =Valuation_Entity1!G19
A20: Discount Factor | B20: =Valuation_Entity1!B20 | C20: =Valuation_Entity1!C20 | D20: =Valuation_Entity1!D20 | E20: =Valuation_Entity1!E20 | F20: =Valuation_Entity1!F20 | G20: =Valuation_Entity1!G20
A21: PV of Cash Flows | B21: =Valuation_Entity1!B21 | C21: =Valuation_Entity1!C21 | D21: =Valuation_Entity1!D21 | E21: =Valuation_Entity1!E21 | F21: =Valuation_Entity1!F21 | G21: =Valuation_Entity1!G21
A23: DCF Enterprise Value | B23: =Valuation_Entity1!B22
A25: SECTION C: MARKET MULTIPLES
A26: Multiple | B26: Multiple Value | C26: Metric | D26: Implied EV
A27: EV/EBITDA | B27: =Valuation_Entity1!B27 -> 6 | C27: =Valuation_Entity1!C27 | D27: =Valuation_Entity1!D27
A28: EV/Revenue | B28: =Valuation_Entity1!B28 -> 1.5 | C28: =Valuation_Entity1!C28 | D28: =Valuation_Entity1!D28
A29: P/E | B29: =Valuation_Entity1!B29 -> 10 | C29: =Valuation_Entity1!C29 | D29: =Valuation_Entity1!D29
A30: Average Multiples Value | D30: =Valuation_Entity1!B30
A32: SECTION D: FINAL VALUATION
A33: Valuation Method | B33: Value | C33: Weight
A34: DCF Value | B34: =Valuation_Entity1!B34 | C34: 0.5
A35: Market Multiples Value | B35: =Valuation_Entity1!B35 | C35: 0.5
A36: Final Valuation | B36: =Valuation_Entity1!B37

Sheet Model_3Statement
A1: 3-STATEMENT FINANCIAL MODEL
A3: REVENUE MODEL
A4: Item | B4: Historical | C4: Year 1 | D4: Year 2 | E4: Year 3 | F4: Year 4 | G4: Year 5
A5: Base Revenue | B5: =Fin_Inputs_Entity1!B5 -> 0
A6: Growth Rate
A7: Projected Revenue | B7: =IF(B5>0,B5*(1+B6),0) -> 0 | C7: =IF(B7>0,B7*(1+C6),0) -> 0 | D7: =IF(C7>0,C7*(1+D6),0) -> 0 | E7: =IF(D7>0,D7*(1+E6),0) -> 0 | F7: =IF(E7>0,E7*(1+F6),0) -> 0 | G7: =IF(F7>0,F7*(1+G6),0) -> 0
A9: COGS MODEL
A10: Item | B10: Historical | C10: Year 1 | D10: Year 2 | E10: Year 3 | F10: Year 4 | G10: Year 5
A11: COGS % of Revenue
A12: Projected COGS | B12: =B7*B11 -> 0 | C12: =C7*C11 -> 0 | D12: =D7*D11 -> 0 | E12: =E7*E11 -> 0 | F12: =F7*F11 -> 0 | G12: =G7*G11 -> 0
A13: Gross Profit | B13: =B7-B12 -> 0 | C13: =C7-C12 -> 0 | D13: =D7-D12 -> 0 | E13: =E7-E12 -> 0 | F13: =F7-F12 -> 0 | G13: =G7-G12 -> 0
A15: OPERATING EXPENSE MODEL
A16: Item | B16: Historical | C16: Year 1 | D16: Year 2 | E16: Year 3 | F16: Year 4 | G16: Year 5
A17: OpEx % of Revenue
A18: Projected OpEx | B18: =B7*B17 -> 0 | C18: =C7*C17 -> 0 | D18: =D7*D17 -> 0 | E18: =E7*E17 -> 0 | F18: =F7*F17 -> 0 | G18: =G7*G17 -> 0
A19: EBITDA | B19: =B13-B18 -> 0 | C19: =C13-C18 -> 0 | D19: =D13-D18 -> 0 | E19: =E13-E18 -> 0 | F19: =F13-F18 -> 0 | G19: =G13-G18 -> 0
A21: WORKING CAPITAL SCHEDULE
A22: Item | B22: Historical | C22: Year 1 | D22: Year 2 | E22: Year 3 | F22: Year 4 | G22: Year 5
A23: AR Days
A24: Inventory Days
A25: AP Days
A26: Accounts Receivable | B26: =IFERROR(B7*B23/365,0) -> 0 | C26: =IFERROR(C7*C23/365,0) -> 0 | D26: =IFERROR(D7*D23/365,0) -> 0 | E26: =IFERROR(E7*E23/365,0) -> 0 | F26: =IFERROR(F7*F23/365,0) -> 0 | G26: =IFERROR(G7*G23/365,0) -> 0
A27: Inventory | B27: =IFERROR(B12*B24/365,0) -> 0 | C27: =IFERROR(C12*C24/365,0) -> 0 | D27: =IFERROR(D12*D24/365,0) -> 0 | E27: =IFERROR(E12*E24/365,0) -> 0 | F27: =IFERROR(F12*F24/365,0) -> 0 | G27: =IFERROR(G12*G24/365,0) -> 0
A28: Accounts Payable | B28: =IFERROR(B12*B25/365,0) -> 0 | C28: =IFERROR(C12*C25/365,0) -> 0 | D28: =IFERROR(D12*D25/365,0) -> 0 | E28: =IFERROR(E12*E25/365,0) -> 0 | F28: =IFERROR(F12*F25/365,0) -> 0 | G28: =IFERROR(G12*G25/365,0) -> 0
A29: Net Working Capital | B29: =B26+B27-B28 -> 0 | C29: =C26+C27-C28 -> 0 | D29: =D26+D27-D28 -> 0 | E29: =E26+E27-E28 -> 0 | F29: =F26+F27-F28 -> 0 | G29: =G26+G27-G28 -> 0
A30: Change in NWC | C30: =C29-B29 -> 0 | D30: =D29-C29 -> 0 | E30: =E29-D29 -> 0 | F30: =F29-E29 -> 0 | G30: =G29-F29 -> 0
A32: CAPEX SCHEDULE
A33: Item | B33: Historical | C33: Year 1 | D33: Year 2 | E33: Year 3 | F33: Year 4 | G33: Year 5
A34: Capex % of Revenue
A35: Capital Expenditures | B35: =B7*B34 -> 0 | C35: =C7*C34 -> 0 | D35: =D7*D34 -> 0 | E35: =E7*E34 -> 0 | F35: =F7*F34 -> 0 | G35: =G7*G34 -> 0
A37: DEPRECIATION SCHEDULE
A38: Item | B38: Historical | C38: Year 1 | D38: Year 2 | E38: Year 3 | F38: Year 4 | G38: Year 5
A39: D&A % of Revenue
A40: Depreciation | B40: =B7*B39 -> 0 | C40: =C7*C39 -> 0 | D40: =D7*D39 -> 0 | E40: =E7*E39 -> 0 | F40: =F7*F39 -> 0 | G40: =G7*G39 -> 0
A41: EBIT | B41: =B19-B40 -> 0 | C41: =C19-C40 -> 0 | D41: =D19-D40 -> 0 | E41: =E19-E40 -> 0 | F41: =F19-F40 -> 0 | G41: =G19-G40 -> 0
A43: DEBT SCHEDULE
A44: Item | B44: Historical | C44: Year 1 | D44: Year 2 | E44: Year 3 | F44: Year 4 | G44: Year 5
A45: Beginning Debt | C45: =B48 -> 0 | D45: =C48 -> 0 | E45: =D48 -> 0 | F45: =E48 -> 0 | G45: =F48 -> 0
A46: New Borrowings
A47: Repayments
A48: Ending Debt | B48: =B45+B46-B47 -> 0 | C48: =C45+C46-C47 -> 0 | D48: =D45+D46-D47 -> 0 | E48: =E45+E46-E47 -> 0 | F48: =F45+F46-F47 -> 0 | G48: =G45+G46-G47 -> 0
A49: Interest Rate
A50: Interest Expense | B50: =IFERROR((B45+B48)/2*B49,0) -> 0 | C50: =IFERROR((C45+C48)/2*C49,0) -> 0 | D50: =IFERROR((D45+D48)/2*D49,0) -> 0 | E50: =IFERROR((E45+E48)/2*E49,0) -> 0 | F50: =IFERROR((F45+F48)/2*F49,0) -> 0 | G50: =IFERROR((G45+G48)/2*G49,0) -> 0
A52: FREE CASH FLOW SCHEDULE
A53: Item | B53: Historical | C53: Year 1 | D53: Year 2 | E53: Year 3 | F53: Year 4 | G53: Year 5
A54: EBIT | B54: =B41 -> 0 | C54: =C41 -> 0 | D54: =D41 -> 0 | E54: =E41 -> 0 | F54: =F41 -> 0 | G54: =G41 -> 0
A55: Tax Rate
A56: NOPAT | B56: =B54*(1-B55) -> 0 | C56: =C54*(1-C55) -> 0 | D56: =D54*(1-D55) -> 0 | E56: =E54*(1-E55) -> 0 | F56: =F54*(1-F55) -> 0 | G56: =G54*(1-G55) -> 0
A57: {=+ Depreciation} -> #NAME? | B57: =B40 -> 0 | C57: =C40 -> 0 | D57: =D40 -> 0 | E57: =E40 -> 0 | F57: =F40 -> 0 | G57: =G40 -> 0
A58: {=- Change in NWC} -> #NAME? | B58: =0 -> 0 | C58: =C30 -> 0 | D58: =D30 -> 0 | E58: =E30 -> 0 | F58: =F30 -> 0 | G58: =G30 -> 0
A59: {=- Capex} -> #NAME? | B59: =B35 -> 0 | C59: =C35 -> 0 | D59: =D35 -> 0 | E59: =E35 -> 0 | F59: =F35 -> 0 | G59: =G35 -> 0
A60: Free Cash Flow | B60: =B56+B57-B58-B59 -> 0 | C60: =C56+C57-C58-C59 -> 0 | D60: =D56+D57-D58-D59 -> 0 | E60: =E56+E57-E58-E59 -> 0 | F60: =F56+F57-F58-F59 -> 0 | G60: =G56+G57-G58-G59 -> 0

Sheet Charts
A1: CHARTS & VISUALIZATIONS
A3: CHART DATA
A5: Revenue Growth | B5: Year 1 | C5: Year 2 | D5: Year 3 | E5: Year 4 | F5: Year 5
A6: Revenue | B6: =Fin_Inputs_Entity1!B5 -> 0 | C6: =Fin_Inputs_Entity1!C5 -> 0 | D6: =Fin_Inputs_Entity1!D5 -> 0 | E6: =Fin_Inputs_Entity1!E5 -> 0 | F6: =Fin_Inputs_Entity1!F5 -> 0
A7: YoY Growth % | C7: =IFERROR((C6-B6)/B6,0) -> 0 | D7: =IFERROR((D6-C6)/C6,0) -> 0 | E7: =IFERROR((E6-D6)/D6,0) -> 0 | F7: =IFERROR((F6-E6)/E6,0) -> 0
A9: EBITDA Margin | B9: Year 1 | C9: Year 2 | D9: Year 3 | E9: Year 4 | F9: Year 5
A10: EBITDA | B10: =Fin_Inputs_Entity1!B9 -> 0 | C10: =Fin_Inputs_Entity1!C9 -> 0 | D10: =Fin_Inputs_Entity1!D9 -> 0 | E10: =Fin_Inputs_Entity1!E9 -> 0 | F10: =Fin_Inputs_Entity1!F9 -> 0
A11: Margin % | B11: =IFERROR(B10/B6,0) -> 0 | C11: =IFERROR(C10/C6,0) -> 0 | D11: =IFERROR(D10/D6,0) -> 0 | E11: =IFERROR(E10/E6,0) -> 0 | F11: =IFERROR(F10/F6,0) -> 0
A13: Cash Flow Trends | B13: Year 1 | C13: Year 2 | D13: Year 3 | E13: Year 4 | F13: Year 5
A14: Free Cash Flow | B14: =Fin_Inputs_Entity1!B37 -> 0 | C14: =Fin_Inputs_Entity1!C37 -> 0 | D14: =Fin_Inputs_Entity1!D37 -> 0 | E14: =Fin_Inputs_Entity1!E37 -> 0 | F14: =Fin_Inputs_Entity1!F37 -> 0
A16: Working Capital | B16: Year 1 | C16: Year 2 | D16: Year 3 | E16: Year 4 | F16: Year 5
A17: Current Assets | B17: =Fin_Inputs_Entity1!B21 -> 0 | C17: =Fin_Inputs_Entity1!C21 -> 0 | D17: =Fin_Inputs_Entity1!D21 -> 0 | E17: =Fin_Inputs_Entity1!E21 -> 0 | F17: =Fin_Inputs_Entity1!F21 -> 0
A18: Current Liabilities | B18: =SUM(Fin_Inputs_Entity1!B24:B26) -> 0 | C18: =SUM(Fin_Inputs_Entity1!C24:C26) -> 0 | D18: =SUM(Fin_Inputs_Entity1!D24:D26) -> 0 | E18: =SUM(Fin_Inputs_Entity1!E24:E26) -> 0 | F18: =SUM(Fin_Inputs_Entity1!F24:F26) -> 0
A19: Net WC | B19: =B17-B18 -> 0 | C19: =C17-C18 -> 0 | D19: =D17-D18 -> 0 | E19: =E17-E18 -> 0 | F19: =F17-F18 -> 0
A21: Valuation Summary | B21: DCF | C21: Multiples | D21: Final
A22: Value | B22: =NR_DCF_Value | C22: =NR_Multiples_Value -> Valuation!D30 | D22: =NR_Final_Valuation
A24: Benchmark Comparison | B24: Client | C24: Industry | D24: Variance
A25: EBITDA Margin | B25: =KPIs!C6 | C25: =Benchmarking!C5 -> 0 | D25: =B25-C25 -> #VALUE!
A26: Net Margin | B26: =KPIs!C7 | C26: =Benchmarking!C6 -> 0 | D26: =B26-C26 -> #VALUE!
A27: Revenue Growth | B27: =KPIs!C4 | C27: =Benchmarking!C4 -> 0 | D27: =B27-C27 -> #VALUE!
A29: Note: Charts will be created using the data above. Select data ranges and insert charts as needed.

Sheet Benchmarking
A1: INDUSTRY BENCHMARKING
A3: Metric | B3: Client | C3: Industry Average | D3: Variance
A4: Revenue Growth | B4: =KPIs!C4 | D4: =IFERROR(B4-C4,0) -> 0
A5: EBITDA Margin | B5: =KPIs!C6 | D5: =IFERROR(B5-C5,0) -> 0
A6: Net Margin | B6: =KPIs!C7 | D6: =IFERROR(B6-C6,0) -> 0
A7: Leverage (Debt/EBITDA) | B7: =KPIs!C11 | D7: =IFERROR(B7-C7,0) -> 0
A8: Working Capital % | B8: =KPIs!C8 | D8: =IFERROR(B8-C8,0) -> 0
A10: Instructions: Enter industry average benchmarks in yellow cells (Column C).

Sheet Due_Diligence
A1: DUE DILIGENCE ANALYSIS
A3: REVENUE TESTING
A4: Test Item | B4: Expected | C4: Actual | D4: Variance | E4: Notes
A5: Revenue per Customer | D5: =IFERROR(C5-B5,0) -> 0
A6: Customer Count Verification | D6: =IFERROR(C6-B6,0) -> 0
A7: Contract Value Reconciliation | D7: =IFERROR(C7-B7,0) -> 0
A8: Revenue Recognition Review | D8: =IFERROR(C8-B8,0) -> 0
A10: EXPENSE TESTING
A11: Test Item | B11: Expected | C11: Actual | D11: Variance | E11: Notes
A12: Payroll Verification | D12: =IFERROR(C12-B12,0) -> 0
A13: Vendor Payment Analysis | D13: =IFERROR(C13-B13,0) -> 0
A14: Related Party Expenses | D14: =IFERROR(C14-B14,0) -> 0
A15: One-Time vs Recurring | D15: =IFERROR(C15-B15,0) -> 0
A17: VARIANCE ANALYSIS
A18: Item | B18: Prior Year | C18: Current Year | D18: Variance % | E18: Explanation
A19: Revenue | D19: =IFERROR((C19-B19)/B19,0) -> 0
A20: Gross Profit | D20: =IFERROR((C20-B20)/B20,0) -> 0
A21: EBITDA | D21: =IFERROR((C21-B21)/B21,0) -> 0
A22: Net Income | D22: =IFERROR((C22-B22)/B22,0) -> 0
A24: RED FLAG IDENTIFICATION
A25: Red Flag Item | B25: Severity | C25: Amount | D25: Status | E25: Resolution
A26: Customer Concentration
A27: Related Party Issues
A28: Revenue Quality Concerns
A29: Working Capital Anomalies
A30: Contingent Liabilities
A32: NORMALIZATION SUMMARY
A33: Adjustment | B33: Amount | C33: Recurring? | D33: Impact | E33: Documentation
A34: Reported EBITDA | B34: =Fin_Inputs_Entity1!F9 -> 0
A35: Owner Comp Adjustment | B35: =Adjustments!B5 -> 0
A36: Related Party Adjustment | B36: =Adjustments!B6 -> 0
A37: Non-Recurring Items | B37: =Adjustments!B15 -> 0
A38: Normalized EBITDA | B38: =NR_EBITDA_Normalized -> Adjustments!B21

Sheet Deal_Terms
A1: M&A / JV DEAL TERMS
A3: OWNERSHIP PERCENTAGES
A4: Party | B4: Ownership % | C4: Notes
A5: Buyer/Investor 1
A6: Buyer/Investor 2
A7: Seller/Existing Owner
A8: Management Pool
A9: Total | B9: =SUM(B5:B8) -> 0 | C9: Must equal 100%
A11: PURCHASE PRICE
A12: Component | B12: Amount | C12: Notes
A13: Base Purchase Price
A14: Working Capital Adjustment
A15: Debt Assumption
A16: Cash on Hand
A17: Total Enterprise Value | B17: =B13+B14+B15-B16 -> 0
A19: EARN OUT STRUCTURE
A20: Milestone | B20: Target | C20: Payout
A21: Year 1 Revenue Target
A22: Year 2 Revenue Target
A23: Year 1 EBITDA Target
A24: Year 2 EBITDA Target
A25: Total Potential Earn Out | C25: =SUM(C21:C24) -> 0
A27: CONTRIBUTION AMOUNTS
A28: Party | B28: Cash | C28: Assets/Services
A29: Party 1
A30: Party 2
A31: Party 3
A32: Total Contributions | B32: =SUM(B29:B31) -> 0 | C32: =SUM(C29:C31) -> 0
A34: SYNERGIES
A35: Synergy Type | B35: Annual Amount | C35: Notes
A36: Revenue Synergies
A37: Cost Synergies
A38: Operational Efficiencies
A39: Total Synergies | B39: =SUM(B36:B38) -> 0
A41: SPECIAL RIGHTS
A42: Right/Provision | B42: Holder | C42: Details
A43: Board Seats
A44: Veto Rights
A45: Tag-Along Rights
A46: Drag-Along Rights
A47: Anti-Dilution

Sheet Consolidation
A1: CONSOLIDATION - 10 ENTITIES
A3: Metric | B3: Entity 1 | C3: Entity 2 | D3: Entity 3 | E3: Entity 4 | F3: Entity 5 | G3: Entity 6 | H3: Entity 7 | I3: Entity 8 | J3: Entity 9 | K3: Entity 10 | L3: Combined Total
A4: Combined Revenue | B4: =IF(FX_Rate_Entity1="","",N(Fin_Inputs_Entity1!F5)*FX_Rate_Entity1*IF(Entity_Ownership!C4="",1,Entity_Ownership!C4)) | C4: =IF(FX_Rate_Entity2="","",N(Fin_Inputs_Entity2!F5)*FX_Rate_Entity2*IF(Entity_Ownership!C5="",1,Entity_Ownership!C5)) | D4: =IF(FX_Rate_Entity3="","",N(Fin_Inputs_Entity3!F5)*FX_Rate_Entity3*IF(Entity_Ownership!C6="",1,Entity_Ownership!C6)) | E4: =IF(FX_Rate_Entity4="","",N(Fin_Inputs_Entity4!F5)*FX_Rate_Entity4*IF(Entity_Ownership!C7="",1,Entity_Ownership!C7)) | F4: =IF(FX_Rate_Entity5="","",N(Fin_Inputs_Entity5!F5)*FX_Rate_Entity5*IF(Entity_Ownership!C8="",1,Entity_Ownership!C8)) | G4: =IF(FX_Rate_Entity6="","",N(Fin_Inputs_Entity6!F5)*FX_Rate_Entity6*IF(Entity_Ownership!C9="",1,Entity_Ownership!C9)) | H4: =IF(FX_Rate_Entity7="","",N(Fin_Inputs_Entity7!F5)*FX_Rate_Entity7*IF(Entity_Ownership!C10="",1,Entity_Ownership!C10)) | I4: =IF(FX_Rate_Entity8="","",N(Fin_Inputs_Entity8!F5)*FX_Rate_Entity8*IF(Entity_Ownership!C11="",1,Entity_Ownership!C11)) | J4: =IF(FX_Rate_Entity9="","",N(Fin_Inputs_Entity9!F5)*FX_Rate_Entity9*IF(Entity_Ownership!C12="",1,Entity_Ownership!C12)) | K4: =IF(FX_Rate_Entity10="","",N(Fin_Inputs_Entity10!F5)*FX_Rate_Entity10*IF(Entity_Ownership!C13="",1,Entity_Ownership!C13)) | L4: =SUM(B4:K4) -> 0
A5: Combined EBITDA | B5: =IF(FX_Rate_Entity1="","",N(Fin_Inputs_Entity1!F9)*FX_Rate_Entity1*IF(Entity_Ownership!C4="",1,Entity_Ownership!C4)) | C5: =IF(FX_Rate_Entity2="","",N(Fin_Inputs_Entity2!F9)*FX_Rate_Entity2*IF(Entity_Ownership!C5="",1,Entity_Ownership!C5)) | D5: =IF(FX_Rate_Entity3="","",N(Fin_Inputs_Entity3!F9)*FX_Rate_Entity3*IF(Entity_Ownership!C6="",1,Entity_Ownership!C6)) | E5: =IF(FX_Rate_Entity4="","",N(Fin_Inputs_Entity4!F9)*FX_Rate_Entity4*IF(Entity_Ownership!C7="",1,Entity_Ownership!C7)) | F5: =IF(FX_Rate_Entity5="","",N(Fin_Inputs_Entity5!F9)*FX_Rate_Entity5*IF(Entity_Ownership!C8="",1,Entity_Ownership!C8)) | G5: =IF(FX_Rate_Entity6="","",N(Fin_Inputs_Entity6!F9)*FX_Rate_Entity6*IF(Entity_Ownership!C9="",1,Entity_Ownership!C9)) | H5: =IF(FX_Rate_Entity7="","",N(Fin_Inputs_Entity7!F9)*FX_Rate_Entity7*IF(Entity_Ownership!C10="",1,Entity_Ownership!C10)) | I5: =IF(FX_Rate_Entity8="","",N(Fin_Inputs_Entity8!F9)*FX_Rate_Entity8*IF(Entity_Ownership!C11="",1,Entity_Ownership!C11)) | J5: =IF(FX_Rate_Entity9="","",N(Fin_Inputs_Entity9!F9)*FX_Rate_Entity9*IF(Entity_Ownership!C12="",1,Entity_Ownership!C12)) | K5: =IF(FX_Rate_Entity10="","",N(Fin_Inputs_Entity10!F9)*FX_Rate_Entity10*IF(Entity_Ownership!C13="",1,Entity_Ownership!C13)) | L5: =SUM(B5:K5) -> 0
A6: Combined Cash Flow | B6: =IF(FX_Rate_Entity1="","",N(Fin_Inputs_Entity1!F37)*FX_Rate_Entity1*IF(Entity_Ownership!C4="",1,Entity_Ownership!C4)) | C6: =IF(FX_Rate_Entity2="","",N(Fin_Inputs_Entity2!F37)*FX_Rate_Entity2*IF(Entity_Ownership!C5="",1,Entity_Ownership!C5)) | D6: =IF(FX_Rate_Entity3="","",N(Fin_Inputs_Entity3!F37)*FX_Rate_Entity3*IF(Entity_Ownership!C6="",1,Entity_Ownership!C6)) | E6: =IF(FX_Rate_Entity4="","",N(Fin_Inputs_Entity4!F37)*FX_Rate_Entity4*IF(Entity_Ownership!C7="",1,Entity_Ownership!C7)) | F6: =IF(FX_Rate_Entity5="","",N(Fin_Inputs_Entity5!F37)*FX_Rate_Entity5*IF(Entity_Ownership!C8="",1,Entity_Ownership!C8)) | G6: =IF(FX_Rate_Entity6="","",N(Fin_Inputs_Entity6!F37)*FX_Rate_Entity6*IF(Entity_Ownership!C9="",1,Entity_Ownership!C9)) | H6: =IF(FX_Rate_Entity7="","",N(Fin_Inputs_Entity7!F37)*FX_Rate_Entity7*IF(Entity_Ownership!C10="",1,Entity_Ownership!C10)) | I6: =IF(FX_Rate_Entity8="","",N(Fin_Inputs_Entity8!F37)*FX_Rate_Entity8*IF(Entity_Ownership!C11="",1,Entity_Ownership!C11)) | J6: =IF(FX_Rate_Entity9="","",N(Fin_Inputs_Entity9!F37)*FX_Rate_Entity9*IF(Entity_Ownership!C12="",1,Entity_Ownership!C12)) | K6: =IF(FX_Rate_Entity10="","",N(Fin_Inputs_Entity10!F37)*FX_Rate_Entity10*IF(Entity_Ownership!C13="",1,Entity_Ownership!C13)) | L6: =SUM(B6:K6) -> 0
A7: Combined Debt | B7: =IF(FX_Rate_Entity1="","",(N(Fin_Inputs_Entity1!F26)+N(Fin_Inputs_Entity1!F27))*FX_Rate_Entity1*IF(Entity_Ownership!C4="",1,Entity_Ownership!C4)) | C7: =IF(FX_Rate_Entity2="","",(N(Fin_Inputs_Entity2!F26)+N(Fin_Inputs_Entity2!F27))*FX_Rate_Entity2*IF(Entity_Ownership!C5="",1,Entity_Ownership!C5)) | D7: =IF(FX_Rate_Entity3="","",(N(Fin_Inputs_Entity3!F26)+N(Fin_Inputs_Entity3!F27))*FX_Rate_Entity3*IF(Entity_Ownership!C6="",1,Entity_Ownership!C6)) | E7: =IF(FX_Rate_Entity4="","",(N(Fin_Inputs_Entity4!F26)+N(Fin_Inputs_Entity4!F27))*FX_Rate_Entity4*IF(Entity_Ownership!C7="",1,Entity_Ownership!C7)) | F7: =IF(FX_Rate_Entity5="","",(N(Fin_Inputs_Entity5!F26)+N(Fin_Inputs_Entity5!F27))*FX_Rate_Entity5*IF(Entity_Ownership!C8="",1,Entity_Ownership!C8)) | G7: =IF(FX_Rate_Entity6="","",(N(Fin_Inputs_Entity6!F26)+N(Fin_Inputs_Entity6!F27))*FX_Rate_Entity6*IF(Entity_Ownership!C9="",1,Entity_Ownership!C9)) | H7: =IF(FX_Rate_Entity7="","",(N(Fin_Inputs_Entity7!F26)+N(Fin_Inputs_Entity7!F27))*FX_Rate_Entity7*IF(Entity_Ownership!C10="",1,Entity_Ownership!C10)) | I7: =IF(FX_Rate_Entity8="","",(N(Fin_Inputs_Entity8!F26)+N(Fin_Inputs_Entity8!F27))*FX_Rate_Entity8*IF(Entity_Ownership!C11="",1,Entity_Ownership!C11)) | J7: =IF(FX_Rate_Entity9="","",(N(Fin_Inputs_Entity9!F26)+N(Fin_Inputs_Entity9!F27))*FX_Rate_Entity9*IF(Entity_Ownership!C12="",1,Entity_Ownership!C12)) | K7: =IF(FX_Rate_Entity10="","",(N(Fin_Inputs_Entity10!F26)+N(Fin_Inputs_Entity10!F27))*FX_Rate_Entity10*IF(Entity_Ownership!C13="",1,Entity_Ownership!C13)) | L7: =SUM(B7:K7) -> 0
A8: Combined Working Capital | B8: =IF(FX_Rate_Entity1="","",(N(Fin_Inputs_Entity1!F21)-N(Fin_Inputs_Entity1!F24)-N(Fin_Inputs_Entity1!F25))*FX_Rate_Entity1*IF(Entity_Ownership!C4="",1,Entity_Ownership!C4)) | C8: =IF(FX_Rate_Entity2="","",(N(Fin_Inputs_Entity2!F21)-N(Fin_Inputs_Entity2!F24)-N(Fin_Inputs_Entity2!F25))*FX_Rate_Entity2*IF(Entity_Ownership!C5="",1,Entity_Ownership!C5)) | D8: =IF(FX_Rate_Entity3="","",(N(Fin_Inputs_Entity3!F21)-N(Fin_Inputs_Entity3!F24)-N(Fin_Inputs_Entity3!F25))*FX_Rate_Entity3*IF(Entity_Ownership!C6="",1,Entity_Ownership!C6)) | E8: =IF(FX_Rate_Entity4="","",(N(Fin_Inputs_Entity4!F21)-N(Fin_Inputs_Entity4!F24)-N(Fin_Inputs_Entity4!F25))*FX_Rate_Entity4*IF(Entity_Ownership!C7="",1,Entity_Ownership!C7)) | F8: =IF(FX_Rate_Entity5="","",(N(Fin_Inputs_Entity5!F21)-N(Fin_Inputs_Entity5!F24)-N(Fin_Inputs_Entity5!F25))*FX_Rate_Entity5*IF(Entity_Ownership!C8="",1,Entity_Ownership!C8)) | G8: =IF(FX_Rate_Entity6="","",(N(Fin_Inputs_Entity6!F21)-N(Fin_Inputs_Entity6!F24)-N(Fin_Inputs_Entity6!F25))*FX_Rate_Entity6*IF(Entity_Ownership!C9="",1,Entity_Ownership!C9)) | H8: =IF(FX_Rate_Entity7="","",(N(Fin_Inputs_Entity7!F21)-N(Fin_Inputs_Entity7!F24)-N(Fin_Inputs_Entity7!F25))*FX_Rate_Entity7*IF(Entity_Ownership!C10="",1,Entity_Ownership!C10)) | I8: =IF(FX_Rate_Entity8="","",(N(Fin_Inputs_Entity8!F21)-N(Fin_Inputs_Entity8!F24)-N(Fin_Inputs_Entity8!F25))*FX_Rate_Entity8*IF(Entity_Ownership!C11="",1,Entity_Ownership!C11)) | J8: =IF(FX_Rate_Entity9="","",(N(Fin_Inputs_Entity9!F21)-N(Fin_Inputs_Entity9!F24)-N(Fin_Inputs_Entity9!F25))*FX_Rate_Entity9*IF(Entity_Ownership!C12="",1,Entity_Ownership!C12)) | K8: =IF(FX_Rate_Entity10="","",(N(Fin_Inputs_Entity10!F21)-N(Fin_Inputs_Entity10!F24)-N(Fin_Inputs_Entity10!F25))*FX_Rate_Entity10*IF(Entity_Ownership!C13="",1,Entity_Ownership!C13)) | L8: =SUM(B8:K8) -> 0
A9: Combined Valuation | B9: =Valuation_Entity1!B37 | C9: =Valuation_Entity2!B37 | D9: =Valuation_Entity3!B37 | E9: =Valuation_Entity4!B37 | F9: =Valuation_Entity5!B37 | G9: =Valuation_Entity6!B37 | H9: =Valuation_Entity7!B37 | I9: =Valuation_Entity8!B37 | J9: =Valuation_Entity9!B37 | K9: =Valuation_Entity10!B37 | L9: =SUM(B9:K9) -> 0
A10: Combined Loan Readiness Metrics | B10: =Loan_Readiness!D11 | C10: =Loan_Readiness!D12 | D10: =Loan_Readiness!D13 | E10: =Loan_Readiness!D14 | F10: =Loan_Readiness!D15 | G10: =Loan_Readiness!D16 | H10: =Loan_Readiness!D17 | I10: =Loan_Readiness!D18 | J10: =Loan_Readiness!D19 | K10: =Loan_Readiness!D20 | L10: =IF(COUNT(B10:K10)=0,"",AVERAGE(B10:K10))
A11: Warning | B11: =IF(COUNT(Fin_Inputs_Entity1!B5:F37)=0,"WARNING: Missing Financial Data",IF(OR(FX_Conversion!B4="",Entity_Ownership!F4="",Entity_Ownership!G4=""),"WARNING: Missing Setup Data","")) -> WARNING: Missing Financial Data | C11: =IF(COUNT(Fin_Inputs_Entity2!B5:F37)=0,"WARNING: Missing Financial Data",IF(OR(FX_Conversion!B5="",Entity_Ownership!F5="",Entity_Ownership!G5=""),"WARNING: Missing Setup Data","")) -> WARNING: Missing Financial Data | D11: =IF(COUNT(Fin_Inputs_Entity3!B5:F37)=0,"WARNING: Missing Financial Data",IF(OR(FX_Conversion!B6="",Entity_Ownership!F6="",Entity_Ownership!G6=""),"WARNING: Missing Setup Data","")) -> WARNING: Missing Financial Data | E11: =IF(COUNT(Fin_Inputs_Entity4!B5:F37)=0,"WARNING: Missing Financial Data",IF(OR(FX_Conversion!B7="",Entity_Ownership!F7="",Entity_Ownership!G7=""),"WARNING: Missing Setup Data","")) -> WARNING: Missing Financial Data | F11: =IF(COUNT(Fin_Inputs_Entity5!B5:F37)=0,"WARNING: Missing Financial Data",IF(OR(FX_Conversion!B8="",Entity_Ownership!F8="",Entity_Ownership!G8=""),"WARNING: Missing Setup Data","")) -> WARNING: Missing Financial Data | G11: =IF(COUNT(Fin_Inputs_Entity6!B5:F37)=0,"WARNING: Missing Financial Data",IF(OR(FX_Conversion!B9="",Entity_Ownership!F9="",Entity_Ownership!G9=""),"WARNING: Missing Setup Data","")) -> WARNING: Missing Financial Data | H11: =IF(COUNT(Fin_Inputs_Entity7!B5:F37)=0,"WARNING: Missing Financial Data",IF(OR(FX_Conversion!B10="",Entity_Ownership!F10="",Entity_Ownership!G10=""),"WARNING: Missing Setup Data","")) -> WARNING: Missing Financial Data | I11: =IF(COUNT(Fin_Inputs_Entity8!B5:F37)=0,"WARNING: Missing Financial Data",IF(OR(FX_Conversion!B11="",Entity_Ownership!F11="",Entity_Ownership!G11=""),"WARNING: Missing Setup Data","")) -> WARNING: Missing Financial Data | J11: =IF(COUNT(Fin_Inputs_Entity9!B5:F37)=0,"WARNING: Missing Financial Data",IF(OR(FX_Conversion!B12="",Entity_Ownership!F12="",Entity_Ownership!G12=""),"WARNING: Missing Setup Data","")) -> WARNING: Missing Financial Data | K11: =IF(COUNT(Fin_Inputs_Entity10!B5:F37)=0,"WARNING: Missing Financial Data",IF(OR(FX_Conversion!B13="",Entity_Ownership!F13="",Entity_Ownership!G13=""),"WARNING: Missing Setup Data","")) -> WARNING: Missing Financial Data | L11: =IF(COUNTIF(B11:K11,"WARNING*")>0,"WARNING: Missing Data in One or More Entities","") -> WARNING: Missing Data in One or More Entities
A13: FCF Contribution Analysis
A14: Metric / Year | B14: Entity 1 | C14: Entity 2 | D14: Entity 3 | E14: Entity 4 | F14: Entity 5 | G14: Entity 6 | H14: Entity 7 | I14: Entity 8 | J14: Entity 9 | K14: Entity 10 | L14: Combined
A15: FCF Year 1 | B15: =IF(Valuation_Entity1!B18="","",Valuation_Entity1!B18*IF(Entity_Ownership!C4="",1,Entity_Ownership!C4)) | C15: =IF(Valuation_Entity2!B18="","",Valuation_Entity2!B18*IF(Entity_Ownership!C5="",1,Entity_Ownership!C5)) | D15: =IF(Valuation_Entity3!B18="","",Valuation_Entity3!B18*IF(Entity_Ownership!C6="",1,Entity_Ownership!C6)) | E15: =IF(Valuation_Entity4!B18="","",Valuation_Entity4!B18*IF(Entity_Ownership!C7="",1,Entity_Ownership!C7)) | F15: =IF(Valuation_Entity5!B18="","",Valuation_Entity5!B18*IF(Entity_Ownership!C8="",1,Entity_Ownership!C8)) | G15: =IF(Valuation_Entity6!B18="","",Valuation_Entity6!B18*IF(Entity_Ownership!C9="",1,Entity_Ownership!C9)) | H15: =IF(Valuation_Entity7!B18="","",Valuation_Entity7!B18*IF(Entity_Ownership!C10="",1,Entity_Ownership!C10)) | I15: =IF(Valuation_Entity8!B18="","",Valuation_Entity8!B18*IF(Entity_Ownership!C11="",1,Entity_Ownership!C11)) | J15: =IF(Valuation_Entity9!B18="","",Valuation_Entity9!B18*IF(Entity_Ownership!C12="",1,Entity_Ownership!C12)) | K15: =IF(Valuation_Entity10!B18="","",Valuation_Entity10!B18*IF(Entity_Ownership!C13="",1,Entity_Ownership!C13)) | L15: =SUM(B15:K15) -> 0
A16: FCF Year 2 | B16: =IF(Valuation_Entity1!C18="","",Valuation_Entity1!C18*IF(Entity_Ownership!C4="",1,Entity_Ownership!C4)) | C16: =IF(Valuation_Entity2!C18="","",Valuation_Entity2!C18*IF(Entity_Ownership!C5="",1,Entity_Ownership!C5)) | D16: =IF(Valuation_Entity3!C18="","",Valuation_Entity3!C18*IF(Entity_Ownership!C6="",1,Entity_Ownership!C6)) | E16: =IF(Valuation_Entity4!C18="","",Valuation_Entity4!C18*IF(Entity_Ownership!C7="",1,Entity_Ownership!C7)) | F16: =IF(Valuation_Entity5!C18="","",Valuation_Entity5!C18*IF(Entity_Ownership!C8="",1,Entity_Ownership!C8)) | G16: =IF(Valuation_Entity6!C18="","",Valuation_Entity6!C18*IF(Entity_Ownership!C9="",1,Entity_Ownership!C9)) | H16: =IF(Valuation_Entity7!C18="","",Valuation_Entity7!C18*IF(Entity_Ownership!C10="",1,Entity_Ownership!C10)) | I16: =IF(Valuation_Entity8!C18="","",Valuation_Entity8!C18*IF(Entity_Ownership!C11="",1,Entity_Ownership!C11)) | J16: =IF(Valuation_Entity9!C18="","",Valuation_Entity9!C18*IF(Entity_Ownership!C12="",1,Entity_Ownership!C12)) | K16: =IF(Valuation_Entity10!C18="","",Valuation_Entity10!C18*IF(Entity_Ownership!C13="",1,Entity_Ownership!C13)) | L16: =SUM(B16:K16) -> 0
A17: FCF Year 3 | B17: =IF(Valuation_Entity1!D18="","",Valuation_Entity1!D18*IF(Entity_Ownership!C4="",1,Entity_Ownership!C4)) | C17: =IF(Valuation_Entity2!D18="","",Valuation_Entity2!D18*IF(Entity_Ownership!C5="",1,Entity_Ownership!C5)) | D17: =IF(Valuation_Entity3!D18="","",Valuation_Entity3!D18*IF(Entity_Ownership!C6="",1,Entity_Ownership!C6)) | E17: =IF(Valuation_Entity4!D18="","",Valuation_Entity4!D18*IF(Entity_Ownership!C7="",1,Entity_Ownership!C7)) | F17: =IF(Valuation_Entity5!D18="","",Valuation_Entity5!D18*IF(Entity_Ownership!C8="",1,Entity_Ownership!C8)) | G17: =IF(Valuation_Entity6!D18="","",Valuation_Entity6!D18*IF(Entity_Ownership!C9="",1,Entity_Ownership!C9)) | H17: =IF(Valuation_Entity7!D18="","",Valuation_Entity7!D18*IF(Entity_Ownership!C10="",1,Entity_Ownership!C10)) | I17: =IF(Valuation_Entity8!D18="","",Valuation_Entity8!D18*IF(Entity_Ownership!C11="",1,Entity_Ownership!C11)) | J17: =IF(Valuation_Entity9!D18="","",Valuation_Entity9!D18*IF(Entity_Ownership!C12="",1,Entity_Ownership!C12)) | K17: =IF(Valuation_Entity10!D18="","",Valuation_Entity10!D18*IF(Entity_Ownership!C13="",1,Entity_Ownership!C13)) | L17: =SUM(B17:K17) -> 0
A18: FCF Year 4 | B18: =IF(Valuation_Entity1!E18="","",Valuation_Entity1!E18*IF(Entity_Ownership!C4="",1,Entity_Ownership!C4)) | C18: =IF(Valuation_Entity2!E18="","",Valuation_Entity2!E18*IF(Entity_Ownership!C5="",1,Entity_Ownership!C5)) | D18: =IF(Valuation_Entity3!E18="","",Valuation_Entity3!E18*IF(Entity_Ownership!C6="",1,Entity_Ownership!C6)) | E18: =IF(Valuation_Entity4!E18="","",Valuation_Entity4!E18*IF(Entity_Ownership!C7="",1,Entity_Ownership!C7)) | F18: =IF(Valuation_Entity5!E18="","",Valuation_Entity5!E18*IF(Entity_Ownership!C8="",1,Entity_Ownership!C8)) | G18: =IF(Valuation_Entity6!E18="","",Valuation_Entity6!E18*IF(Entity_Ownership!C9="",1,Entity_Ownership!C9)) | H18: =IF(Valuation_Entity7!E18="","",Valuation_Entity7!E18*IF(Entity_Ownership!C10="",1,Entity_Ownership!C10)) | I18: =IF(Valuation_Entity8!E18="","",Valuation_Entity8!E18*IF(Entity_Ownership!C11="",1,Entity_Ownership!C11)) | J18: =IF(Valuation_Entity9!E18="","",Valuation_Entity9!E18*IF(Entity_Ownership!C12="",1,Entity_Ownership!C12)) | K18: =IF(Valuation_Entity10!E18="","",Valuation_Entity10!E18*IF(Entity_Ownership!C13="",1,Entity_Ownership!C13)) | L18: =SUM(B18:K18) -> 0
A19: FCF Year 5 | B19: =IF(Valuation_Entity1!F18="","",Valuation_Entity1!F18*IF(Entity_Ownership!C4="",1,Entity_Ownership!C4)) | C19: =IF(Valuation_Entity2!F18="","",Valuation_Entity2!F18*IF(Entity_Ownership!C5="",1,Entity_Ownership!C5)) | D19: =IF(Valuation_Entity3!F18="","",Valuation_Entity3!F18*IF(Entity_Ownership!C6="",1,Entity_Ownership!C6)) | E19: =IF(Valuation_Entity4!F18="","",Valuation_Entity4!F18*IF(Entity_Ownership!C7="",1,Entity_Ownership!C7)) | F19: =IF(Valuation_Entity5!F18="","",Valuation_Entity5!F18*IF(Entity_Ownership!C8="",1,Entity_Ownership!C8)) | G19: =IF(Valuation_Entity6!F18="","",Valuation_Entity6!F18*IF(Entity_Ownership!C9="",1,Entity_Ownership!C9)) | H19: =IF(Valuation_Entity7!F18="","",Valuation_Entity7!F18*IF(Entity_Ownership!C10="",1,Entity_Ownership!C10)) | I19: =IF(Valuation_Entity8!F18="","",Valuation_Entity8!F18*IF(Entity_Ownership!C11="",1,Entity_Ownership!C11)) | J19: =IF(Valuation_Entity9!F18="","",Valuation_Entity9!F18*IF(Entity_Ownership!C12="",1,Entity_Ownership!C12)) | K19: =IF(Valuation_Entity10!F18="","",Valuation_Entity10!F18*IF(Entity_Ownership!C13="",1,Entity_Ownership!C13)) | L19: =SUM(B19:K19) -> 0
A20: Valuation Contribution Analysis
A21: Entity | B21: Value | C21: Contribution %
A22: Entity 1 | B22: =Valuation_Entity1!B37 | C22: =IF(OR($L$9="",$L$9=0,B22=""),"",B22/$L$9)
A23: Entity 2 | B23: =Valuation_Entity2!B37 | C23: =IF(OR($L$9="",$L$9=0,B23=""),"",B23/$L$9)
A24: Entity 3 | B24: =Valuation_Entity3!B37 | C24: =IF(OR($L$9="",$L$9=0,B24=""),"",B24/$L$9)
A25: Entity 4 | B25: =Valuation_Entity4!B37 | C25: =IF(OR($L$9="",$L$9=0,B25=""),"",B25/$L$9)
A26: Entity 5 | B26: =Valuation_Entity5!B37 | C26: =IF(OR($L$9="",$L$9=0,B26=""),"",B26/$L$9)
A27: Entity 6 | B27: =Valuation_Entity6!B37 | C27: =IF(OR($L$9="",$L$9=0,B27=""),"",B27/$L$9)
A28: Entity 7 | B28: =Valuation_Entity7!B37 | C28: =IF(OR($L$9="",$L$9=0,B28=""),"",B28/$L$9)
A29: Entity 8 | B29: =Valuation_Entity8!B37 | C29: =IF(OR($L$9="",$L$9=0,B29=""),"",B29/$L$9)
A30: Entity 9 | B30: =Valuation_Entity9!B37 | C30: =IF(OR($L$9="",$L$9=0,B30=""),"",B30/$L$9)
A31: Entity 10 | B31: =Valuation_Entity10!B37 | C31: =IF(OR($L$9="",$L$9=0,B31=""),"",B31/$L$9)
A32: JV Readiness | B32: Ownership % applied after FX conversion; JV split fields remain ready for future AI inputs
A33: Revenue Synergies | B33: =0 -> 0 | C33: =IFERROR(B33/G15,0) -> 0 | L33: =Valuation_Entity3!B37 | M33: =IF(OR($L$9="",$L$9=0,B24=""),"",B24/$L$9)
A34: Cost Synergies | B34: =0 -> 0 | C34: =IFERROR(B34/G15,0) -> 0 | L34: =Valuation_Entity10!B37 | M34: =IF(OR($L$9="",$L$9=0,B31=""),"",B31/$L$9)
A35: Operational Efficiencies | B35: =0 -> 0 | C35: =IFERROR(B35/G15,0) -> 0
A36: Total Synergies | B36: =SUM(B33:B35) -> 0 | C36: =IFERROR(B36/G15,0) -> 0
A37: Pro Forma EBITDA (w/ Synergies) | B37: =IF(L5="","",L5+B36) -> 0

Sheet Review_Checks
A1: MODEL REVIEW CHECKS | X1: List_Country | Y1: United States | Z1: Canada | AA1: United Kingdom | AB1: Germany | AC1: France | AD1: Japan | AE1: Australia | AF1: Mexico | AG1: Other
X2: List_Currency | Y2: USD | Z2: EUR | AA2: GBP | AB2: CAD | AC2: JPY | AD2: AUD | AE2: MXN | AF2: CHF | AG2: Other
A3: Check | B3: Result | C3: Status | D3: Notes
A4: 1. Balance Sheet Balances | B4: =IF(OR(Fin_Inputs_Entity1!F23=0,Fin_Inputs_Entity1!F23=(Fin_Inputs_Entity1!F28+Fin_Inputs_Entity1!F29)),"PASS","FAIL") -> PASS | C4: =IF(B4="PASS","✓",IF(B4="FAIL","✗","?")) -> ✓ | D4: Assets = Liabilities + Equity
A5: 2. Cash Flow Reconciliation | B5: =IF(OR(Fin_Inputs_Entity1!F37=0,Fin_Inputs_Entity1!F37=(Fin_Inputs_Entity1!F33+Fin_Inputs_Entity1!F34-Fin_Inputs_Entity1!F35-Fin_Inputs_Entity1!F36)),"PASS","FAIL") -> PASS | C5: =IF(B5="PASS","✓",IF(B5="FAIL","✗","?")) -> ✓ | D5: FCF ties to change in cash
A6: 3. Missing Data Check | B6: =IF(COUNTBLANK(Fin_Inputs_Entity1!B5:F14)>0,"FAIL","PASS") -> FAIL | C6: =IF(B6="PASS","✓",IF(B6="FAIL","✗","?")) -> ✗ | D6: All required inputs populated
A7: 4. Outlier Detection | B7: =IF(OR(IFERROR(ABS(Fin_Inputs_Entity1!F5/Fin_Inputs_Entity1!B5-1),0)>1,IFERROR(ABS(Fin_Inputs_Entity1!F9/Fin_Inputs_Entity1!B9-1),0)>2),"FAIL","PASS") -> PASS | C7: =IF(B7="PASS","✓",IF(B7="FAIL","✗","?")) -> ✓ | D7: No unusual growth/margin spikes
A8: 5. FX Conversion Applied | B8: =IF(NR_FX_Final>0,"PASS","FAIL") -> PASS | C8: =IF(B8="PASS","✓",IF(B8="FAIL","✗","?")) -> ✓ | D8: USD rate entered
A9: 6. Formula Integrity | B9: =IF(AND(NR_Final_Valuation>=0,NR_DCF_Value>=0),"PASS","FAIL") -> PASS | C9: =IF(B9="PASS","✓",IF(B9="FAIL","✗","?")) -> ✓ | D9: No circular references
A11: SUMMARY
A12: Total Checks | B12: =6 -> 6
A13: Passed | B13: =COUNTIF(B4:B9,"PASS") -> 5
A14: Failed/Review | B14: =COUNTIF(B4:B9,"FAIL")+COUNTIF(B4:B9,"CHECK") -> 1
A15: Overall Status | B15: =IF(B14=0,"ALL PASSED",IF(COUNTIF(B4:B9,"FAIL")>0,"REVIEW REQUIRED","NEEDS ATTENTION")) -> REVIEW REQUIRED

Sheet Export_Report
A1: VALUATION EXPORT REPORT
A3: CLIENT INFORMATION
A4: Client Name | B4: =NR_Client_Name -> 0
A5: Valuation Date | B5: =NR_Valuation_Date -> 0
A6: Service Line | B6: =NR_Service_Line -> 0
A7: Industry | B7: =NR_Industry -> 0
A8: Location | B8: =NR_Location -> 0
A10: FINAL VALUATION
A11: DCF Value | B11: =NR_DCF_Value
A12: Market Multiples Value | B12: =NR_Multiples_Value -> Valuation!D30
A13: Final Valuation | B13: =NR_Final_Valuation
A15: KEY PERFORMANCE INDICATORS
A16: Revenue CAGR | B16: =KPIs!C4
A17: EBITDA Margin | B17: =KPIs!C6
A18: Net Margin | B18: =KPIs!C7
A19: Debt/EBITDA | B19: =KPIs!C11
A20: ROE | B20: =KPIs!C14
A22: BENCHMARK SUMMARY
A23: Metric | B23: Client | C23: Industry
A24: EBITDA Margin | B24: =KPIs!C6 | C24: =Benchmarking!C5 -> 0
A25: Net Margin | B25: =KPIs!C7 | C25: =Benchmarking!C6 -> 0
A26: Revenue Growth | B26: =KPIs!C4 | C26: =Benchmarking!C4 -> 0
A28: NARRATIVE SUMMARY
A29: Executive Summary:
A30: [Enter executive summary here]
A32: Key Findings:
A33: [Enter key findings here]
A35: Risks & Considerations:
A36: [Enter risks here]
A38: Recommendation:
A39: [Enter recommendation here]
A41: CHART REFERENCES
A42: Revenue Growth Chart | B42: See Charts tab
A43: EBITDA Margin Trend | B43: See Charts tab
A44: Valuation Summary | B44: See Charts tab
A45: Benchmark Comparison | B45: See Charts tab

Sheet Fin_Inputs_Entity4
A1: ENTITY 4 FINANCIAL INPUTS
A3: INCOME STATEMENT
A4: Line Item | B4: Year 1 | C4: Year 2 | D4: Year 3 | E4: Year 4 | F4: Year 5
A5: Revenue
A6: COGS
A7: Gross Profit
A8: Operating Expenses
A9: EBITDA
A10: Depreciation
A11: EBIT
A12: Interest
A13: Taxes
A14: Net Income
A16: BALANCE SHEET
A17: Line Item | B17: Year 1 | C17: Year 2 | D17: Year 3 | E17: Year 4 | F17: Year 5
A18: Cash
A19: AR
A20: Inventory
A21: Current Assets
A22: PP&E
A23: Total Assets
A24: AP
A25: Accrued Liabilities
A26: Short-Term Debt
A27: Long-Term Debt
A28: Total Liabilities
A29: Equity
A31: CASH FLOW STATEMENT
A32: Line Item | B32: Year 1 | C32: Year 2 | D32: Year 3 | E32: Year 4 | F32: Year 5
A33: Net Income
A34: Depreciation
A35: Working Capital Changes
A36: Capex
A37: Free Cash Flow

Sheet Fin_Inputs_Entity5
A1: ENTITY 5 FINANCIAL INPUTS
A3: INCOME STATEMENT
A4: Line Item | B4: Year 1 | C4: Year 2 | D4: Year 3 | E4: Year 4 | F4: Year 5
A5: Revenue
A6: COGS
A7: Gross Profit
A8: Operating Expenses
A9: EBITDA
A10: Depreciation
A11: EBIT
A12: Interest
A13: Taxes
A14: Net Income
A16: BALANCE SHEET
A17: Line Item | B17: Year 1 | C17: Year 2 | D17: Year 3 | E17: Year 4 | F17: Year 5
A18: Cash
A19: AR
A20: Inventory
A21: Current Assets
A22: PP&E
A23: Total Assets
A24: AP
A25: Accrued Liabilities
A26: Short-Term Debt
A27: Long-Term Debt
A28: Total Liabilities
A29: Equity
A31: CASH FLOW STATEMENT
A32: Line Item | B32: Year 1 | C32: Year 2 | D32: Year 3 | E32: Year 4 | F32: Year 5
A33: Net Income
A34: Depreciation
A35: Working Capital Changes
A36: Capex
A37: Free Cash Flow

Sheet Fin_Inputs_Entity6
A1: ENTITY 6 FINANCIAL INPUTS
A3: INCOME STATEMENT
A4: Line Item | B4: Year 1 | C4: Year 2 | D4: Year 3 | E4: Year 4 | F4: Year 5
A5: Revenue
A6: COGS
A7: Gross Profit
A8: Operating Expenses
A9: EBITDA
A10: Depreciation
A11: EBIT
A12: Interest
A13: Taxes
A14: Net Income
A16: BALANCE SHEET
A17: Line Item | B17: Year 1 | C17: Year 2 | D17: Year 3 | E17: Year 4 | F17: Year 5
A18: Cash
A19: AR
A20: Inventory
A21: Current Assets
A22: PP&E
A23: Total Assets
A24: AP
A25: Accrued Liabilities
A26: Short-Term Debt
A27: Long-Term Debt
A28: Total Liabilities
A29: Equity
A31: CASH FLOW STATEMENT
A32: Line Item | B32: Year 1 | C32: Year 2 | D32: Year 3 | E32: Year 4 | F32: Year 5
A33: Net Income
A34: Depreciation
A35: Working Capital Changes
A36: Capex
A37: Free Cash Flow

Sheet Fin_Inputs_Entity7
A1: ENTITY 7 FINANCIAL INPUTS
A3: INCOME STATEMENT
A4: Line Item | B4: Year 1 | C4: Year 2 | D4: Year 3 | E4: Year 4 | F4: Year 5
A5: Revenue
A6: COGS
A7: Gross Profit
A8: Operating Expenses
A9: EBITDA
A10: Depreciation
A11: EBIT
A12: Interest
A13: Taxes
A14: Net Income
A16: BALANCE SHEET
A17: Line Item | B17: Year 1 | C17: Year 2 | D17: Year 3 | E17: Year 4 | F17: Year 5
A18: Cash
A19: AR
A20: Inventory
A21: Current Assets
A22: PP&E
A23: Total Assets
A24: AP
A25: Accrued Liabilities
A26: Short-Term Debt
A27: Long-Term Debt
A28: Total Liabilities
A29: Equity
A31: CASH FLOW STATEMENT
A32: Line Item | B32: Year 1 | C32: Year 2 | D32: Year 3 | E32: Year 4 | F32: Year 5
A33: Net Income
A34: Depreciation
A35: Working Capital Changes
A36: Capex
A37: Free Cash Flow

Sheet Fin_Inputs_Entity8
A1: ENTITY 8 FINANCIAL INPUTS
A3: INCOME STATEMENT
A4: Line Item | B4: Year 1 | C4: Year 2 | D4: Year 3 | E4: Year 4 | F4: Year 5
A5: Revenue
A6: COGS
A7: Gross Profit
A8: Operating Expenses
A9: EBITDA
A10: Depreciation
A11: EBIT
A12: Interest
A13: Taxes
A14: Net Income
A16: BALANCE SHEET
A17: Line Item | B17: Year 1 | C17: Year 2 | D17: Year 3 | E17: Year 4 | F17: Year 5
A18: Cash
A19: AR
A20: Inventory
A21: Current Assets
A22: PP&E
A23: Total Assets
A24: AP
A25: Accrued Liabilities
A26: Short-Term Debt
A27: Long-Term Debt
A28: Total Liabilities
A29: Equity
A31: CASH FLOW STATEMENT
A32: Line Item | B32: Year 1 | C32: Year 2 | D32: Year 3 | E32: Year 4 | F32: Year 5
A33: Net Income
A34: Depreciation
A35: Working Capital Changes
A36: Capex
A37: Free Cash Flow

Sheet Fin_Inputs_Entity9
A1: ENTITY 9 FINANCIAL INPUTS
A3: INCOME STATEMENT
A4: Line Item | B4: Year 1 | C4: Year 2 | D4: Year 3 | E4: Year 4 | F4: Year 5
A5: Revenue
A6: COGS
A7: Gross Profit
A8: Operating Expenses
A9: EBITDA
A10: Depreciation
A11: EBIT
A12: Interest
A13: Taxes
A14: Net Income
A16: BALANCE SHEET
A17: Line Item | B17: Year 1 | C17: Year 2 | D17: Year 3 | E17: Year 4 | F17: Year 5
A18: Cash
A19: AR
A20: Inventory
A21: Current Assets
A22: PP&E
A23: Total Assets
A24: AP
A25: Accrued Liabilities
A26: Short-Term Debt
A27: Long-Term Debt
A28: Total Liabilities
A29: Equity
A31: CASH FLOW STATEMENT
A32: Line Item | B32: Year 1 | C32: Year 2 | D32: Year 3 | E32: Year 4 | F32: Year 5
A33: Net Income
A34: Depreciation
A35: Working Capital Changes
A36: Capex
A37: Free Cash Flow

Sheet Fin_Inputs_Entity10
A1: ENTITY 10 FINANCIAL INPUTS
A3: INCOME STATEMENT
A4: Line Item | B4: Year 1 | C4: Year 2 | D4: Year 3 | E4: Year 4 | F4: Year 5
A5: Revenue
A6: COGS
A7: Gross Profit
A8: Operating Expenses
A9: EBITDA
A10: Depreciation
A11: EBIT
A12: Interest
A13: Taxes
A14: Net Income
A16: BALANCE SHEET
A17: Line Item | B17: Year 1 | C17: Year 2 | D17: Year 3 | E17: Year 4 | F17: Year 5
A18: Cash
A19: AR
A20: Inventory
A21: Current Assets
A22: PP&E
A23: Total Assets
A24: AP
A25: Accrued Liabilities
A26: Short-Term Debt
A27: Long-Term Debt
A28: Total Liabilities
A29: Equity
A31: CASH FLOW STATEMENT
A32: Line Item | B32: Year 1 | C32: Year 2 | D32: Year 3 | E32: Year 4 | F32: Year 5
A33: Net Income
A34: Depreciation
A35: Working Capital Changes
A36: Capex
A37: Free Cash Flow

Sheet Global_Rates
A1: GLOBAL RATES - PREVIOUS MONTH-END
A3: Rate Name | B3: Entity | C3: Country | D3: Currency | E3: Previous Month-End Date | F3: Value Used | G3: Source URL | H3: AI_Fetched (Yes/No) | I3: Manual Override (Yes/No) | J3: Purpose | K3: Warning
A4: U.S. 10-Year Treasury | B4: Entity 1 | C4: United States | D4: USD | E4: =EOMONTH(TODAY(),-1) -> 46142 | H4: =IF(OR(F4="",G4=""),"","Yes") | J4: WACC / CAPM | K4: =IF(OR(A4="Local 10-Year Government Bond Yield",A4="Local Market Risk Premium",A4="Local Corporate Bond Yield"),IF(OR(C4="",D4=""),"WARNING: Missing Country/Currency Data",IF(F4="","WARNING: Rate Missing — Fallback Value Used","")),IF(F4="","WARNING: Rate Missing — Fallback Value Used","")) -> WARNING: Rate Missing — Fallback Value Used
A5: U.S. Market Risk Premium | B5: Entity 1 | C5: United States | D5: USD | E5: =EOMONTH(TODAY(),-1) -> 46142 | H5: =IF(OR(F5="",G5=""),"","Yes") | J5: CAPM | K5: =IF(OR(A5="Local 10-Year Government Bond Yield",A5="Local Market Risk Premium",A5="Local Corporate Bond Yield"),IF(OR(C5="",D5=""),"WARNING: Missing Country/Currency Data",IF(F5="","WARNING: Rate Missing — Fallback Value Used","")),IF(F5="","WARNING: Rate Missing — Fallback Value Used","")) -> WARNING: Rate Missing — Fallback Value Used
A6: U.S. Corporate Bond Yield | B6: Entity 1 | C6: United States | D6: USD | E6: =EOMONTH(TODAY(),-1) -> 46142 | H6: =IF(OR(F6="",G6=""),"","Yes") | J6: WACC / Loan Readiness | K6: =IF(OR(A6="Local 10-Year Government Bond Yield",A6="Local Market Risk Premium",A6="Local Corporate Bond Yield"),IF(OR(C6="",D6=""),"WARNING: Missing Country/Currency Data",IF(F6="","WARNING: Rate Missing — Fallback Value Used","")),IF(F6="","WARNING: Rate Missing — Fallback Value Used","")) -> WARNING: Rate Missing — Fallback Value Used
A7: Beta | B7: Entity 1 | C7: United States | D7: USD | E7: =EOMONTH(TODAY(),-1) -> 46142 | H7: =IF(OR(F7="",G7=""),"","Yes") | J7: CAPM | K7: =IF(OR(A7="Local 10-Year Government Bond Yield",A7="Local Market Risk Premium",A7="Local Corporate Bond Yield"),IF(OR(C7="",D7=""),"WARNING: Missing Country/Currency Data",IF(F7="","WARNING: Rate Missing — Fallback Value Used","")),IF(F7="","WARNING: Rate Missing — Fallback Value Used","")) -> WARNING: Rate Missing — Fallback Value Used
A8: Local 10-Year Government Bond Yield | B8: Entity 1 | C8: =IF(Entity_Ownership!F4="","",Entity_Ownership!F4) | D8: =IF(Entity_Ownership!G4="","",Entity_Ownership!G4) | E8: =EOMONTH(TODAY(),-1) -> 46142 | H8: =IF(OR(F8="",G8=""),"","Yes") | J8: WACC / CAPM | K8: =IF(OR(A8="Local 10-Year Government Bond Yield",A8="Local Market Risk Premium",A8="Local Corporate Bond Yield"),IF(OR(C8="",D8=""),"WARNING: Missing Country/Currency Data",IF(F8="","WARNING: Rate Missing — Fallback Value Used","")),IF(F8="","WARNING: Rate Missing — Fallback Value Used","")) -> WARNING: Missing Country/Currency Data
A9: Local Market Risk Premium | B9: Entity 1 | C9: =IF(Entity_Ownership!F4="","",Entity_Ownership!F4) | D9: =IF(Entity_Ownership!G4="","",Entity_Ownership!G4) | E9: =EOMONTH(TODAY(),-1) -> 46142 | H9: =IF(OR(F9="",G9=""),"","Yes") | J9: CAPM | K9: =IF(OR(A9="Local 10-Year Government Bond Yield",A9="Local Market Risk Premium",A9="Local Corporate Bond Yield"),IF(OR(C9="",D9=""),"WARNING: Missing Country/Currency Data",IF(F9="","WARNING: Rate Missing — Fallback Value Used","")),IF(F9="","WARNING: Rate Missing — Fallback Value Used","")) -> WARNING: Missing Country/Currency Data
A10: Local Corporate Bond Yield | B10: Entity 1 | C10: =IF(Entity_Ownership!F4="","",Entity_Ownership!F4) | D10: =IF(Entity_Ownership!G4="","",Entity_Ownership!G4) | E10: =EOMONTH(TODAY(),-1) -> 46142 | H10: =IF(OR(F10="",G10=""),"","Yes") | J10: WACC / Loan Readiness | K10: =IF(OR(A10="Local 10-Year Government Bond Yield",A10="Local Market Risk Premium",A10="Local Corporate Bond Yield"),IF(OR(C10="",D10=""),"WARNING: Missing Country/Currency Data",IF(F10="","WARNING: Rate Missing — Fallback Value Used","")),IF(F10="","WARNING: Rate Missing — Fallback Value Used","")) -> WARNING: Missing Country/Currency Data
A11: U.S. 10-Year Treasury | B11: Entity 2 | C11: United States | D11: USD | E11: =EOMONTH(TODAY(),-1) -> 46142 | H11: =IF(OR(F11="",G11=""),"","Yes") | J11: WACC / CAPM | K11: =IF(OR(A11="Local 10-Year Government Bond Yield",A11="Local Market Risk Premium",A11="Local Corporate Bond Yield"),IF(OR(C11="",D11=""),"WARNING: Missing Country/Currency Data",IF(F11="","WARNING: Rate Missing — Fallback Value Used","")),IF(F11="","WARNING: Rate Missing — Fallback Value Used","")) -> WARNING: Rate Missing — Fallback Value Used
A12: U.S. Market Risk Premium | B12: Entity 2 | C12: United States | D12: USD | E12: =EOMONTH(TODAY(),-1) -> 46142 | H12: =IF(OR(F12="",G12=""),"","Yes") | J12: CAPM | K12: =IF(OR(A12="Local 10-Year Government Bond Yield",A12="Local Market Risk Premium",A12="Local Corporate Bond Yield"),IF(OR(C12="",D12=""),"WARNING: Missing Country/Currency Data",IF(F12="","WARNING: Rate Missing — Fallback Value Used","")),IF(F12="","WARNING: Rate Missing — Fallback Value Used","")) -> WARNING: Rate Missing — Fallback Value Used
A13: U.S. Corporate Bond Yield | B13: Entity 2 | C13: United States | D13: USD | E13: =EOMONTH(TODAY(),-1) -> 46142 | H13: =IF(OR(F13="",G13=""),"","Yes") | J13: WACC / Loan Readiness | K13: =IF(OR(A13="Local 10-Year Government Bond Yield",A13="Local Market Risk Premium",A13="Local Corporate Bond Yield"),IF(OR(C13="",D13=""),"WARNING: Missing Country/Currency Data",IF(F13="","WARNING: Rate Missing — Fallback Value Used","")),IF(F13="","WARNING: Rate Missing — Fallback Value Used","")) -> WARNING: Rate Missing — Fallback Value Used
A14: Beta | B14: Entity 2 | C14: United States | D14: USD | E14: =EOMONTH(TODAY(),-1) -> 46142 | H14: =IF(OR(F14="",G14=""),"","Yes") | J14: CAPM | K14: =IF(OR(A14="Local 10-Year Government Bond Yield",A14="Local Market Risk Premium",A14="Local Corporate Bond Yield"),IF(OR(C14="",D14=""),"WARNING: Missing Country/Currency Data",IF(F14="","WARNING: Rate Missing — Fallback Value Used","")),IF(F14="","WARNING: Rate Missing — Fallback Value Used","")) -> WARNING: Rate Missing — Fallback Value Used
A15: Local 10-Year Government Bond Yield | B15: Entity 2 | C15: =IF(Entity_Ownership!F5="","",Entity_Ownership!F5) | D15: =IF(Entity_Ownership!G5="","",Entity_Ownership!G5) | E15: =EOMONTH(TODAY(),-1) -> 46142 | H15: =IF(OR(F15="",G15=""),"","Yes") | J15: WACC / CAPM | K15: =IF(OR(A15="Local 10-Year Government Bond Yield",A15="Local Market Risk Premium",A15="Local Corporate Bond Yield"),IF(OR(C15="",D15=""),"WARNING: Missing Country/Currency Data",IF(F15="","WARNING: Rate Missing — Fallback Value Used","")),IF(F15="","WARNING: Rate Missing — Fallback Value Used","")) -> WARNING: Missing Country/Currency Data
A16: Local Market Risk Premium | B16: Entity 2 | C16: =IF(Entity_Ownership!F5="","",Entity_Ownership!F5) | D16: =IF(Entity_Ownership!G5="","",Entity_Ownership!G5) | E16: =EOMONTH(TODAY(),-1) -> 46142 | H16: =IF(OR(F16="",G16=""),"","Yes") | J16: CAPM | K16: =IF(OR(A16="Local 10-Year Government Bond Yield",A16="Local Market Risk Premium",A16="Local Corporate Bond Yield"),IF(OR(C16="",D16=""),"WARNING: Missing Country/Currency Data",IF(F16="","WARNING: Rate Missing — Fallback Value Used","")),IF(F16="","WARNING: Rate Missing — Fallback Value Used","")) -> WARNING: Missing Country/Currency Data
A17: Local Corporate Bond Yield | B17: Entity 2 | C17: =IF(Entity_Ownership!F5="","",Entity_Ownership!F5) | D17: =IF(Entity_Ownership!G5="","",Entity_Ownership!G5) | E17: =EOMONTH(TODAY(),-1) -> 46142 | H17: =IF(OR(F17="",G17=""),"","Yes") | J17: WACC / Loan Readiness | K17: =IF(OR(A17="Local 10-Year Government Bond Yield",A17="Local Market Risk Premium",A17="Local Corporate Bond Yield"),IF(OR(C17="",D17=""),"WARNING: Missing Country/Currency Data",IF(F17="","WARNING: Rate Missing — Fallback Value Used","")),IF(F17="","WARNING: Rate Missing — Fallback Value Used","")) -> WARNING: Missing Country/Currency Data
A18: U.S. 10-Year Treasury | B18: Entity 3 | C18: United States | D18: USD | E18: =EOMONTH(TODAY(),-1) -> 46142 | H18: =IF(OR(F18="",G18=""),"","Yes") | J18: WACC / CAPM | K18: =IF(OR(A18="Local 10-Year Government Bond Yield",A18="Local Market Risk Premium",A18="Local Corporate Bond Yield"),IF(OR(C18="",D18=""),"WARNING: Missing Country/Currency Data",IF(F18="","WARNING: Rate Missing — Fallback Value Used","")),IF(F18="","WARNING: Rate Missing — Fallback Value Used","")) -> WARNING: Rate Missing — Fallback Value Used
A19: U.S. Market Risk Premium | B19: Entity 3 | C19: United States | D19: USD | E19: =EOMONTH(TODAY(),-1) -> 46142 | H19: =IF(OR(F19="",G19=""),"","Yes") | J19: CAPM | K19: =IF(OR(A19="Local 10-Year Government Bond Yield",A19="Local Market Risk Premium",A19="Local Corporate Bond Yield"),IF(OR(C19="",D19=""),"WARNING: Missing Country/Currency Data",IF(F19="","WARNING: Rate Missing — Fallback Value Used","")),IF(F19="","WARNING: Rate Missing — Fallback Value Used","")) -> WARNING: Rate Missing — Fallback Value Used
A20: U.S. Corporate Bond Yield | B20: Entity 3 | C20: United States | D20: USD | E20: =EOMONTH(TODAY(),-1) -> 46142 | H20: =IF(OR(F20="",G20=""),"","Yes") | J20: WACC / Loan Readiness | K20: =IF(OR(A20="Local 10-Year Government Bond Yield",A20="Local Market Risk Premium",A20="Local Corporate Bond Yield"),IF(OR(C20="",D20=""),"WARNING: Missing Country/Currency Data",IF(F20="","WARNING: Rate Missing — Fallback Value Used","")),IF(F20="","WARNING: Rate Missing — Fallback Value Used","")) -> WARNING: Rate Missing — Fallback Value Used
A21: Beta | B21: Entity 3 | C21: United States | D21: USD | E21: =EOMONTH(TODAY(),-1) -> 46142 | H21: =IF(OR(F21="",G21=""),"","Yes") | J21: CAPM | K21: =IF(OR(A21="Local 10-Year Government Bond Yield",A21="Local Market Risk Premium",A21="Local Corporate Bond Yield"),IF(OR(C21="",D21=""),"WARNING: Missing Country/Currency Data",IF(F21="","WARNING: Rate Missing — Fallback Value Used","")),IF(F21="","WARNING: Rate Missing — Fallback Value Used","")) -> WARNING: Rate Missing — Fallback Value Used
A22: Local 10-Year Government Bond Yield | B22: Entity 3 | C22: =IF(Entity_Ownership!F6="","",Entity_Ownership!F6) | D22: =IF(Entity_Ownership!G6="","",Entity_Ownership!G6) | E22: =EOMONTH(TODAY(),-1) -> 46142 | H22: =IF(OR(F22="",G22=""),"","Yes") | J22: WACC / CAPM | K22: =IF(OR(A22="Local 10-Year Government Bond Yield",A22="Local Market Risk Premium",A22="Local Corporate Bond Yield"),IF(OR(C22="",D22=""),"WARNING: Missing Country/Currency Data",IF(F22="","WARNING: Rate Missing — Fallback Value Used","")),IF(F22="","WARNING: Rate Missing — Fallback Value Used","")) -> WARNING: Missing Country/Currency Data
A23: Local Market Risk Premium | B23: Entity 3 | C23: =IF(Entity_Ownership!F6="","",Entity_Ownership!F6) | D23: =IF(Entity_Ownership!G6="","",Entity_Ownership!G6) | E23: =EOMONTH(TODAY(),-1) -> 46142 | H23: =IF(OR(F23="",G23=""),"","Yes") | J23: CAPM | K23: =IF(OR(A23="Local 10-Year Government Bond Yield",A23="Local Market Risk Premium",A23="Local Corporate Bond Yield"),IF(OR(C23="",D23=""),"WARNING: Missing Country/Currency Data",IF(F23="","WARNING: Rate Missing — Fallback Value Used","")),IF(F23="","WARNING: Rate Missing — Fallback Value Used","")) -> WARNING: Missing Country/Currency Data
A24: Local Corporate Bond Yield | B24: Entity 3 | C24: =IF(Entity_Ownership!F6="","",Entity_Ownership!F6) | D24: =IF(Entity_Ownership!G6="","",Entity_Ownership!G6) | E24: =EOMONTH(TODAY(),-1) -> 46142 | H24: =IF(OR(F24="",G24=""),"","Yes") | J24: WACC / Loan Readiness | K24: =IF(OR(A24="Local 10-Year Government Bond Yield",A24="Local Market Risk Premium",A24="Local Corporate Bond Yield"),IF(OR(C24="",D24=""),"WARNING: Missing Country/Currency Data",IF(F24="","WARNING: Rate Missing — Fallback Value Used","")),IF(F24="","WARNING: Rate Missing — Fallback Value Used","")) -> WARNING: Missing Country/Currency Data
A25: U.S. 10-Year Treasury | B25: Entity 4 | C25: United States | D25: USD | E25: =EOMONTH(TODAY(),-1) -> 46142 | H25: =IF(OR(F25="",G25=""),"","Yes") | J25: WACC / CAPM | K25: =IF(OR(A25="Local 10-Year Government Bond Yield",A25="Local Market Risk Premium",A25="Local Corporate Bond Yield"),IF(OR(C25="",D25=""),"WARNING: Missing Country/Currency Data",IF(F25="","WARNING: Rate Missing — Fallback Value Used","")),IF(F25="","WARNING: Rate Missing — Fallback Value Used","")) -> WARNING: Rate Missing — Fallback Value Used
A26: U.S. Market Risk Premium | B26: Entity 4 | C26: United States | D26: USD | E26: =EOMONTH(TODAY(),-1) -> 46142 | H26: =IF(OR(F26="",G26=""),"","Yes") | J26: CAPM | K26: =IF(OR(A26="Local 10-Year Government Bond Yield",A26="Local Market Risk Premium",A26="Local Corporate Bond Yield"),IF(OR(C26="",D26=""),"WARNING: Missing Country/Currency Data",IF(F26="","WARNING: Rate Missing — Fallback Value Used","")),IF(F26="","WARNING: Rate Missing — Fallback Value Used","")) -> WARNING: Rate Missing — Fallback Value Used
A27: U.S. Corporate Bond Yield | B27: Entity 4 | C27: United States | D27: USD | E27: =EOMONTH(TODAY(),-1) -> 46142 | H27: =IF(OR(F27="",G27=""),"","Yes") | J27: WACC / Loan Readiness | K27: =IF(OR(A27="Local 10-Year Government Bond Yield",A27="Local Market Risk Premium",A27="Local Corporate Bond Yield"),IF(OR(C27="",D27=""),"WARNING: Missing Country/Currency Data",IF(F27="","WARNING: Rate Missing — Fallback Value Used","")),IF(F27="","WARNING: Rate Missing — Fallback Value Used","")) -> WARNING: Rate Missing — Fallback Value Used
A28: Beta | B28: Entity 4 | C28: United States | D28: USD | E28: =EOMONTH(TODAY(),-1) -> 46142 | H28: =IF(OR(F28="",G28=""),"","Yes") | J28: CAPM | K28: =IF(OR(A28="Local 10-Year Government Bond Yield",A28="Local Market Risk Premium",A28="Local Corporate Bond Yield"),IF(OR(C28="",D28=""),"WARNING: Missing Country/Currency Data",IF(F28="","WARNING: Rate Missing — Fallback Value Used","")),IF(F28="","WARNING: Rate Missing — Fallback Value Used","")) -> WARNING: Rate Missing — Fallback Value Used
A29: Local 10-Year Government Bond Yield | B29: Entity 4 | C29: =IF(Entity_Ownership!F7="","",Entity_Ownership!F7) | D29: =IF(Entity_Ownership!G7="","",Entity_Ownership!G7) | E29: =EOMONTH(TODAY(),-1) -> 46142 | H29: =IF(OR(F29="",G29=""),"","Yes") | J29: WACC / CAPM | K29: =IF(OR(A29="Local 10-Year Government Bond Yield",A29="Local Market Risk Premium",A29="Local Corporate Bond Yield"),IF(OR(C29="",D29=""),"WARNING: Missing Country/Currency Data",IF(F29="","WARNING: Rate Missing — Fallback Value Used","")),IF(F29="","WARNING: Rate Missing — Fallback Value Used","")) -> WARNING: Missing Country/Currency Data
A30: Local Market Risk Premium | B30: Entity 4 | C30: =IF(Entity_Ownership!F7="","",Entity_Ownership!F7) | D30: =IF(Entity_Ownership!G7="","",Entity_Ownership!G7) | E30: =EOMONTH(TODAY(),-1) -> 46142 | H30: =IF(OR(F30="",G30=""),"","Yes") | J30: CAPM | K30: =IF(OR(A30="Local 10-Year Government Bond Yield",A30="Local Market Risk Premium",A30="Local Corporate Bond Yield"),IF(OR(C30="",D30=""),"WARNING: Missing Country/Currency Data",IF(F30="","WARNING: Rate Missing — Fallback Value Used","")),IF(F30="","WARNING: Rate Missing — Fallback Value Used","")) -> WARNING: Missing Country/Currency Data
A31: Local Corporate Bond Yield | B31: Entity 4 | C31: =IF(Entity_Ownership!F7="","",Entity_Ownership!F7) | D31: =IF(Entity_Ownership!G7="","",Entity_Ownership!G7) | E31: =EOMONTH(TODAY(),-1) -> 46142 | H31: =IF(OR(F31="",G31=""),"","Yes") | J31: WACC / Loan Readiness | K31: =IF(OR(A31="Local 10-Year Government Bond Yield",A31="Local Market Risk Premium",A31="Local Corporate Bond Yield"),IF(OR(C31="",D31=""),"WARNING: Missing Country/Currency Data",IF(F31="","WARNING: Rate Missing — Fallback Value Used","")),IF(F31="","WARNING: Rate Missing — Fallback Value Used","")) -> WARNING: Missing Country/Currency Data
A32: U.S. 10-Year Treasury | B32: Entity 5 | C32: United States | D32: USD | E32: =EOMONTH(TODAY(),-1) -> 46142 | H32: =IF(OR(F32="",G32=""),"","Yes") | J32: WACC / CAPM | K32: =IF(OR(A32="Local 10-Year Government Bond Yield",A32="Local Market Risk Premium",A32="Local Corporate Bond Yield"),IF(OR(C32="",D32=""),"WARNING: Missing Country/Currency Data",IF(F32="","WARNING: Rate Missing — Fallback Value Used","")),IF(F32="","WARNING: Rate Missing — Fallback Value Used","")) -> WARNING: Rate Missing — Fallback Value Used
A33: U.S. Market Risk Premium | B33: Entity 5 | C33: United States | D33: USD | E33: =EOMONTH(TODAY(),-1) -> 46142 | H33: =IF(OR(F33="",G33=""),"","Yes") | J33: CAPM | K33: =IF(OR(A33="Local 10-Year Government Bond Yield",A33="Local Market Risk Premium",A33="Local Corporate Bond Yield"),IF(OR(C33="",D33=""),"WARNING: Missing Country/Currency Data",IF(F33="","WARNING: Rate Missing — Fallback Value Used","")),IF(F33="","WARNING: Rate Missing — Fallback Value Used","")) -> WARNING: Rate Missing — Fallback Value Used
A34: U.S. Corporate Bond Yield | B34: Entity 5 | C34: United States | D34: USD | E34: =EOMONTH(TODAY(),-1) -> 46142 | H34: =IF(OR(F34="",G34=""),"","Yes") | J34: WACC / Loan Readiness | K34: =IF(OR(A34="Local 10-Year Government Bond Yield",A34="Local Market Risk Premium",A34="Local Corporate Bond Yield"),IF(OR(C34="",D34=""),"WARNING: Missing Country/Currency Data",IF(F34="","WARNING: Rate Missing — Fallback Value Used","")),IF(F34="","WARNING: Rate Missing — Fallback Value Used","")) -> WARNING: Rate Missing — Fallback Value Used
A35: Beta | B35: Entity 5 | C35: United States | D35: USD | E35: =EOMONTH(TODAY(),-1) -> 46142 | H35: =IF(OR(F35="",G35=""),"","Yes") | J35: CAPM | K35: =IF(OR(A35="Local 10-Year Government Bond Yield",A35="Local Market Risk Premium",A35="Local Corporate Bond Yield"),IF(OR(C35="",D35=""),"WARNING: Missing Country/Currency Data",IF(F35="","WARNING: Rate Missing — Fallback Value Used","")),IF(F35="","WARNING: Rate Missing — Fallback Value Used","")) -> WARNING: Rate Missing — Fallback Value Used
A36: Local 10-Year Government Bond Yield | B36: Entity 5 | C36: =IF(Entity_Ownership!F8="","",Entity_Ownership!F8) | D36: =IF(Entity_Ownership!G8="","",Entity_Ownership!G8) | E36: =EOMONTH(TODAY(),-1) -> 46142 | H36: =IF(OR(F36="",G36=""),"","Yes") | J36: WACC / CAPM | K36: =IF(OR(A36="Local 10-Year Government Bond Yield",A36="Local Market Risk Premium",A36="Local Corporate Bond Yield"),IF(OR(C36="",D36=""),"WARNING: Missing Country/Currency Data",IF(F36="","WARNING: Rate Missing — Fallback Value Used","")),IF(F36="","WARNING: Rate Missing — Fallback Value Used","")) -> WARNING: Missing Country/Currency Data
A37: Local Market Risk Premium | B37: Entity 5 | C37: =IF(Entity_Ownership!F8="","",Entity_Ownership!F8) | D37: =IF(Entity_Ownership!G8="","",Entity_Ownership!G8) | E37: =EOMONTH(TODAY(),-1) -> 46142 | H37: =IF(OR(F37="",G37=""),"","Yes") | J37: CAPM | K37: =IF(OR(A37="Local 10-Year Government Bond Yield",A37="Local Market Risk Premium",A37="Local Corporate Bond Yield"),IF(OR(C37="",D37=""),"WARNING: Missing Country/Currency Data",IF(F37="","WARNING: Rate Missing — Fallback Value Used","")),IF(F37="","WARNING: Rate Missing — Fallback Value Used","")) -> WARNING: Missing Country/Currency Data
A38: Local Corporate Bond Yield | B38: Entity 5 | C38: =IF(Entity_Ownership!F8="","",Entity_Ownership!F8) | D38: =IF(Entity_Ownership!G8="","",Entity_Ownership!G8) | E38: =EOMONTH(TODAY(),-1) -> 46142 | H38: =IF(OR(F38="",G38=""),"","Yes") | J38: WACC / Loan Readiness | K38: =IF(OR(A38="Local 10-Year Government Bond Yield",A38="Local Market Risk Premium",A38="Local Corporate Bond Yield"),IF(OR(C38="",D38=""),"WARNING: Missing Country/Currency Data",IF(F38="","WARNING: Rate Missing — Fallback Value Used","")),IF(F38="","WARNING: Rate Missing — Fallback Value Used","")) -> WARNING: Missing Country/Currency Data
A39: U.S. 10-Year Treasury | B39: Entity 6 | C39: United States | D39: USD | E39: =EOMONTH(TODAY(),-1) -> 46142 | H39: =IF(OR(F39="",G39=""),"","Yes") | J39: WACC / CAPM | K39: =IF(OR(A39="Local 10-Year Government Bond Yield",A39="Local Market Risk Premium",A39="Local Corporate Bond Yield"),IF(OR(C39="",D39=""),"WARNING: Missing Country/Currency Data",IF(F39="","WARNING: Rate Missing — Fallback Value Used","")),IF(F39="","WARNING: Rate Missing — Fallback Value Used","")) -> WARNING: Rate Missing — Fallback Value Used
A40: U.S. Market Risk Premium | B40: Entity 6 | C40: United States | D40: USD | E40: =EOMONTH(TODAY(),-1) -> 46142 | H40: =IF(OR(F40="",G40=""),"","Yes") | J40: CAPM | K40: =IF(OR(A40="Local 10-Year Government Bond Yield",A40="Local Market Risk Premium",A40="Local Corporate Bond Yield"),IF(OR(C40="",D40=""),"WARNING: Missing Country/Currency Data",IF(F40="","WARNING: Rate Missing — Fallback Value Used","")),IF(F40="","WARNING: Rate Missing — Fallback Value Used","")) -> WARNING: Rate Missing — Fallback Value Used
A41: U.S. Corporate Bond Yield | B41: Entity 6 | C41: United States | D41: USD | E41: =EOMONTH(TODAY(),-1) -> 46142 | H41: =IF(OR(F41="",G41=""),"","Yes") | J41: WACC / Loan Readiness | K41: =IF(OR(A41="Local 10-Year Government Bond Yield",A41="Local Market Risk Premium",A41="Local Corporate Bond Yield"),IF(OR(C41="",D41=""),"WARNING: Missing Country/Currency Data",IF(F41="","WARNING: Rate Missing — Fallback Value Used","")),IF(F41="","WARNING: Rate Missing — Fallback Value Used","")) -> WARNING: Rate Missing — Fallback Value Used
A42: Beta | B42: Entity 6 | C42: United States | D42: USD | E42: =EOMONTH(TODAY(),-1) -> 46142 | H42: =IF(OR(F42="",G42=""),"","Yes") | J42: CAPM | K42: =IF(OR(A42="Local 10-Year Government Bond Yield",A42="Local Market Risk Premium",A42="Local Corporate Bond Yield"),IF(OR(C42="",D42=""),"WARNING: Missing Country/Currency Data",IF(F42="","WARNING: Rate Missing — Fallback Value Used","")),IF(F42="","WARNING: Rate Missing — Fallback Value Used","")) -> WARNING: Rate Missing — Fallback Value Used
A43: Local 10-Year Government Bond Yield | B43: Entity 6 | C43: =IF(Entity_Ownership!F9="","",Entity_Ownership!F9) | D43: =IF(Entity_Ownership!G9="","",Entity_Ownership!G9) | E43: =EOMONTH(TODAY(),-1) -> 46142 | H43: =IF(OR(F43="",G43=""),"","Yes") | J43: WACC / CAPM | K43: =IF(OR(A43="Local 10-Year Government Bond Yield",A43="Local Market Risk Premium",A43="Local Corporate Bond Yield"),IF(OR(C43="",D43=""),"WARNING: Missing Country/Currency Data",IF(F43="","WARNING: Rate Missing — Fallback Value Used","")),IF(F43="","WARNING: Rate Missing — Fallback Value Used","")) -> WARNING: Missing Country/Currency Data
A44: Local Market Risk Premium | B44: Entity 6 | C44: =IF(Entity_Ownership!F9="","",Entity_Ownership!F9) | D44: =IF(Entity_Ownership!G9="","",Entity_Ownership!G9) | E44: =EOMONTH(TODAY(),-1) -> 46142 | H44: =IF(OR(F44="",G44=""),"","Yes") | J44: CAPM | K44: =IF(OR(A44="Local 10-Year Government Bond Yield",A44="Local Market Risk Premium",A44="Local Corporate Bond Yield"),IF(OR(C44="",D44=""),"WARNING: Missing Country/Currency Data",IF(F44="","WARNING: Rate Missing — Fallback Value Used","")),IF(F44="","WARNING: Rate Missing — Fallback Value Used","")) -> WARNING: Missing Country/Currency Data
A45: Local Corporate Bond Yield | B45: Entity 6 | C45: =IF(Entity_Ownership!F9="","",Entity_Ownership!F9) | D45: =IF(Entity_Ownership!G9="","",Entity_Ownership!G9) | E45: =EOMONTH(TODAY(),-1) -> 46142 | H45: =IF(OR(F45="",G45=""),"","Yes") | J45: WACC / Loan Readiness | K45: =IF(OR(A45="Local 10-Year Government Bond Yield",A45="Local Market Risk Premium",A45="Local Corporate Bond Yield"),IF(OR(C45="",D45=""),"WARNING: Missing Country/Currency Data",IF(F45="","WARNING: Rate Missing — Fallback Value Used","")),IF(F45="","WARNING: Rate Missing — Fallback Value Used","")) -> WARNING: Missing Country/Currency Data
A46: U.S. 10-Year Treasury | B46: Entity 7 | C46: United States | D46: USD | E46: =EOMONTH(TODAY(),-1) -> 46142 | H46: =IF(OR(F46="",G46=""),"","Yes") | J46: WACC / CAPM | K46: =IF(OR(A46="Local 10-Year Government Bond Yield",A46="Local Market Risk Premium",A46="Local Corporate Bond Yield"),IF(OR(C46="",D46=""),"WARNING: Missing Country/Currency Data",IF(F46="","WARNING: Rate Missing — Fallback Value Used","")),IF(F46="","WARNING: Rate Missing — Fallback Value Used","")) -> WARNING: Rate Missing — Fallback Value Used
A47: U.S. Market Risk Premium | B47: Entity 7 | C47: United States | D47: USD | E47: =EOMONTH(TODAY(),-1) -> 46142 | H47: =IF(OR(F47="",G47=""),"","Yes") | J47: CAPM | K47: =IF(OR(A47="Local 10-Year Government Bond Yield",A47="Local Market Risk Premium",A47="Local Corporate Bond Yield"),IF(OR(C47="",D47=""),"WARNING: Missing Country/Currency Data",IF(F47="","WARNING: Rate Missing — Fallback Value Used","")),IF(F47="","WARNING: Rate Missing — Fallback Value Used","")) -> WARNING: Rate Missing — Fallback Value Used
A48: U.S. Corporate Bond Yield | B48: Entity 7 | C48: United States | D48: USD | E48: =EOMONTH(TODAY(),-1) -> 46142 | H48: =IF(OR(F48="",G48=""),"","Yes") | J48: WACC / Loan Readiness | K48: =IF(OR(A48="Local 10-Year Government Bond Yield",A48="Local Market Risk Premium",A48="Local Corporate Bond Yield"),IF(OR(C48="",D48=""),"WARNING: Missing Country/Currency Data",IF(F48="","WARNING: Rate Missing — Fallback Value Used","")),IF(F48="","WARNING: Rate Missing — Fallback Value Used","")) -> WARNING: Rate Missing — Fallback Value Used
A49: Beta | B49: Entity 7 | C49: United States | D49: USD | E49: =EOMONTH(TODAY(),-1) -> 46142 | H49: =IF(OR(F49="",G49=""),"","Yes") | J49: CAPM | K49: =IF(OR(A49="Local 10-Year Government Bond Yield",A49="Local Market Risk Premium",A49="Local Corporate Bond Yield"),IF(OR(C49="",D49=""),"WARNING: Missing Country/Currency Data",IF(F49="","WARNING: Rate Missing — Fallback Value Used","")),IF(F49="","WARNING: Rate Missing — Fallback Value Used","")) -> WARNING: Rate Missing — Fallback Value Used
A50: Local 10-Year Government Bond Yield | B50: Entity 7 | C50: =IF(Entity_Ownership!F10="","",Entity_Ownership!F10) | D50: =IF(Entity_Ownership!G10="","",Entity_Ownership!G10) | E50: =EOMONTH(TODAY(),-1) -> 46142 | H50: =IF(OR(F50="",G50=""),"","Yes") | J50: WACC / CAPM | K50: =IF(OR(A50="Local 10-Year Government Bond Yield",A50="Local Market Risk Premium",A50="Local Corporate Bond Yield"),IF(OR(C50="",D50=""),"WARNING: Missing Country/Currency Data",IF(F50="","WARNING: Rate Missing — Fallback Value Used","")),IF(F50="","WARNING: Rate Missing — Fallback Value Used","")) -> WARNING: Missing Country/Currency Data
A51: Local Market Risk Premium | B51: Entity 7 | C51: =IF(Entity_Ownership!F10="","",Entity_Ownership!F10) | D51: =IF(Entity_Ownership!G10="","",Entity_Ownership!G10) | E51: =EOMONTH(TODAY(),-1) -> 46142 | H51: =IF(OR(F51="",G51=""),"","Yes") | J51: CAPM | K51: =IF(OR(A51="Local 10-Year Government Bond Yield",A51="Local Market Risk Premium",A51="Local Corporate Bond Yield"),IF(OR(C51="",D51=""),"WARNING: Missing Country/Currency Data",IF(F51="","WARNING: Rate Missing — Fallback Value Used","")),IF(F51="","WARNING: Rate Missing — Fallback Value Used","")) -> WARNING: Missing Country/Currency Data
A52: Local Corporate Bond Yield | B52: Entity 7 | C52: =IF(Entity_Ownership!F10="","",Entity_Ownership!F10) | D52: =IF(Entity_Ownership!G10="","",Entity_Ownership!G10) | E52: =EOMONTH(TODAY(),-1) -> 46142 | H52: =IF(OR(F52="",G52=""),"","Yes") | J52: WACC / Loan Readiness | K52: =IF(OR(A52="Local 10-Year Government Bond Yield",A52="Local Market Risk Premium",A52="Local Corporate Bond Yield"),IF(OR(C52="",D52=""),"WARNING: Missing Country/Currency Data",IF(F52="","WARNING: Rate Missing — Fallback Value Used","")),IF(F52="","WARNING: Rate Missing — Fallback Value Used","")) -> WARNING: Missing Country/Currency Data
A53: U.S. 10-Year Treasury | B53: Entity 8 | C53: United States | D53: USD | E53: =EOMONTH(TODAY(),-1) -> 46142 | H53: =IF(OR(F53="",G53=""),"","Yes") | J53: WACC / CAPM | K53: =IF(OR(A53="Local 10-Year Government Bond Yield",A53="Local Market Risk Premium",A53="Local Corporate Bond Yield"),IF(OR(C53="",D53=""),"WARNING: Missing Country/Currency Data",IF(F53="","WARNING: Rate Missing — Fallback Value Used","")),IF(F53="","WARNING: Rate Missing — Fallback Value Used","")) -> WARNING: Rate Missing — Fallback Value Used
A54: U.S. Market Risk Premium | B54: Entity 8 | C54: United States | D54: USD | E54: =EOMONTH(TODAY(),-1) -> 46142 | H54: =IF(OR(F54="",G54=""),"","Yes") | J54: CAPM | K54: =IF(OR(A54="Local 10-Year Government Bond Yield",A54="Local Market Risk Premium",A54="Local Corporate Bond Yield"),IF(OR(C54="",D54=""),"WARNING: Missing Country/Currency Data",IF(F54="","WARNING: Rate Missing — Fallback Value Used","")),IF(F54="","WARNING: Rate Missing — Fallback Value Used","")) -> WARNING: Rate Missing — Fallback Value Used
A55: U.S. Corporate Bond Yield | B55: Entity 8 | C55: United States | D55: USD | E55: =EOMONTH(TODAY(),-1) -> 46142 | H55: =IF(OR(F55="",G55=""),"","Yes") | J55: WACC / Loan Readiness | K55: =IF(OR(A55="Local 10-Year Government Bond Yield",A55="Local Market Risk Premium",A55="Local Corporate Bond Yield"),IF(OR(C55="",D55=""),"WARNING: Missing Country/Currency Data",IF(F55="","WARNING: Rate Missing — Fallback Value Used","")),IF(F55="","WARNING: Rate Missing — Fallback Value Used","")) -> WARNING: Rate Missing — Fallback Value Used
A56: Beta | B56: Entity 8 | C56: United States | D56: USD | E56: =EOMONTH(TODAY(),-1) -> 46142 | H56: =IF(OR(F56="",G56=""),"","Yes") | J56: CAPM | K56: =IF(OR(A56="Local 10-Year Government Bond Yield",A56="Local Market Risk Premium",A56="Local Corporate Bond Yield"),IF(OR(C56="",D56=""),"WARNING: Missing Country/Currency Data",IF(F56="","WARNING: Rate Missing — Fallback Value Used","")),IF(F56="","WARNING: Rate Missing — Fallback Value Used","")) -> WARNING: Rate Missing — Fallback Value Used
A57: Local 10-Year Government Bond Yield | B57: Entity 8 | C57: =IF(Entity_Ownership!F11="","",Entity_Ownership!F11) | D57: =IF(Entity_Ownership!G11="","",Entity_Ownership!G11) | E57: =EOMONTH(TODAY(),-1) -> 46142 | H57: =IF(OR(F57="",G57=""),"","Yes") | J57: WACC / CAPM | K57: =IF(OR(A57="Local 10-Year Government Bond Yield",A57="Local Market Risk Premium",A57="Local Corporate Bond Yield"),IF(OR(C57="",D57=""),"WARNING: Missing Country/Currency Data",IF(F57="","WARNING: Rate Missing — Fallback Value Used","")),IF(F57="","WARNING: Rate Missing — Fallback Value Used","")) -> WARNING: Missing Country/Currency Data
A58: Local Market Risk Premium | B58: Entity 8 | C58: =IF(Entity_Ownership!F11="","",Entity_Ownership!F11) | D58: =IF(Entity_Ownership!G11="","",Entity_Ownership!G11) | E58: =EOMONTH(TODAY(),-1) -> 46142 | H58: =IF(OR(F58="",G58=""),"","Yes") | J58: CAPM | K58: =IF(OR(A58="Local 10-Year Government Bond Yield",A58="Local Market Risk Premium",A58="Local Corporate Bond Yield"),IF(OR(C58="",D58=""),"WARNING: Missing Country/Currency Data",IF(F58="","WARNING: Rate Missing — Fallback Value Used","")),IF(F58="","WARNING: Rate Missing — Fallback Value Used","")) -> WARNING: Missing Country/Currency Data
A59: Local Corporate Bond Yield | B59: Entity 8 | C59: =IF(Entity_Ownership!F11="","",Entity_Ownership!F11) | D59: =IF(Entity_Ownership!G11="","",Entity_Ownership!G11) | E59: =EOMONTH(TODAY(),-1) -> 46142 | H59: =IF(OR(F59="",G59=""),"","Yes") | J59: WACC / Loan Readiness | K59: =IF(OR(A59="Local 10-Year Government Bond Yield",A59="Local Market Risk Premium",A59="Local Corporate Bond Yield"),IF(OR(C59="",D59=""),"WARNING: Missing Country/Currency Data",IF(F59="","WARNING: Rate Missing — Fallback Value Used","")),IF(F59="","WARNING: Rate Missing — Fallback Value Used","")) -> WARNING: Missing Country/Currency Data
A60: U.S. 10-Year Treasury | B60: Entity 9 | C60: United States | D60: USD | E60: =EOMONTH(TODAY(),-1) -> 46142 | H60: =IF(OR(F60="",G60=""),"","Yes") | J60: WACC / CAPM | K60: =IF(OR(A60="Local 10-Year Government Bond Yield",A60="Local Market Risk Premium",A60="Local Corporate Bond Yield"),IF(OR(C60="",D60=""),"WARNING: Missing Country/Currency Data",IF(F60="","WARNING: Rate Missing — Fallback Value Used","")),IF(F60="","WARNING: Rate Missing — Fallback Value Used","")) -> WARNING: Rate Missing — Fallback Value Used
A61: U.S. Market Risk Premium | B61: Entity 9 | C61: United States | D61: USD | E61: =EOMONTH(TODAY(),-1) -> 46142 | H61: =IF(OR(F61="",G61=""),"","Yes") | J61: CAPM | K61: =IF(OR(A61="Local 10-Year Government Bond Yield",A61="Local Market Risk Premium",A61="Local Corporate Bond Yield"),IF(OR(C61="",D61=""),"WARNING: Missing Country/Currency Data",IF(F61="","WARNING: Rate Missing — Fallback Value Used","")),IF(F61="","WARNING: Rate Missing — Fallback Value Used","")) -> WARNING: Rate Missing — Fallback Value Used
A62: U.S. Corporate Bond Yield | B62: Entity 9 | C62: United States | D62: USD | E62: =EOMONTH(TODAY(),-1) -> 46142 | H62: =IF(OR(F62="",G62=""),"","Yes") | J62: WACC / Loan Readiness | K62: =IF(OR(A62="Local 10-Year Government Bond Yield",A62="Local Market Risk Premium",A62="Local Corporate Bond Yield"),IF(OR(C62="",D62=""),"WARNING: Missing Country/Currency Data",IF(F62="","WARNING: Rate Missing — Fallback Value Used","")),IF(F62="","WARNING: Rate Missing — Fallback Value Used","")) -> WARNING: Rate Missing — Fallback Value Used
A63: Beta | B63: Entity 9 | C63: United States | D63: USD | E63: =EOMONTH(TODAY(),-1) -> 46142 | H63: =IF(OR(F63="",G63=""),"","Yes") | J63: CAPM | K63: =IF(OR(A63="Local 10-Year Government Bond Yield",A63="Local Market Risk Premium",A63="Local Corporate Bond Yield"),IF(OR(C63="",D63=""),"WARNING: Missing Country/Currency Data",IF(F63="","WARNING: Rate Missing — Fallback Value Used","")),IF(F63="","WARNING: Rate Missing — Fallback Value Used","")) -> WARNING: Rate Missing — Fallback Value Used
A64: Local 10-Year Government Bond Yield | B64: Entity 9 | C64: =IF(Entity_Ownership!F12="","",Entity_Ownership!F12) | D64: =IF(Entity_Ownership!G12="","",Entity_Ownership!G12) | E64: =EOMONTH(TODAY(),-1) -> 46142 | H64: =IF(OR(F64="",G64=""),"","Yes") | J64: WACC / CAPM | K64: =IF(OR(A64="Local 10-Year Government Bond Yield",A64="Local Market Risk Premium",A64="Local Corporate Bond Yield"),IF(OR(C64="",D64=""),"WARNING: Missing Country/Currency Data",IF(F64="","WARNING: Rate Missing — Fallback Value Used","")),IF(F64="","WARNING: Rate Missing — Fallback Value Used","")) -> WARNING: Missing Country/Currency Data
A65: Local Market Risk Premium | B65: Entity 9 | C65: =IF(Entity_Ownership!F12="","",Entity_Ownership!F12) | D65: =IF(Entity_Ownership!G12="","",Entity_Ownership!G12) | E65: =EOMONTH(TODAY(),-1) -> 46142 | H65: =IF(OR(F65="",G65=""),"","Yes") | J65: CAPM | K65: =IF(OR(A65="Local 10-Year Government Bond Yield",A65="Local Market Risk Premium",A65="Local Corporate Bond Yield"),IF(OR(C65="",D65=""),"WARNING: Missing Country/Currency Data",IF(F65="","WARNING: Rate Missing — Fallback Value Used","")),IF(F65="","WARNING: Rate Missing — Fallback Value Used","")) -> WARNING: Missing Country/Currency Data
A66: Local Corporate Bond Yield | B66: Entity 9 | C66: =IF(Entity_Ownership!F12="","",Entity_Ownership!F12) | D66: =IF(Entity_Ownership!G12="","",Entity_Ownership!G12) | E66: =EOMONTH(TODAY(),-1) -> 46142 | H66: =IF(OR(F66="",G66=""),"","Yes") | J66: WACC / Loan Readiness | K66: =IF(OR(A66="Local 10-Year Government Bond Yield",A66="Local Market Risk Premium",A66="Local Corporate Bond Yield"),IF(OR(C66="",D66=""),"WARNING: Missing Country/Currency Data",IF(F66="","WARNING: Rate Missing — Fallback Value Used","")),IF(F66="","WARNING: Rate Missing — Fallback Value Used","")) -> WARNING: Missing Country/Currency Data
A67: U.S. 10-Year Treasury | B67: Entity 10 | C67: United States | D67: USD | E67: =EOMONTH(TODAY(),-1) -> 46142 | H67: =IF(OR(F67="",G67=""),"","Yes") | J67: WACC / CAPM | K67: =IF(OR(A67="Local 10-Year Government Bond Yield",A67="Local Market Risk Premium",A67="Local Corporate Bond Yield"),IF(OR(C67="",D67=""),"WARNING: Missing Country/Currency Data",IF(F67="","WARNING: Rate Missing — Fallback Value Used","")),IF(F67="","WARNING: Rate Missing — Fallback Value Used","")) -> WARNING: Rate Missing — Fallback Value Used
A68: U.S. Market Risk Premium | B68: Entity 10 | C68: United States | D68: USD | E68: =EOMONTH(TODAY(),-1) -> 46142 | H68: =IF(OR(F68="",G68=""),"","Yes") | J68: CAPM | K68: =IF(OR(A68="Local 10-Year Government Bond Yield",A68="Local Market Risk Premium",A68="Local Corporate Bond Yield"),IF(OR(C68="",D68=""),"WARNING: Missing Country/Currency Data",IF(F68="","WARNING: Rate Missing — Fallback Value Used","")),IF(F68="","WARNING: Rate Missing — Fallback Value Used","")) -> WARNING: Rate Missing — Fallback Value Used
A69: U.S. Corporate Bond Yield | B69: Entity 10 | C69: United States | D69: USD | E69: =EOMONTH(TODAY(),-1) -> 46142 | H69: =IF(OR(F69="",G69=""),"","Yes") | J69: WACC / Loan Readiness | K69: =IF(OR(A69="Local 10-Year Government Bond Yield",A69="Local Market Risk Premium",A69="Local Corporate Bond Yield"),IF(OR(C69="",D69=""),"WARNING: Missing Country/Currency Data",IF(F69="","WARNING: Rate Missing — Fallback Value Used","")),IF(F69="","WARNING: Rate Missing — Fallback Value Used","")) -> WARNING: Rate Missing — Fallback Value Used
A70: Beta | B70: Entity 10 | C70: United States | D70: USD | E70: =EOMONTH(TODAY(),-1) -> 46142 | H70: =IF(OR(F70="",G70=""),"","Yes") | J70: CAPM | K70: =IF(OR(A70="Local 10-Year Government Bond Yield",A70="Local Market Risk Premium",A70="Local Corporate Bond Yield"),IF(OR(C70="",D70=""),"WARNING: Missing Country/Currency Data",IF(F70="","WARNING: Rate Missing — Fallback Value Used","")),IF(F70="","WARNING: Rate Missing — Fallback Value Used","")) -> WARNING: Rate Missing — Fallback Value Used
A71: Local 10-Year Government Bond Yield | B71: Entity 10 | C71: =IF(Entity_Ownership!F13="","",Entity_Ownership!F13) | D71: =IF(Entity_Ownership!G13="","",Entity_Ownership!G13) | E71: =EOMONTH(TODAY(),-1) -> 46142 | H71: =IF(OR(F71="",G71=""),"","Yes") | J71: WACC / CAPM | K71: =IF(OR(A71="Local 10-Year Government Bond Yield",A71="Local Market Risk Premium",A71="Local Corporate Bond Yield"),IF(OR(C71="",D71=""),"WARNING: Missing Country/Currency Data",IF(F71="","WARNING: Rate Missing — Fallback Value Used","")),IF(F71="","WARNING: Rate Missing — Fallback Value Used","")) -> WARNING: Missing Country/Currency Data
A72: Local Market Risk Premium | B72: Entity 10 | C72: =IF(Entity_Ownership!F13="","",Entity_Ownership!F13) | D72: =IF(Entity_Ownership!G13="","",Entity_Ownership!G13) | E72: =EOMONTH(TODAY(),-1) -> 46142 | H72: =IF(OR(F72="",G72=""),"","Yes") | J72: CAPM | K72: =IF(OR(A72="Local 10-Year Government Bond Yield",A72="Local Market Risk Premium",A72="Local Corporate Bond Yield"),IF(OR(C72="",D72=""),"WARNING: Missing Country/Currency Data",IF(F72="","WARNING: Rate Missing — Fallback Value Used","")),IF(F72="","WARNING: Rate Missing — Fallback Value Used","")) -> WARNING: Missing Country/Currency Data
A73: Local Corporate Bond Yield | B73: Entity 10 | C73: =IF(Entity_Ownership!F13="","",Entity_Ownership!F13) | D73: =IF(Entity_Ownership!G13="","",Entity_Ownership!G13) | E73: =EOMONTH(TODAY(),-1) -> 46142 | H73: =IF(OR(F73="",G73=""),"","Yes") | J73: WACC / Loan Readiness | K73: =IF(OR(A73="Local 10-Year Government Bond Yield",A73="Local Market Risk Premium",A73="Local Corporate Bond Yield"),IF(OR(C73="",D73=""),"WARNING: Missing Country/Currency Data",IF(F73="","WARNING: Rate Missing — Fallback Value Used","")),IF(F73="","WARNING: Rate Missing — Fallback Value Used","")) -> WARNING: Missing Country/Currency Data

Sheet Audit_Log_Rates
A1: AUDIT LOG - RATES & FX
A3: Rate Name | B3: Entity | C3: Country | D3: Currency | E3: Previous Month-End Date | F3: Value Used | G3: Source URL | H3: AI_Fetched (Yes/No) | I3: Manual Override (Yes/No) | J3: Override Reason | K3: Override Date | L3: User Initials | M3: Purpose in Model
A4: =IF(Global_Rates!A4="","",Global_Rates!A4) -> U.S. 10-Year Treasury | B4: =IF(Global_Rates!B4="","",Global_Rates!B4) -> Entity 1 | C4: =IF(Global_Rates!C4="","",Global_Rates!C4) -> United States | D4: =IF(Global_Rates!D4="","",Global_Rates!D4) -> USD | E4: =IF(Global_Rates!E4="","",Global_Rates!E4) -> 46142 | F4: =IF(Global_Rates!F4="","",Global_Rates!F4) | G4: =IF(Global_Rates!G4="","",Global_Rates!G4) | H4: =IF(Global_Rates!H4="","",Global_Rates!H4) | I4: =IF(Global_Rates!I4="","",Global_Rates!I4) | M4: =IF(Global_Rates!J4="","",Global_Rates!J4) -> WACC / CAPM
A5: =IF(Global_Rates!A5="","",Global_Rates!A5) -> U.S. Market Risk Premium | B5: =IF(Global_Rates!B5="","",Global_Rates!B5) -> Entity 1 | C5: =IF(Global_Rates!C5="","",Global_Rates!C5) -> United States | D5: =IF(Global_Rates!D5="","",Global_Rates!D5) -> USD | E5: =IF(Global_Rates!E5="","",Global_Rates!E5) -> 46142 | F5: =IF(Global_Rates!F5="","",Global_Rates!F5) | G5: =IF(Global_Rates!G5="","",Global_Rates!G5) | H5: =IF(Global_Rates!H5="","",Global_Rates!H5) | I5: =IF(Global_Rates!I5="","",Global_Rates!I5) | M5: =IF(Global_Rates!J5="","",Global_Rates!J5) -> CAPM
A6: =IF(Global_Rates!A6="","",Global_Rates!A6) -> U.S. Corporate Bond Yield | B6: =IF(Global_Rates!B6="","",Global_Rates!B6) -> Entity 1 | C6: =IF(Global_Rates!C6="","",Global_Rates!C6) -> United States | D6: =IF(Global_Rates!D6="","",Global_Rates!D6) -> USD | E6: =IF(Global_Rates!E6="","",Global_Rates!E6) -> 46142 | F6: =IF(Global_Rates!F6="","",Global_Rates!F6) | G6: =IF(Global_Rates!G6="","",Global_Rates!G6) | H6: =IF(Global_Rates!H6="","",Global_Rates!H6) | I6: =IF(Global_Rates!I6="","",Global_Rates!I6) | M6: =IF(Global_Rates!J6="","",Global_Rates!J6) -> WACC / Loan Readiness
A7: =IF(Global_Rates!A7="","",Global_Rates!A7) -> Beta | B7: =IF(Global_Rates!B7="","",Global_Rates!B7) -> Entity 1 | C7: =IF(Global_Rates!C7="","",Global_Rates!C7) -> United States | D7: =IF(Global_Rates!D7="","",Global_Rates!D7) -> USD | E7: =IF(Global_Rates!E7="","",Global_Rates!E7) -> 46142 | F7: =IF(Global_Rates!F7="","",Global_Rates!F7) | G7: =IF(Global_Rates!G7="","",Global_Rates!G7) | H7: =IF(Global_Rates!H7="","",Global_Rates!H7) | I7: =IF(Global_Rates!I7="","",Global_Rates!I7) | M7: =IF(Global_Rates!J7="","",Global_Rates!J7) -> CAPM
A8: =IF(Global_Rates!A8="","",Global_Rates!A8) -> Local 10-Year Government Bond Yield | B8: =IF(Global_Rates!B8="","",Global_Rates!B8) -> Entity 1 | C8: =IF(Global_Rates!C8="","",Global_Rates!C8) | D8: =IF(Global_Rates!D8="","",Global_Rates!D8) | E8: =IF(Global_Rates!E8="","",Global_Rates!E8) -> 46142 | F8: =IF(Global_Rates!F8="","",Global_Rates!F8) | G8: =IF(Global_Rates!G8="","",Global_Rates!G8) | H8: =IF(Global_Rates!H8="","",Global_Rates!H8) | I8: =IF(Global_Rates!I8="","",Global_Rates!I8) | M8: =IF(Global_Rates!J8="","",Global_Rates!J8) -> WACC / CAPM
A9: =IF(Global_Rates!A9="","",Global_Rates!A9) -> Local Market Risk Premium | B9: =IF(Global_Rates!B9="","",Global_Rates!B9) -> Entity 1 | C9: =IF(Global_Rates!C9="","",Global_Rates!C9) | D9: =IF(Global_Rates!D9="","",Global_Rates!D9) | E9: =IF(Global_Rates!E9="","",Global_Rates!E9) -> 46142 | F9: =IF(Global_Rates!F9="","",Global_Rates!F9) | G9: =IF(Global_Rates!G9="","",Global_Rates!G9) | H9: =IF(Global_Rates!H9="","",Global_Rates!H9) | I9: =IF(Global_Rates!I9="","",Global_Rates!I9) | M9: =IF(Global_Rates!J9="","",Global_Rates!J9) -> CAPM
A10: =IF(Global_Rates!A10="","",Global_Rates!A10) -> Local Corporate Bond Yield | B10: =IF(Global_Rates!B10="","",Global_Rates!B10) -> Entity 1 | C10: =IF(Global_Rates!C10="","",Global_Rates!C10) | D10: =IF(Global_Rates!D10="","",Global_Rates!D10) | E10: =IF(Global_Rates!E10="","",Global_Rates!E10) -> 46142 | F10: =IF(Global_Rates!F10="","",Global_Rates!F10) | G10: =IF(Global_Rates!G10="","",Global_Rates!G10) | H10: =IF(Global_Rates!H10="","",Global_Rates!H10) | I10: =IF(Global_Rates!I10="","",Global_Rates!I10) | M10: =IF(Global_Rates!J10="","",Global_Rates!J10) -> WACC / Loan Readiness
A11: =IF(Global_Rates!A11="","",Global_Rates!A11) -> U.S. 10-Year Treasury | B11: =IF(Global_Rates!B11="","",Global_Rates!B11) -> Entity 2 | C11: =IF(Global_Rates!C11="","",Global_Rates!C11) -> United States | D11: =IF(Global_Rates!D11="","",Global_Rates!D11) -> USD | E11: =IF(Global_Rates!E11="","",Global_Rates!E11) -> 46142 | F11: =IF(Global_Rates!F11="","",Global_Rates!F11) | G11: =IF(Global_Rates!G11="","",Global_Rates!G11) | H11: =IF(Global_Rates!H11="","",Global_Rates!H11) | I11: =IF(Global_Rates!I11="","",Global_Rates!I11) | M11: =IF(Global_Rates!J11="","",Global_Rates!J11) -> WACC / CAPM
A12: =IF(Global_Rates!A12="","",Global_Rates!A12) -> U.S. Market Risk Premium | B12: =IF(Global_Rates!B12="","",Global_Rates!B12) -> Entity 2 | C12: =IF(Global_Rates!C12="","",Global_Rates!C12) -> United States | D12: =IF(Global_Rates!D12="","",Global_Rates!D12) -> USD | E12: =IF(Global_Rates!E12="","",Global_Rates!E12) -> 46142 | F12: =IF(Global_Rates!F12="","",Global_Rates!F12) | G12: =IF(Global_Rates!G12="","",Global_Rates!G12) | H12: =IF(Global_Rates!H12="","",Global_Rates!H12) | I12: =IF(Global_Rates!I12="","",Global_Rates!I12) | M12: =IF(Global_Rates!J12="","",Global_Rates!J12) -> CAPM
A13: =IF(Global_Rates!A13="","",Global_Rates!A13) -> U.S. Corporate Bond Yield | B13: =IF(Global_Rates!B13="","",Global_Rates!B13) -> Entity 2 | C13: =IF(Global_Rates!C13="","",Global_Rates!C13) -> United States | D13: =IF(Global_Rates!D13="","",Global_Rates!D13) -> USD | E13: =IF(Global_Rates!E13="","",Global_Rates!E13) -> 46142 | F13: =IF(Global_Rates!F13="","",Global_Rates!F13) | G13: =IF(Global_Rates!G13="","",Global_Rates!G13) | H13: =IF(Global_Rates!H13="","",Global_Rates!H13) | I13: =IF(Global_Rates!I13="","",Global_Rates!I13) | M13: =IF(Global_Rates!J13="","",Global_Rates!J13) -> WACC / Loan Readiness
A14: =IF(Global_Rates!A14="","",Global_Rates!A14) -> Beta | B14: =IF(Global_Rates!B14="","",Global_Rates!B14) -> Entity 2 | C14: =IF(Global_Rates!C14="","",Global_Rates!C14) -> United States | D14: =IF(Global_Rates!D14="","",Global_Rates!D14) -> USD | E14: =IF(Global_Rates!E14="","",Global_Rates!E14) -> 46142 | F14: =IF(Global_Rates!F14="","",Global_Rates!F14) | G14: =IF(Global_Rates!G14="","",Global_Rates!G14) | H14: =IF(Global_Rates!H14="","",Global_Rates!H14) | I14: =IF(Global_Rates!I14="","",Global_Rates!I14) | M14: =IF(Global_Rates!J14="","",Global_Rates!J14) -> CAPM
A15: =IF(Global_Rates!A15="","",Global_Rates!A15) -> Local 10-Year Government Bond Yield | B15: =IF(Global_Rates!B15="","",Global_Rates!B15) -> Entity 2 | C15: =IF(Global_Rates!C15="","",Global_Rates!C15) | D15: =IF(Global_Rates!D15="","",Global_Rates!D15) | E15: =IF(Global_Rates!E15="","",Global_Rates!E15) -> 46142 | F15: =IF(Global_Rates!F15="","",Global_Rates!F15) | G15: =IF(Global_Rates!G15="","",Global_Rates!G15) | H15: =IF(Global_Rates!H15="","",Global_Rates!H15) | I15: =IF(Global_Rates!I15="","",Global_Rates!I15) | M15: =IF(Global_Rates!J15="","",Global_Rates!J15) -> WACC / CAPM
... A73: =IF(Global_Rates!A73="","",Global_Rates!A73) -> Local Corporate Bond Yield | B73: =IF(Global_Rates!B73="","",Global_Rates!B73) -> Entity 10 | C73: =IF(Global_Rates!C73="","",Global_Rates!C73) | D73: =IF(Global_Rates!D73="","",Global_Rates!D73) | E73: =IF(Global_Rates!E73="","",Global_Rates!E73) -> 46142 | F73: =IF(Global_Rates!F73="","",Global_Rates!F73) | G73: =IF(Global_Rates!G73="","",Global_Rates!G73) | H73: =IF(Global_Rates!H73="","",Global_Rates!H73) | I73: =IF(Global_Rates!I73="","",Global_Rates!I73) | M73: =IF(Global_Rates!J73="","",Global_Rates!J73) -> WACC / Loan Readiness
A75: FX Rate Log | B75: Entity | C75: Currency | D75: FX Rate | E75: Source URL | F75: AI_Fetched
A76: ="FX Conversion" -> FX Conversion | B76: ="Entity 1" -> Entity 1 | C76: =IF(FX_Conversion!B4="","",FX_Conversion!B4) | D76: =IF(FX_Conversion!C4="","",FX_Conversion!C4) | E76: =IF(FX_Conversion!D4="","",FX_Conversion!D4) | F76: =IF(FX_Conversion!E4="","",FX_Conversion!E4)
A77: ="FX Conversion" -> FX Conversion | B77: ="Entity 2" -> Entity 2 | C77: =IF(FX_Conversion!B5="","",FX_Conversion!B5) | D77: =IF(FX_Conversion!C5="","",FX_Conversion!C5) | E77: =IF(FX_Conversion!D5="","",FX_Conversion!D5) | F77: =IF(FX_Conversion!E5="","",FX_Conversion!E5)
A78: ="FX Conversion" -> FX Conversion | B78: ="Entity 3" -> Entity 3 | C78: =IF(FX_Conversion!B6="","",FX_Conversion!B6) | D78: =IF(FX_Conversion!C6="","",FX_Conversion!C6) | E78: =IF(FX_Conversion!D6="","",FX_Conversion!D6) | F78: =IF(FX_Conversion!E6="","",FX_Conversion!E6)
A79: ="FX Conversion" -> FX Conversion | B79: ="Entity 4" -> Entity 4 | C79: =IF(FX_Conversion!B7="","",FX_Conversion!B7) | D79: =IF(FX_Conversion!C7="","",FX_Conversion!C7) | E79: =IF(FX_Conversion!D7="","",FX_Conversion!D7) | F79: =IF(FX_Conversion!E7="","",FX_Conversion!E7)
A80: ="FX Conversion" -> FX Conversion | B80: ="Entity 5" -> Entity 5 | C80: =IF(FX_Conversion!B8="","",FX_Conversion!B8) | D80: =IF(FX_Conversion!C8="","",FX_Conversion!C8) | E80: =IF(FX_Conversion!D8="","",FX_Conversion!D8) | F80: =IF(FX_Conversion!E8="","",FX_Conversion!E8)
A81: ="FX Conversion" -> FX Conversion | B81: ="Entity 6" -> Entity 6 | C81: =IF(FX_Conversion!B9="","",FX_Conversion!B9) | D81: =IF(FX_Conversion!C9="","",FX_Conversion!C9) | E81: =IF(FX_Conversion!D9="","",FX_Conversion!D9) | F81: =IF(FX_Conversion!E9="","",FX_Conversion!E9)
A82: ="FX Conversion" -> FX Conversion | B82: ="Entity 7" -> Entity 7 | C82: =IF(FX_Conversion!B10="","",FX_Conversion!B10) | D82: =IF(FX_Conversion!C10="","",FX_Conversion!C10) | E82: =IF(FX_Conversion!D10="","",FX_Conversion!D10) | F82: =IF(FX_Conversion!E10="","",FX_Conversion!E10)
A83: ="FX Conversion" -> FX Conversion | B83: ="Entity 8" -> Entity 8 | C83: =IF(FX_Conversion!B11="","",FX_Conversion!B11) | D83: =IF(FX_Conversion!C11="","",FX_Conversion!C11) | E83: =IF(FX_Conversion!D11="","",FX_Conversion!D11) | F83: =IF(FX_Conversion!E11="","",FX_Conversion!E11)
A84: ="FX Conversion" -> FX Conversion | B84: ="Entity 9" -> Entity 9 | C84: =IF(FX_Conversion!B12="","",FX_Conversion!B12) | D84: =IF(FX_Conversion!C12="","",FX_Conversion!C12) | E84: =IF(FX_Conversion!D12="","",FX_Conversion!D12) | F84: =IF(FX_Conversion!E12="","",FX_Conversion!E12)
A85: ="FX Conversion" -> FX Conversion | B85: ="Entity 10" -> Entity 10 | C85: =IF(FX_Conversion!B13="","",FX_Conversion!B13) | D85: =IF(FX_Conversion!C13="","",FX_Conversion!C13) | E85: =IF(FX_Conversion!D13="","",FX_Conversion!D13) | F85: =IF(FX_Conversion!E13="","",FX_Conversion!E13)
A86: Historical Snapshot | B86: Date Logic | C86: Value | D86: {=IFERROR(INDEX(Global_Rates!$F$4:$F$73,MATCH(1,(Global_Rates!$A$4:$A$73="Local 10-Year Government Bond Yield")*(Global_Rates!$B$4:$B$73=A86),0)),"")} | E86: {=IFERROR(INDEX(Global_Rates!$F$4:$F$73,MATCH(1,(Global_Rates!$A$4:$A$73="Local Market Risk Premium")*(Global_Rates!$B$4:$B$73=A86),0)),"")} | F86: {=IFERROR(INDEX(Global_Rates!$F$4:$F$73,MATCH(1,(Global_Rates!$A$4:$A$73="Local Corporate Bond Yield")*(Global_Rates!$B$4:$B$73=A86),0)),"")}
A87: Previous month | B87: =EOMONTH(TODAY(),-1) -> 46142 | D87: {=IFERROR(INDEX(Global_Rates!$F$4:$F$73,MATCH(1,(Global_Rates!$A$4:$A$73="Local 10-Year Government Bond Yield")*(Global_Rates!$B$4:$B$73=A87),0)),"")} | E87: {=IFERROR(INDEX(Global_Rates!$F$4:$F$73,MATCH(1,(Global_Rates!$A$4:$A$73="Local Market Risk Premium")*(Global_Rates!$B$4:$B$73=A87),0)),"")} | F87: {=IFERROR(INDEX(Global_Rates!$F$4:$F$73,MATCH(1,(Global_Rates!$A$4:$A$73="Local Corporate Bond Yield")*(Global_Rates!$B$4:$B$73=A87),0)),"")}
A88: Previous quarter | B88: =EOMONTH(TODAY(),-3) -> 46081 | D88: {=IFERROR(INDEX(Global_Rates!$F$4:$F$73,MATCH(1,(Global_Rates!$A$4:$A$73="Local 10-Year Government Bond Yield")*(Global_Rates!$B$4:$B$73=A88),0)),"")} | E88: {=IFERROR(INDEX(Global_Rates!$F$4:$F$73,MATCH(1,(Global_Rates!$A$4:$A$73="Local Market Risk Premium")*(Global_Rates!$B$4:$B$73=A88),0)),"")} | F88: {=IFERROR(INDEX(Global_Rates!$F$4:$F$73,MATCH(1,(Global_Rates!$A$4:$A$73="Local Corporate Bond Yield")*(Global_Rates!$B$4:$B$73=A88),0)),"")}
A89: Previous year | B89: =EOMONTH(TODAY(),-12) -> 45808 | D89: {=IFERROR(INDEX(Global_Rates!$F$4:$F$73,MATCH(1,(Global_Rates!$A$4:$A$73="Local 10-Year Government Bond Yield")*(Global_Rates!$B$4:$B$73=A89),0)),"")} | E89: {=IFERROR(INDEX(Global_Rates!$F$4:$F$73,MATCH(1,(Global_Rates!$A$4:$A$73="Local Market Risk Premium")*(Global_Rates!$B$4:$B$73=A89),0)),"")} | F89: {=IFERROR(INDEX(Global_Rates!$F$4:$F$73,MATCH(1,(Global_Rates!$A$4:$A$73="Local Corporate Bond Yield")*(Global_Rates!$B$4:$B$73=A89),0)),"")}
A90: Entity 6 | B90: =IF(Entity_Ownership!G9="","",Entity_Ownership!G9) | C90: =IFERROR(INDEX(FX_Conversion!$C$4:$C$13,MATCH(A90,FX_Conversion!$A$4:$A$13,0)),"") -> 0 | D90: {=IFERROR(INDEX(Global_Rates!$F$4:$F$73,MATCH(1,(Global_Rates!$A$4:$A$73="Local 10-Year Government Bond Yield")*(Global_Rates!$B$4:$B$73=A90),0)),"")} -> 0 | E90: {=IFERROR(INDEX(Global_Rates!$F$4:$F$73,MATCH(1,(Global_Rates!$A$4:$A$73="Local Market Risk Premium")*(Global_Rates!$B$4:$B$73=A90),0)),"")} -> 0 | F90: {=IFERROR(INDEX(Global_Rates!$F$4:$F$73,MATCH(1,(Global_Rates!$A$4:$A$73="Local Corporate Bond Yield")*(Global_Rates!$B$4:$B$73=A90),0)),"")} -> 0
A91: Entity 7 | B91: =IF(Entity_Ownership!G10="","",Entity_Ownership!G10) | C91: =IFERROR(INDEX(FX_Conversion!$C$4:$C$13,MATCH(A91,FX_Conversion!$A$4:$A$13,0)),"") -> 0 | D91: {=IFERROR(INDEX(Global_Rates!$F$4:$F$73,MATCH(1,(Global_Rates!$A$4:$A$73="Local 10-Year Government Bond Yield")*(Global_Rates!$B$4:$B$73=A91),0)),"")} -> 0 | E91: {=IFERROR(INDEX(Global_Rates!$F$4:$F$73,MATCH(1,(Global_Rates!$A$4:$A$73="Local Market Risk Premium")*(Global_Rates!$B$4:$B$73=A91),0)),"")} -> 0 | F91: {=IFERROR(INDEX(Global_Rates!$F$4:$F$73,MATCH(1,(Global_Rates!$A$4:$A$73="Local Corporate Bond Yield")*(Global_Rates!$B$4:$B$73=A91),0)),"")} -> 0
A92: Entity 8 | B92: =IF(Entity_Ownership!G11="","",Entity_Ownership!G11) | C92: =IFERROR(INDEX(FX_Conversion!$C$4:$C$13,MATCH(A92,FX_Conversion!$A$4:$A$13,0)),"") -> 0 | D92: {=IFERROR(INDEX(Global_Rates!$F$4:$F$73,MATCH(1,(Global_Rates!$A$4:$A$73="Local 10-Year Government Bond Yield")*(Global_Rates!$B$4:$B$73=A92),0)),"")} -> 0 | E92: {=IFERROR(INDEX(Global_Rates!$F$4:$F$73,MATCH(1,(Global_Rates!$A$4:$A$73="Local Market Risk Premium")*(Global_Rates!$B$4:$B$73=A92),0)),"")} -> 0 | F92: {=IFERROR(INDEX(Global_Rates!$F$4:$F$73,MATCH(1,(Global_Rates!$A$4:$A$73="Local Corporate Bond Yield")*(Global_Rates!$B$4:$B$73=A92),0)),"")} -> 0
A93: Entity 9 | B93: =IF(Entity_Ownership!G12="","",Entity_Ownership!G12) | C93: =IFERROR(INDEX(FX_Conversion!$C$4:$C$13,MATCH(A93,FX_Conversion!$A$4:$A$13,0)),"") -> 0 | D93: {=IFERROR(INDEX(Global_Rates!$F$4:$F$73,MATCH(1,(Global_Rates!$A$4:$A$73="Local 10-Year Government Bond Yield")*(Global_Rates!$B$4:$B$73=A93),0)),"")} -> 0 | E93: {=IFERROR(INDEX(Global_Rates!$F$4:$F$73,MATCH(1,(Global_Rates!$A$4:$A$73="Local Market Risk Premium")*(Global_Rates!$B$4:$B$73=A93),0)),"")} -> 0 | F93: {=IFERROR(INDEX(Global_Rates!$F$4:$F$73,MATCH(1,(Global_Rates!$A$4:$A$73="Local Corporate Bond Yield")*(Global_Rates!$B$4:$B$73=A93),0)),"")} -> 0
A94: Entity 10 | B94: =IF(Entity_Ownership!G13="","",Entity_Ownership!G13) | C94: =IFERROR(INDEX(FX_Conversion!$C$4:$C$13,MATCH(A94,FX_Conversion!$A$4:$A$13,0)),"") -> 0 | D94: {=IFERROR(INDEX(Global_Rates!$F$4:$F$73,MATCH(1,(Global_Rates!$A$4:$A$73="Local 10-Year Government Bond Yield")*(Global_Rates!$B$4:$B$73=A94),0)),"")} -> 0 | E94: {=IFERROR(INDEX(Global_Rates!$F$4:$F$73,MATCH(1,(Global_Rates!$A$4:$A$73="Local Market Risk Premium")*(Global_Rates!$B$4:$B$73=A94),0)),"")} -> 0 | F94: {=IFERROR(INDEX(Global_Rates!$F$4:$F$73,MATCH(1,(Global_Rates!$A$4:$A$73="Local Corporate Bond Yield")*(Global_Rates!$B$4:$B$73=A94),0)),"")} -> 0
A97: MISSING RATE WARNING SYSTEM | B97: Fallback Value | C97: Impact on Valuation
A98: =IF(COUNTIF(Global_Rates!K4:K73,"WARNING*")>0,"WARNING: Rate Missing — Fallback Value Used","All Required Rates Present") -> WARNING: Rate Missing — Fallback Value Used | B98: Manual override or analyst-entered fallback | C98: May affect WACC, FX conversion, valuation, and loan readiness outputs
A101: HISTORICAL RATE SNAPSHOT | B101: Value | C101: Notes
A102: Previous month | C102: Use previous month-end values
A103: Previous quarter | C103: Enter comparison values as needed
A104: Previous year | C104: Enter comparison values as needed
A107: Timestamp | B107: Rate Name | C107: Country | D107: Success/Fail | E107: Fallback Used (Yes/No)
D108: Fail | E108: Yes
D109: Fail | E109: Yes
D110: Fail | E110: Yes
D111: Fail | E111: Yes
D112: Fail | E112: Yes

Sheet Entity_Ownership
A1: ENTITY OWNERSHIP & JV MODELING
A3: Entity Name | B3: Parent Entity | C3: Ownership % | D3: JV Partner Name | E3: JV Partner Ownership % | F3: Country | G3: Currency | H3: Contribution Type | I3: Contribution Amount | J3: Distribution Rules | K3: Waterfall Tier | L3: Notes | M3: Warning
A4: Entity 1 | M4: =IF(OR(F4="",G4=""),"WARNING: Missing Country/Currency Data","") -> WARNING: Missing Country/Currency Data
A5: Entity 2 | M5: =IF(OR(F5="",G5=""),"WARNING: Missing Country/Currency Data","") -> WARNING: Missing Country/Currency Data
A6: Entity 3 | M6: =IF(OR(F6="",G6=""),"WARNING: Missing Country/Currency Data","") -> WARNING: Missing Country/Currency Data
A7: Entity 4 | M7: =IF(OR(F7="",G7=""),"WARNING: Missing Country/Currency Data","") -> WARNING: Missing Country/Currency Data
A8: Entity 5 | M8: =IF(OR(F8="",G8=""),"WARNING: Missing Country/Currency Data","") -> WARNING: Missing Country/Currency Data
A9: Entity 6 | M9: =IF(OR(F9="",G9=""),"WARNING: Missing Country/Currency Data","") -> WARNING: Missing Country/Currency Data
A10: Entity 7 | M10: =IF(OR(F10="",G10=""),"WARNING: Missing Country/Currency Data","") -> WARNING: Missing Country/Currency Data
A11: Entity 8 | M11: =IF(OR(F11="",G11=""),"WARNING: Missing Country/Currency Data","") -> WARNING: Missing Country/Currency Data
A12: Entity 9 | M12: =IF(OR(F12="",G12=""),"WARNING: Missing Country/Currency Data","") -> WARNING: Missing Country/Currency Data
A13: Entity 10 | M13: =IF(OR(F13="",G13=""),"WARNING: Missing Country/Currency Data","") -> WARNING: Missing Country/Currency Data
A15: JV / OWNERSHIP SUPPORT NOTES
A16: Ownership Trees | B16: Supports parent/sub ownership mapping
A17: JV Profit Splits | B17: Use Ownership % and JV Partner Ownership % for split modeling
A18: JV Cash Waterfalls | B18: Document distribution rules and waterfall tiers here
A19: JV Exit Modeling | B19: Capture partner economics and ownership-adjusted consolidation

Sheet Loan_Readiness
A1: LOAN READINESS
A3: Key Formulas
A4: DSCR = EBITDA / Total_Debt_Service
A5: Interest_Coverage = EBIT / Interest_Expense
A6: Fixed_Charge_Coverage = (EBITDA - Capex) / Fixed_Charges
A7: Debt_to_EBITDA = Total_Debt / EBITDA
A8: Loan_Capacity = EBITDA / Required_DSCR
A10: Entity | B10: EBITDA | C10: Total_Debt_Service | D10: DSCR | E10: EBIT | F10: Interest_Expense | G10: Interest_Coverage | H10: Capex | I10: Fixed_Charges | J10: Fixed_Charge_Coverage | K10: Total_Debt | L10: Debt_to_EBITDA | M10: Required_DSCR | N10: Loan_Capacity | O10: Warning
A11: Entity 1 | B11: =N(Fin_Inputs_Entity1!F9) -> 0 | D11: =IF(OR(C11="",C11=0),"",B11/C11) | E11: =N(Fin_Inputs_Entity1!F11) -> 0 | F11: =N(Fin_Inputs_Entity1!F12) -> 0 | G11: =IF(OR(F11="",F11=0),"",E11/F11) | H11: =N(Fin_Inputs_Entity1!F36) -> 0 | J11: =IF(OR(I11="",I11=0),"",(B11-H11)/I11) | K11: =N(Fin_Inputs_Entity1!F26)+N(Fin_Inputs_Entity1!F27) -> 0 | L11: =IF(OR(B11="",B11=0),"",K11/B11) | N11: =IF(OR(M11="",M11=0),"",B11/M11) | O11: =IF(C11="","WARNING: Debt schedule missing","")&IF(COUNT(Fin_Inputs_Entity1!B5:F37)<=2,IF(C11="","; ","")&"WARNING: Only 1-2 years of data","")&IF((N(Fin_Inputs_Entity1!F21)-N(Fin_Inputs_Entity1!F24)-N(Fin_Inputs_Entity1!F25))<0,IF(OR(C11="",COUNT(Fin_Inputs_Entity1!B5:F37)<=2),"; ","")&"WARNING: Negative working capital","")&IF(N(Fin_Inputs_Entity1!F5)<N(Fin_Inputs_Entity1!E5),IF(OR(C11="",COUNT(Fin_Inputs_Entity1!B5:F37)<=2,(N(Fin_Inputs_Entity1!F21)-N(Fin_Inputs_Entity1!F24)-N(Fin_Inputs_Entity1!F25))<0),"; ","")&"WARNING: Declining revenue","") -> WARNING: Debt schedule missing; WARNING: Only 1-2 years of data
A12: Entity 2 | B12: =N(Fin_Inputs_Entity2!F9) -> 0 | D12: =IF(OR(C12="",C12=0),"",B12/C12) | E12: =N(Fin_Inputs_Entity2!F11) -> 0 | F12: =N(Fin_Inputs_Entity2!F12) -> 0 | G12: =IF(OR(F12="",F12=0),"",E12/F12) | H12: =N(Fin_Inputs_Entity2!F36) -> 0 | J12: =IF(OR(I12="",I12=0),"",(B12-H12)/I12) | K12: =N(Fin_Inputs_Entity2!F26)+N(Fin_Inputs_Entity2!F27) -> 0 | L12: =IF(OR(B12="",B12=0),"",K12/B12) | N12: =IF(OR(M12="",M12=0),"",B12/M12) | O12: =IF(C12="","WARNING: Debt schedule missing","")&IF(COUNT(Fin_Inputs_Entity2!B5:F37)<=2,IF(C12="","; ","")&"WARNING: Only 1-2 years of data","")&IF((N(Fin_Inputs_Entity2!F21)-N(Fin_Inputs_Entity2!F24)-N(Fin_Inputs_Entity2!F25))<0,IF(OR(C12="",COUNT(Fin_Inputs_Entity2!B5:F37)<=2),"; ","")&"WARNING: Negative working capital","")&IF(N(Fin_Inputs_Entity2!F5)<N(Fin_Inputs_Entity2!E5),IF(OR(C12="",COUNT(Fin_Inputs_Entity2!B5:F37)<=2,(N(Fin_Inputs_Entity2!F21)-N(Fin_Inputs_Entity2!F24)-N(Fin_Inputs_Entity2!F25))<0),"; ","")&"WARNING: Declining revenue","") -> WARNING: Debt schedule missing; WARNING: Only 1-2 years of data
A13: Entity 3 | B13: =N(Fin_Inputs_Entity3!F9) -> 0 | D13: =IF(OR(C13="",C13=0),"",B13/C13) | E13: =N(Fin_Inputs_Entity3!F11) -> 0 | F13: =N(Fin_Inputs_Entity3!F12) -> 0 | G13: =IF(OR(F13="",F13=0),"",E13/F13) | H13: =N(Fin_Inputs_Entity3!F36) -> 0 | J13: =IF(OR(I13="",I13=0),"",(B13-H13)/I13) | K13: =N(Fin_Inputs_Entity3!F26)+N(Fin_Inputs_Entity3!F27) -> 0 | L13: =IF(OR(B13="",B13=0),"",K13/B13) | N13: =IF(OR(M13="",M13=0),"",B13/M13) | O13: =IF(C13="","WARNING: Debt schedule missing","")&IF(COUNT(Fin_Inputs_Entity3!B5:F37)<=2,IF(C13="","; ","")&"WARNING: Only 1-2 years of data","")&IF((N(Fin_Inputs_Entity3!F21)-N(Fin_Inputs_Entity3!F24)-N(Fin_Inputs_Entity3!F25))<0,IF(OR(C13="",COUNT(Fin_Inputs_Entity3!B5:F37)<=2),"; ","")&"WARNING: Negative working capital","")&IF(N(Fin_Inputs_Entity3!F5)<N(Fin_Inputs_Entity3!E5),IF(OR(C13="",COUNT(Fin_Inputs_Entity3!B5:F37)<=2,(N(Fin_Inputs_Entity3!F21)-N(Fin_Inputs_Entity3!F24)-N(Fin_Inputs_Entity3!F25))<0),"; ","")&"WARNING: Declining revenue","") -> WARNING: Debt schedule missing; WARNING: Only 1-2 years of data
A14: Entity 4 | B14: =N(Fin_Inputs_Entity4!F9) -> 0 | D14: =IF(OR(C14="",C14=0),"",B14/C14) | E14: =N(Fin_Inputs_Entity4!F11) -> 0 | F14: =N(Fin_Inputs_Entity4!F12) -> 0 | G14: =IF(OR(F14="",F14=0),"",E14/F14) | H14: =N(Fin_Inputs_Entity4!F36) -> 0 | J14: =IF(OR(I14="",I14=0),"",(B14-H14)/I14) | K14: =N(Fin_Inputs_Entity4!F26)+N(Fin_Inputs_Entity4!F27) -> 0 | L14: =IF(OR(B14="",B14=0),"",K14/B14) | N14: =IF(OR(M14="",M14=0),"",B14/M14) | O14: =IF(C14="","WARNING: Debt schedule missing","")&IF(COUNT(Fin_Inputs_Entity4!B5:F37)<=2,IF(C14="","; ","")&"WARNING: Only 1-2 years of data","")&IF((N(Fin_Inputs_Entity4!F21)-N(Fin_Inputs_Entity4!F24)-N(Fin_Inputs_Entity4!F25))<0,IF(OR(C14="",COUNT(Fin_Inputs_Entity4!B5:F37)<=2),"; ","")&"WARNING: Negative working capital","")&IF(N(Fin_Inputs_Entity4!F5)<N(Fin_Inputs_Entity4!E5),IF(OR(C14="",COUNT(Fin_Inputs_Entity4!B5:F37)<=2,(N(Fin_Inputs_Entity4!F21)-N(Fin_Inputs_Entity4!F24)-N(Fin_Inputs_Entity4!F25))<0),"; ","")&"WARNING: Declining revenue","") -> WARNING: Debt schedule missing; WARNING: Only 1-2 years of data
A15: Entity 5 | B15: =N(Fin_Inputs_Entity5!F9) -> 0 | D15: =IF(OR(C15="",C15=0),"",B15/C15) | E15: =N(Fin_Inputs_Entity5!F11) -> 0 | F15: =N(Fin_Inputs_Entity5!F12) -> 0 | G15: =IF(OR(F15="",F15=0),"",E15/F15) | H15: =N(Fin_Inputs_Entity5!F36) -> 0 | J15: =IF(OR(I15="",I15=0),"",(B15-H15)/I15) | K15: =N(Fin_Inputs_Entity5!F26)+N(Fin_Inputs_Entity5!F27) -> 0 | L15: =IF(OR(B15="",B15=0),"",K15/B15) | N15: =IF(OR(M15="",M15=0),"",B15/M15) | O15: =IF(C15="","WARNING: Debt schedule missing","")&IF(COUNT(Fin_Inputs_Entity5!B5:F37)<=2,IF(C15="","; ","")&"WARNING: Only 1-2 years of data","")&IF((N(Fin_Inputs_Entity5!F21)-N(Fin_Inputs_Entity5!F24)-N(Fin_Inputs_Entity5!F25))<0,IF(OR(C15="",COUNT(Fin_Inputs_Entity5!B5:F37)<=2),"; ","")&"WARNING: Negative working capital","")&IF(N(Fin_Inputs_Entity5!F5)<N(Fin_Inputs_Entity5!E5),IF(OR(C15="",COUNT(Fin_Inputs_Entity5!B5:F37)<=2,(N(Fin_Inputs_Entity5!F21)-N(Fin_Inputs_Entity5!F24)-N(Fin_Inputs_Entity5!F25))<0),"; ","")&"WARNING: Declining revenue","") -> WARNING: Debt schedule missing; WARNING: Only 1-2 years of data
A16: Entity 6 | B16: =N(Fin_Inputs_Entity6!F9) -> 0 | D16: =IF(OR(C16="",C16=0),"",B16/C16) | E16: =N(Fin_Inputs_Entity6!F11) -> 0 | F16: =N(Fin_Inputs_Entity6!F12) -> 0 | G16: =IF(OR(F16="",F16=0),"",E16/F16) | H16: =N(Fin_Inputs_Entity6!F36) -> 0 | J16: =IF(OR(I16="",I16=0),"",(B16-H16)/I16) | K16: =N(Fin_Inputs_Entity6!F26)+N(Fin_Inputs_Entity6!F27) -> 0 | L16: =IF(OR(B16="",B16=0),"",K16/B16) | N16: =IF(OR(M16="",M16=0),"",B16/M16) | O16: =IF(C16="","WARNING: Debt schedule missing","")&IF(COUNT(Fin_Inputs_Entity6!B5:F37)<=2,IF(C16="","; ","")&"WARNING: Only 1-2 years of data","")&IF((N(Fin_Inputs_Entity6!F21)-N(Fin_Inputs_Entity6!F24)-N(Fin_Inputs_Entity6!F25))<0,IF(OR(C16="",COUNT(Fin_Inputs_Entity6!B5:F37)<=2),"; ","")&"WARNING: Negative working capital","")&IF(N(Fin_Inputs_Entity6!F5)<N(Fin_Inputs_Entity6!E5),IF(OR(C16="",COUNT(Fin_Inputs_Entity6!B5:F37)<=2,(N(Fin_Inputs_Entity6!F21)-N(Fin_Inputs_Entity6!F24)-N(Fin_Inputs_Entity6!F25))<0),"; ","")&"WARNING: Declining revenue","") -> WARNING: Debt schedule missing; WARNING: Only 1-2 years of data
A17: Entity 7 | B17: =N(Fin_Inputs_Entity7!F9) -> 0 | D17: =IF(OR(C17="",C17=0),"",B17/C17) | E17: =N(Fin_Inputs_Entity7!F11) -> 0 | F17: =N(Fin_Inputs_Entity7!F12) -> 0 | G17: =IF(OR(F17="",F17=0),"",E17/F17) | H17: =N(Fin_Inputs_Entity7!F36) -> 0 | J17: =IF(OR(I17="",I17=0),"",(B17-H17)/I17) | K17: =N(Fin_Inputs_Entity7!F26)+N(Fin_Inputs_Entity7!F27) -> 0 | L17: =IF(OR(B17="",B17=0),"",K17/B17) | N17: =IF(OR(M17="",M17=0),"",B17/M17) | O17: =IF(C17="","WARNING: Debt schedule missing","")&IF(COUNT(Fin_Inputs_Entity7!B5:F37)<=2,IF(C17="","; ","")&"WARNING: Only 1-2 years of data","")&IF((N(Fin_Inputs_Entity7!F21)-N(Fin_Inputs_Entity7!F24)-N(Fin_Inputs_Entity7!F25))<0,IF(OR(C17="",COUNT(Fin_Inputs_Entity7!B5:F37)<=2),"; ","")&"WARNING: Negative working capital","")&IF(N(Fin_Inputs_Entity7!F5)<N(Fin_Inputs_Entity7!E5),IF(OR(C17="",COUNT(Fin_Inputs_Entity7!B5:F37)<=2,(N(Fin_Inputs_Entity7!F21)-N(Fin_Inputs_Entity7!F24)-N(Fin_Inputs_Entity7!F25))<0),"; ","")&"WARNING: Declining revenue","") -> WARNING: Debt schedule missing; WARNING: Only 1-2 years of data
A18: Entity 8 | B18: =N(Fin_Inputs_Entity8!F9) -> 0 | D18: =IF(OR(C18="",C18=0),"",B18/C18) | E18: =N(Fin_Inputs_Entity8!F11) -> 0 | F18: =N(Fin_Inputs_Entity8!F12) -> 0 | G18: =IF(OR(F18="",F18=0),"",E18/F18) | H18: =N(Fin_Inputs_Entity8!F36) -> 0 | J18: =IF(OR(I18="",I18=0),"",(B18-H18)/I18) | K18: =N(Fin_Inputs_Entity8!F26)+N(Fin_Inputs_Entity8!F27) -> 0 | L18: =IF(OR(B18="",B18=0),"",K18/B18) | N18: =IF(OR(M18="",M18=0),"",B18/M18) | O18: =IF(C18="","WARNING: Debt schedule missing","")&IF(COUNT(Fin_Inputs_Entity8!B5:F37)<=2,IF(C18="","; ","")&"WARNING: Only 1-2 years of data","")&IF((N(Fin_Inputs_Entity8!F21)-N(Fin_Inputs_Entity8!F24)-N(Fin_Inputs_Entity8!F25))<0,IF(OR(C18="",COUNT(Fin_Inputs_Entity8!B5:F37)<=2),"; ","")&"WARNING: Negative working capital","")&IF(N(Fin_Inputs_Entity8!F5)<N(Fin_Inputs_Entity8!E5),IF(OR(C18="",COUNT(Fin_Inputs_Entity8!B5:F37)<=2,(N(Fin_Inputs_Entity8!F21)-N(Fin_Inputs_Entity8!F24)-N(Fin_Inputs_Entity8!F25))<0),"; ","")&"WARNING: Declining revenue","") -> WARNING: Debt schedule missing; WARNING: Only 1-2 years of data
A19: Entity 9 | B19: =N(Fin_Inputs_Entity9!F9) -> 0 | D19: =IF(OR(C19="",C19=0),"",B19/C19) | E19: =N(Fin_Inputs_Entity9!F11) -> 0 | F19: =N(Fin_Inputs_Entity9!F12) -> 0 | G19: =IF(OR(F19="",F19=0),"",E19/F19) | H19: =N(Fin_Inputs_Entity9!F36) -> 0 | J19: =IF(OR(I19="",I19=0),"",(B19-H19)/I19) | K19: =N(Fin_Inputs_Entity9!F26)+N(Fin_Inputs_Entity9!F27) -> 0 | L19: =IF(OR(B19="",B19=0),"",K19/B19) | N19: =IF(OR(M19="",M19=0),"",B19/M19) | O19: =IF(C19="","WARNING: Debt schedule missing","")&IF(COUNT(Fin_Inputs_Entity9!B5:F37)<=2,IF(C19="","; ","")&"WARNING: Only 1-2 years of data","")&IF((N(Fin_Inputs_Entity9!F21)-N(Fin_Inputs_Entity9!F24)-N(Fin_Inputs_Entity9!F25))<0,IF(OR(C19="",COUNT(Fin_Inputs_Entity9!B5:F37)<=2),"; ","")&"WARNING: Negative working capital","")&IF(N(Fin_Inputs_Entity9!F5)<N(Fin_Inputs_Entity9!E5),IF(OR(C19="",COUNT(Fin_Inputs_Entity9!B5:F37)<=2,(N(Fin_Inputs_Entity9!F21)-N(Fin_Inputs_Entity9!F24)-N(Fin_Inputs_Entity9!F25))<0),"; ","")&"WARNING: Declining revenue","") -> WARNING: Debt schedule missing; WARNING: Only 1-2 years of data
A20: Entity 10 | B20: =N(Fin_Inputs_Entity10!F9) -> 0 | D20: =IF(OR(C20="",C20=0),"",B20/C20) | E20: =N(Fin_Inputs_Entity10!F11) -> 0 | F20: =N(Fin_Inputs_Entity10!F12) -> 0 | G20: =IF(OR(F20="",F20=0),"",E20/F20) | H20: =N(Fin_Inputs_Entity10!F36) -> 0 | J20: =IF(OR(I20="",I20=0),"",(B20-H20)/I20) | K20: =N(Fin_Inputs_Entity10!F26)+N(Fin_Inputs_Entity10!F27) -> 0 | L20: =IF(OR(B20="",B20=0),"",K20/B20) | N20: =IF(OR(M20="",M20=0),"",B20/M20) | O20: =IF(C20="","WARNING: Debt schedule missing","")&IF(COUNT(Fin_Inputs_Entity10!B5:F37)<=2,IF(C20="","; ","")&"WARNING: Only 1-2 years of data","")&IF((N(Fin_Inputs_Entity10!F21)-N(Fin_Inputs_Entity10!F24)-N(Fin_Inputs_Entity10!F25))<0,IF(OR(C20="",COUNT(Fin_Inputs_Entity10!B5:F37)<=2),"; ","")&"WARNING: Negative working capital","")&IF(N(Fin_Inputs_Entity10!F5)<N(Fin_Inputs_Entity10!E5),IF(OR(C20="",COUNT(Fin_Inputs_Entity10!B5:F37)<=2,(N(Fin_Inputs_Entity10!F21)-N(Fin_Inputs_Entity10!F24)-N(Fin_Inputs_Entity10!F25))<0),"; ","")&"WARNING: Declining revenue","") -> WARNING: Debt schedule missing; WARNING: Only 1-2 years of data
A22: Entity | B22: Required_DSCR | C22: Loan_Capacity | D22: Warning
A23: Entity 1 | C23: =IF(OR(B23="",B23=0,B11=""),"",B11/B23) | D23: =IF(B23="","WARNING: Required_DSCR Missing","") -> WARNING: Required_DSCR Missing
A24: Entity 2 | C24: =IF(OR(B24="",B24=0,B12=""),"",B12/B24) | D24: =IF(B24="","WARNING: Required_DSCR Missing","") -> WARNING: Required_DSCR Missing
A25: Entity 3 | C25: =IF(OR(B25="",B25=0,B13=""),"",B13/B25) | D25: =IF(B25="","WARNING: Required_DSCR Missing","") -> WARNING: Required_DSCR Missing
A26: Entity 4 | C26: =IF(OR(B26="",B26=0,B14=""),"",B14/B26) | D26: =IF(B26="","WARNING: Required_DSCR Missing","") -> WARNING: Required_DSCR Missing
A27: Entity 5 | C27: =IF(OR(B27="",B27=0,B15=""),"",B15/B27) | D27: =IF(B27="","WARNING: Required_DSCR Missing","") -> WARNING: Required_DSCR Missing
A28: Entity 6 | C28: =IF(OR(B28="",B28=0,B16=""),"",B16/B28) | D28: =IF(B28="","WARNING: Required_DSCR Missing","") -> WARNING: Required_DSCR Missing
A29: Entity 7 | C29: =IF(OR(B29="",B29=0,B17=""),"",B17/B29) | D29: =IF(B29="","WARNING: Required_DSCR Missing","") -> WARNING: Required_DSCR Missing
A30: Entity 8 | C30: =IF(OR(B30="",B30=0,B18=""),"",B18/B30) | D30: =IF(B30="","WARNING: Required_DSCR Missing","") -> WARNING: Required_DSCR Missing
A31: Entity 9 | C31: =IF(OR(B31="",B31=0,B19=""),"",B19/B31) | D31: =IF(B31="","WARNING: Required_DSCR Missing","") -> WARNING: Required_DSCR Missing
A32: Entity 10 | C32: =IF(OR(B32="",B32=0,B20=""),"",B20/B32) | D32: =IF(B32="","WARNING: Required_DSCR Missing","") -> WARNING: Required_DSCR Missing

Sheet Business_Health_Score
A1: BUSINESS HEALTH SCORE
A3: Category | B3: Weight | C3: Score | D3: Weighted Score
A4: Profitability | B4: 0.2 | D4: =IF(C4="","",B4*C4)
A5: Liquidity | B5: 0.15 | D5: =IF(C5="","",B5*C5)
A6: Leverage | B6: 0.15 | D6: =IF(C6="","",B6*C6)
A7: Efficiency | B7: 0.15 | D7: =IF(C7="","",B7*C7)
A8: Cash Flow Stability | B8: 0.15 | D8: =IF(C8="","",B8*C8)
A9: Growth | B9: 0.2 | D9: =IF(C9="","",B9*C9)
A11: Total Health Score | B11: =SUM(D4:D9) -> 0
A13: Strengths
A14: Weaknesses
A15: Risk Indicators

Sheet Scenario_Analysis
A1: SCENARIO ANALYSIS
A2: Selected Scenario | E2: Selected Value
A3: Assumption | B3: Best Case | C3: Base Case | D3: Worst Case | E3: ="Selected Value" -> Selected Value
A4: Revenue growth | B4: 0.1 | C4: 0.05 | D4: -0.05 | E4: =IF($B$2="","",INDEX($B$4:$D$4,1,MATCH($B$2,$B$10:$D$10,0)))
A5: Margin changes | B5: 0.05 | C5: 0 | D5: -0.05 | E5: =IF($B$2="","",INDEX($B$5:$D$5,1,MATCH($B$2,$B$10:$D$10,0)))
A6: Expense sensitivity | B6: 0.02 | C6: 0 | D6: 0.03 | E6: =IF($B$2="","",INDEX($B$6:$D$6,1,MATCH($B$2,$B$10:$D$10,0)))
A7: Working capital changes | B7: 0.01 | C7: 0 | D7: 0.02 | E7: =IF($B$2="","",INDEX($B$7:$D$7,1,MATCH($B$2,$B$10:$D$10,0)))
A8: Debt service stress tests | B8: 0.01 | C8: 0 | D8: 0.03 | E8: =IF($B$2="","",INDEX($B$8:$D$8,1,MATCH($B$2,$B$10:$D$10,0)))
A10: Output | B10: Best Case | C10: Base Case | D10: Worst Case
A11: Projected Revenue | B11: =Consolidation!L4*(1+B4) -> 0 | C11: =Consolidation!L4*(1+C4) -> 0 | D11: =Consolidation!L4*(1+D4) -> 0
A12: Projected EBITDA | B12: =Consolidation!L5*(1+B5-B6) -> 0 | C12: =Consolidation!L5*(1+C5-C6) -> 0 | D12: =Consolidation!L5*(1+D5-D6) -> 0
A13: Projected Cash Flow | B13: =Consolidation!L6*(1+B4-B7) -> 0 | C13: =Consolidation!L6*(1+C4-C7) -> 0 | D13: =Consolidation!L6*(1+D4-D7) -> 0

Sheet SBA_Prep
A1: SBA PREP - BUSINESS ONLY
A3: Section | B3: Detail | C3: Status / Warning
A4: Ownership structure | B4: Reference Entity_Ownership sheet | C4: =IF(COUNTIF(Document_Intake_Checklist!B4:B15,"Ownership / Cap Table")=0,"WARNING: Missing ownership document","")
A5: Use of funds
A6: Business financial summary | B6: Reference Consolidation sheet
A7: Debt schedule | B7: Reference Loan_Readiness / checklist | C7: =IF(COUNTIF(Document_Intake_Checklist!B4:B15,"Debt Schedule")=0,"WARNING: Missing debt schedule","Check document status") -> Check document status
A8: Collateral summary
A9: SBA eligibility checklist

Sheet Exit_Readiness
A1: EXIT READINESS
A3: Metric / Section | B3: Value | C3: Warning / Notes
A4: Normalized EBITDA | B4: =IF(Adjustments!B21="",Consolidation!L5,Adjustments!B21) -> 0
A5: Quality of Earnings indicators | C5: Document QoE risks and normalization items
A6: Buyer red flags | C6: List buyer diligence concerns
A7: Value drivers | C7: List valuation and strategic upside drivers
A8: Exit score (0-100) | B8: =IF(B4="","",IF(Document_Intake_Checklist!B18="Complete",80,60)) -> 60 | C8: =IF(Document_Intake_Checklist!B18="WARNING: Missing Financial Documents","WARNING: Missing supporting documents may reduce exit readiness","") -> WARNING: Missing supporting documents may reduce exit readiness

Sheet Working_Capital_Optimization
A1: WORKING CAPITAL OPTIMIZATION
A3: Metric / Formula | B3: Value | C3: Notes
A4: Revenue | B4: =Consolidation!L4 -> 0
A5: COGS | B5: =SUM(N(Fin_Inputs_Entity1!F6)*IF(FX_Rate_Entity1="",1,FX_Rate_Entity1)*IF(Entity_Ownership!C4="",1,Entity_Ownership!C4),N(Fin_Inputs_Entity2!F6)*IF(FX_Rate_Entity2="",1,FX_Rate_Entity2)*IF(Entity_Ownership!C5="",1,Entity_Ownership!C5),N(Fin_Inputs_Entity3!F6)*IF(FX_Rate_Entity3="",1,FX_Rate_Entity3)*IF(Entity_Ownership!C6="",1,Entity_Ownership!C6),N(Fin_Inputs_Entity4!F6)*IF(FX_Rate_Entity4="",1,FX_Rate_Entity4)*IF(Entity_Ownership!C7="",1,Entity_Ownership!C7),N(Fin_Inputs_Entity5!F6)*IF(FX_Rate_Entity5="",1,FX_Rate_Entity5)*IF(Entity_Ownership!C8="",1,Entity_Ownership!C8),N(Fin_Inputs_Entity6!F6)*IF(FX_Rate_Entity6="",1,FX_Rate_Entity6)*IF(Entity_Ownership!C9="",1,Entity_Ownership!C9),N(Fin_Inputs_Entity7!F6)*IF(FX_Rate_Entity7="",1,FX_Rate_Entity7)*IF(Entity_Ownership!C10="",1,Entity_Ownership!C10),N(Fin_Inputs_Entity8!F6)*IF(FX_Rate_Entity8="",1,FX_Rate_Entity8)*IF(Entity_Ownership!C11="",1,Entity_Ownership!C11),N(Fin_Inputs_Entity9!F6)*IF(FX_Rate_Entity9="",1,FX_Rate_Entity9)*IF(Entity_Ownership!C12="",1,Entity_Ownership!C12),N(Fin_Inputs_Entity10!F6)*IF(FX_Rate_Entity10="",1,FX_Rate_Entity10)*IF(Entity_Ownership!C13="",1,Entity_Ownership!C13)) -> 0
A6: AR | B6: =SUM(N(Fin_Inputs_Entity1!F19)*IF(FX_Rate_Entity1="",1,FX_Rate_Entity1)*IF(Entity_Ownership!C4="",1,Entity_Ownership!C4),N(Fin_Inputs_Entity2!F19)*IF(FX_Rate_Entity2="",1,FX_Rate_Entity2)*IF(Entity_Ownership!C5="",1,Entity_Ownership!C5),N(Fin_Inputs_Entity3!F19)*IF(FX_Rate_Entity3="",1,FX_Rate_Entity3)*IF(Entity_Ownership!C6="",1,Entity_Ownership!C6),N(Fin_Inputs_Entity4!F19)*IF(FX_Rate_Entity4="",1,FX_Rate_Entity4)*IF(Entity_Ownership!C7="",1,Entity_Ownership!C7),N(Fin_Inputs_Entity5!F19)*IF(FX_Rate_Entity5="",1,FX_Rate_Entity5)*IF(Entity_Ownership!C8="",1,Entity_Ownership!C8),N(Fin_Inputs_Entity6!F19)*IF(FX_Rate_Entity6="",1,FX_Rate_Entity6)*IF(Entity_Ownership!C9="",1,Entity_Ownership!C9),N(Fin_Inputs_Entity7!F19)*IF(FX_Rate_Entity7="",1,FX_Rate_Entity7)*IF(Entity_Ownership!C10="",1,Entity_Ownership!C10),N(Fin_Inputs_Entity8!F19)*IF(FX_Rate_Entity8="",1,FX_Rate_Entity8)*IF(Entity_Ownership!C11="",1,Entity_Ownership!C11),N(Fin_Inputs_Entity9!F19)*IF(FX_Rate_Entity9="",1,FX_Rate_Entity9)*IF(Entity_Ownership!C12="",1,Entity_Ownership!C12),N(Fin_Inputs_Entity10!F19)*IF(FX_Rate_Entity10="",1,FX_Rate_Entity10)*IF(Entity_Ownership!C13="",1,Entity_Ownership!C13)) -> 0
A7: AP | B7: =SUM(N(Fin_Inputs_Entity1!F24)*IF(FX_Rate_Entity1="",1,FX_Rate_Entity1)*IF(Entity_Ownership!C4="",1,Entity_Ownership!C4),N(Fin_Inputs_Entity2!F24)*IF(FX_Rate_Entity2="",1,FX_Rate_Entity2)*IF(Entity_Ownership!C5="",1,Entity_Ownership!C5),N(Fin_Inputs_Entity3!F24)*IF(FX_Rate_Entity3="",1,FX_Rate_Entity3)*IF(Entity_Ownership!C6="",1,Entity_Ownership!C6),N(Fin_Inputs_Entity4!F24)*IF(FX_Rate_Entity4="",1,FX_Rate_Entity4)*IF(Entity_Ownership!C7="",1,Entity_Ownership!C7),N(Fin_Inputs_Entity5!F24)*IF(FX_Rate_Entity5="",1,FX_Rate_Entity5)*IF(Entity_Ownership!C8="",1,Entity_Ownership!C8),N(Fin_Inputs_Entity6!F24)*IF(FX_Rate_Entity6="",1,FX_Rate_Entity6)*IF(Entity_Ownership!C9="",1,Entity_Ownership!C9),N(Fin_Inputs_Entity7!F24)*IF(FX_Rate_Entity7="",1,FX_Rate_Entity7)*IF(Entity_Ownership!C10="",1,Entity_Ownership!C10),N(Fin_Inputs_Entity8!F24)*IF(FX_Rate_Entity8="",1,FX_Rate_Entity8)*IF(Entity_Ownership!C11="",1,Entity_Ownership!C11),N(Fin_Inputs_Entity9!F24)*IF(FX_Rate_Entity9="",1,FX_Rate_Entity9)*IF(Entity_Ownership!C12="",1,Entity_Ownership!C12),N(Fin_Inputs_Entity10!F24)*IF(FX_Rate_Entity10="",1,FX_Rate_Entity10)*IF(Entity_Ownership!C13="",1,Entity_Ownership!C13)) -> 0
A8: Inventory | B8: =SUM(N(Fin_Inputs_Entity1!F20)*IF(FX_Rate_Entity1="",1,FX_Rate_Entity1)*IF(Entity_Ownership!C4="",1,Entity_Ownership!C4),N(Fin_Inputs_Entity2!F20)*IF(FX_Rate_Entity2="",1,FX_Rate_Entity2)*IF(Entity_Ownership!C5="",1,Entity_Ownership!C5),N(Fin_Inputs_Entity3!F20)*IF(FX_Rate_Entity3="",1,FX_Rate_Entity3)*IF(Entity_Ownership!C6="",1,Entity_Ownership!C6),N(Fin_Inputs_Entity4!F20)*IF(FX_Rate_Entity4="",1,FX_Rate_Entity4)*IF(Entity_Ownership!C7="",1,Entity_Ownership!C7),N(Fin_Inputs_Entity5!F20)*IF(FX_Rate_Entity5="",1,FX_Rate_Entity5)*IF(Entity_Ownership!C8="",1,Entity_Ownership!C8),N(Fin_Inputs_Entity6!F20)*IF(FX_Rate_Entity6="",1,FX_Rate_Entity6)*IF(Entity_Ownership!C9="",1,Entity_Ownership!C9),N(Fin_Inputs_Entity7!F20)*IF(FX_Rate_Entity7="",1,FX_Rate_Entity7)*IF(Entity_Ownership!C10="",1,Entity_Ownership!C10),N(Fin_Inputs_Entity8!F20)*IF(FX_Rate_Entity8="",1,FX_Rate_Entity8)*IF(Entity_Ownership!C11="",1,Entity_Ownership!C11),N(Fin_Inputs_Entity9!F20)*IF(FX_Rate_Entity9="",1,FX_Rate_Entity9)*IF(Entity_Ownership!C12="",1,Entity_Ownership!C12),N(Fin_Inputs_Entity10!F20)*IF(FX_Rate_Entity10="",1,FX_Rate_Entity10)*IF(Entity_Ownership!C13="",1,Entity_Ownership!C13)) -> 0
A9: DSO | B9: =IF(OR(B4="",B4=0,B6=""),0,B6/(B4/365)) -> 0 | C9: DSO = AR / (Revenue/365)
A10: DPO | B10: =IF(OR(B5="",B5=0,B7=""),0,B7/(B5/365)) -> 0 | C10: DPO = AP / (COGS/365)
A11: DIO | B11: =IF(OR(B5="",B5=0,B8=""),0,B8/(B5/365)) -> 0 | C11: DIO = Inventory / (COGS/365)
A12: Cash_Conversion_Cycle | B12: =IFERROR(B9 + B11 - B10, "") -> 0 | C12: Cash_Conversion_Cycle = DSO + DIO - DPO

Sheet Valuation_Summary
A1: VALUATION SUMMARY
A3: Section | B3: Value | C3: Notes
A4: DCF Value | B4: =SUM(Valuation_Entity1!B34,Valuation_Entity2!B34,Valuation_Entity3!B34,Valuation_Entity4!B34,Valuation_Entity5!B34,Valuation_Entity6!B34,Valuation_Entity7!B34,Valuation_Entity8!B34,Valuation_Entity9!B34,Valuation_Entity10!B34) -> 0
A5: Multiples Value | B5: =SUM(Valuation_Entity1!B35,Valuation_Entity2!B35,Valuation_Entity3!B35,Valuation_Entity4!B35,Valuation_Entity5!B35,Valuation_Entity6!B35,Valuation_Entity7!B35,Valuation_Entity8!B35,Valuation_Entity9!B35,Valuation_Entity10!B35) -> 0
A6: Final Valuation | B6: =Consolidation!L9 -> 0
A7: Key KPIs | B7: Reference KPIs sheet
A8: Key Risks | B8: =IF(Consolidation!L11="","",Consolidation!L11) -> WARNING: Missing Data in One or More Entities
A9: Key Opportunities | B9: =IF(Scenario_Analysis!B2="","Base scenario in use",IF(Scenario_Analysis!B2="Worst Case","Scenario downside pressure on valuation",IF(Scenario_Analysis!B2="Best Case","Scenario upside optionality reflected","Base scenario in use"))) -> Base scenario in use
A10: Narrative Summary | B10: =IF(Scenario_Analysis!B2="","",Scenario_Analysis!B2)

Sheet Document_Intake_Checklist
A1: DOCUMENT INTAKE CHECKLIST | H1: ENTITY DOCUMENT COMPLETENESS
A3: Document Category | B3: Required Document | C3: Status | D3: Received Date | E3: Owner | F3: Warning | G3: Required Document | H3: Entity | I3: Financial Inputs | J3: Ownership | K3: Debt Schedule | L3: Forecast/Budget | M3: Missing Count | N3: Warning | O3: Entity 8 | P3: Entity 9 | Q3: Entity 10
A4: Corporate | B4: Articles / Formation Docs | F4: =IF(C4<>"Received","WARNING: Missing Financial Document","") -> WARNING: Missing Financial Document | G4: =B4 -> Articles / Formation Docs | H4: Entity 1 | I4: =IF(COUNT(Fin_Inputs_Entity1!B5:F37)>0,"Received","Missing") -> Missing | J4: =IF(AND(Entity_Ownership!F4<>"",Entity_Ownership!G4<>""),"Received","Missing") -> Missing | K4: =IF(OR(Fin_Inputs_Entity1!F26<>"",Fin_Inputs_Entity1!F27<>"",Fin_Inputs_Entity1!F12<>""),"Received","Missing") -> Missing | L4: =IF(COUNT(Fin_Inputs_Entity1!D5:F37)>0,"Received","Missing") -> Missing | M4: =COUNTIF(I4:L4,"Missing") -> 4 | N4: =IF(M4>0,"WARNING: Missing entity documents","") -> WARNING: Missing entity documents
A5: Corporate | B5: Ownership / Cap Table | F5: =IF(C5<>"Received","WARNING: Missing Financial Document","") -> WARNING: Missing Financial Document | G5: =B5 -> Ownership / Cap Table | H5: Entity 2 | I5: =IF(COUNT(Fin_Inputs_Entity2!B5:F37)>0,"Received","Missing") -> Missing | J5: =IF(AND(Entity_Ownership!F5<>"",Entity_Ownership!G5<>""),"Received","Missing") -> Missing | K5: =IF(OR(Fin_Inputs_Entity2!F26<>"",Fin_Inputs_Entity2!F27<>"",Fin_Inputs_Entity2!F12<>""),"Received","Missing") -> Missing | L5: =IF(COUNT(Fin_Inputs_Entity2!D5:F37)>0,"Received","Missing") -> Missing | M5: =COUNTIF(I5:L5,"Missing") -> 4 | N5: =IF(M5>0,"WARNING: Missing entity documents","") -> WARNING: Missing entity documents
A6: Financial | B6: 5 Years Income Statement | F6: =IF(C6<>"Received","WARNING: Missing Financial Document","") -> WARNING: Missing Financial Document | G6: =B6 -> 5 Years Income Statement | H6: Entity 3 | I6: =IF(COUNT(Fin_Inputs_Entity3!B5:F37)>0,"Received","Missing") -> Missing | J6: =IF(AND(Entity_Ownership!F6<>"",Entity_Ownership!G6<>""),"Received","Missing") -> Missing | K6: =IF(OR(Fin_Inputs_Entity3!F26<>"",Fin_Inputs_Entity3!F27<>"",Fin_Inputs_Entity3!F12<>""),"Received","Missing") -> Missing | L6: =IF(COUNT(Fin_Inputs_Entity3!D5:F37)>0,"Received","Missing") -> Missing | M6: =COUNTIF(I6:L6,"Missing") -> 4 | N6: =IF(M6>0,"WARNING: Missing entity documents","") -> WARNING: Missing entity documents
A7: Financial | B7: 5 Years Balance Sheet | F7: =IF(C7<>"Received","WARNING: Missing Financial Document","") -> WARNING: Missing Financial Document | G7: =B7 -> 5 Years Balance Sheet | H7: Entity 4 | I7: =IF(COUNT(Fin_Inputs_Entity4!B5:F37)>0,"Received","Missing") -> Missing | J7: =IF(AND(Entity_Ownership!F7<>"",Entity_Ownership!G7<>""),"Received","Missing") -> Missing | K7: =IF(OR(Fin_Inputs_Entity4!F26<>"",Fin_Inputs_Entity4!F27<>"",Fin_Inputs_Entity4!F12<>""),"Received","Missing") -> Missing | L7: =IF(COUNT(Fin_Inputs_Entity4!D5:F37)>0,"Received","Missing") -> Missing | M7: =COUNTIF(I7:L7,"Missing") -> 4 | N7: =IF(M7>0,"WARNING: Missing entity documents","") -> WARNING: Missing entity documents
A8: Financial | B8: 5 Years Cash Flow Statement | F8: =IF(C8<>"Received","WARNING: Missing Financial Document","") -> WARNING: Missing Financial Document | G8: =B8 -> 5 Years Cash Flow Statement | H8: Entity 5 | I8: =IF(COUNT(Fin_Inputs_Entity5!B5:F37)>0,"Received","Missing") -> Missing | J8: =IF(AND(Entity_Ownership!F8<>"",Entity_Ownership!G8<>""),"Received","Missing") -> Missing | K8: =IF(OR(Fin_Inputs_Entity5!F26<>"",Fin_Inputs_Entity5!F27<>"",Fin_Inputs_Entity5!F12<>""),"Received","Missing") -> Missing | L8: =IF(COUNT(Fin_Inputs_Entity5!D5:F37)>0,"Received","Missing") -> Missing | M8: =COUNTIF(I8:L8,"Missing") -> 4 | N8: =IF(M8>0,"WARNING: Missing entity documents","") -> WARNING: Missing entity documents
A9: Financial | B9: Tax Returns | F9: =IF(C9<>"Received","WARNING: Missing Financial Document","") -> WARNING: Missing Financial Document | G9: =B9 -> Tax Returns | H9: Entity 6 | I9: =IF(COUNT(Fin_Inputs_Entity6!B5:F37)>0,"Received","Missing") -> Missing | J9: =IF(AND(Entity_Ownership!F9<>"",Entity_Ownership!G9<>""),"Received","Missing") -> Missing | K9: =IF(OR(Fin_Inputs_Entity6!F26<>"",Fin_Inputs_Entity6!F27<>"",Fin_Inputs_Entity6!F12<>""),"Received","Missing") -> Missing | L9: =IF(COUNT(Fin_Inputs_Entity6!D5:F37)>0,"Received","Missing") -> Missing | M9: =COUNTIF(I9:L9,"Missing") -> 4 | N9: =IF(M9>0,"WARNING: Missing entity documents","") -> WARNING: Missing entity documents
A10: Debt | B10: Debt Schedule | F10: =IF(C10<>"Received","WARNING: Missing Financial Document","") -> WARNING: Missing Financial Document | G10: =B10 -> Debt Schedule | H10: Entity 7 | I10: =IF(COUNT(Fin_Inputs_Entity7!B5:F37)>0,"Received","Missing") -> Missing | J10: =IF(AND(Entity_Ownership!F10<>"",Entity_Ownership!G10<>""),"Received","Missing") -> Missing | K10: =IF(OR(Fin_Inputs_Entity7!F26<>"",Fin_Inputs_Entity7!F27<>"",Fin_Inputs_Entity7!F12<>""),"Received","Missing") -> Missing | L10: =IF(COUNT(Fin_Inputs_Entity7!D5:F37)>0,"Received","Missing") -> Missing | M10: =COUNTIF(I10:L10,"Missing") -> 4 | N10: =IF(M10>0,"WARNING: Missing entity documents","") -> WARNING: Missing entity documents
A11: Operations | B11: AR Aging | F11: =IF(C11<>"Received","WARNING: Missing Financial Document","") -> WARNING: Missing Financial Document | G11: =B11 -> AR Aging | H11: Entity 8 | I11: =IF(COUNT(Fin_Inputs_Entity8!B5:F37)>0,"Received","Missing") -> Missing | J11: =IF(AND(Entity_Ownership!F11<>"",Entity_Ownership!G11<>""),"Received","Missing") -> Missing | K11: =IF(OR(Fin_Inputs_Entity8!F26<>"",Fin_Inputs_Entity8!F27<>"",Fin_Inputs_Entity8!F12<>""),"Received","Missing") -> Missing | L11: =IF(COUNT(Fin_Inputs_Entity8!D5:F37)>0,"Received","Missing") -> Missing | M11: =COUNTIF(I11:L11,"Missing") -> 4 | N11: =IF(M11>0,"WARNING: Missing entity documents","") -> WARNING: Missing entity documents
A12: Operations | B12: AP Aging | F12: =IF(C12<>"Received","WARNING: Missing Financial Document","") -> WARNING: Missing Financial Document | G12: =B12 -> AP Aging | H12: Entity 9 | I12: =IF(COUNT(Fin_Inputs_Entity9!B5:F37)>0,"Received","Missing") -> Missing | J12: =IF(AND(Entity_Ownership!F12<>"",Entity_Ownership!G12<>""),"Received","Missing") -> Missing | K12: =IF(OR(Fin_Inputs_Entity9!F26<>"",Fin_Inputs_Entity9!F27<>"",Fin_Inputs_Entity9!F12<>""),"Received","Missing") -> Missing | L12: =IF(COUNT(Fin_Inputs_Entity9!D5:F37)>0,"Received","Missing") -> Missing | M12: =COUNTIF(I12:L12,"Missing") -> 4 | N12: =IF(M12>0,"WARNING: Missing entity documents","") -> WARNING: Missing entity documents
A13: Operations | B13: Inventory Rollforward | F13: =IF(C13<>"Received","WARNING: Missing Financial Document","") -> WARNING: Missing Financial Document | G13: =B13 -> Inventory Rollforward | H13: Entity 10 | I13: =IF(COUNT(Fin_Inputs_Entity10!B5:F37)>0,"Received","Missing") -> Missing | J13: =IF(AND(Entity_Ownership!F13<>"",Entity_Ownership!G13<>""),"Received","Missing") -> Missing | K13: =IF(OR(Fin_Inputs_Entity10!F26<>"",Fin_Inputs_Entity10!F27<>"",Fin_Inputs_Entity10!F12<>""),"Received","Missing") -> Missing | L13: =IF(COUNT(Fin_Inputs_Entity10!D5:F37)>0,"Received","Missing") -> Missing | M13: =COUNTIF(I13:L13,"Missing") -> 4 | N13: =IF(M13>0,"WARNING: Missing entity documents","") -> WARNING: Missing entity documents
A14: Valuation | B14: Forecast / Budget | F14: =IF(C14<>"Received","WARNING: Missing Financial Document","") -> WARNING: Missing Financial Document | G14: =B14 -> Forecast / Budget
A15: Collateral | B15: Collateral Summary | F15: =IF(C15<>"Received","WARNING: Missing Financial Document","") -> WARNING: Missing Financial Document | G15: =B15 -> Collateral Summary
A17: Missing Documents Count | B17: =SUM(H17:N17) -> 100 | G17: Missing Documents Count | H17: =COUNTIF(I4:I13,"<>Received") -> 10 | I17: =COUNTIF(I4:I13,"Missing") -> 10 | J17: =COUNTIF(J4:J13,"Missing") -> 10 | K17: =COUNTIF(K4:K13,"Missing") -> 10 | L17: =COUNTIF(L4:L13,"Missing") -> 10 | M17: =SUM(I17:L17) -> 40 | N17: =COUNTIF(N4:N13,"WARNING*") -> 10 | O17: =COUNTIF(O4:O15,"<>Received") -> 12 | P17: =COUNTIF(P4:P15,"<>Received") -> 12 | Q17: =COUNTIF(Q4:Q15,"<>Received") -> 12
A18: Overall Status | B18: =IF(B17>0,"WARNING: Missing Financial Documents","Complete") -> WARNING: Missing Financial Documents | G18: Status | H18: =IF(H17>0,"WARNING: Missing Financial Document","Complete") -> WARNING: Missing Financial Document | I18: =IF(I17>0,"WARNING: Missing Financial Document","Complete") -> WARNING: Missing Financial Document | J18: =IF(J17>0,"WARNING: Missing Financial Document","Complete") -> WARNING: Missing Financial Document | K18: =IF(K17>0,"WARNING: Missing Financial Document","Complete") -> WARNING: Missing Financial Document | L18: =IF(L17>0,"WARNING: Missing Financial Document","Complete") -> WARNING: Missing Financial Document | M18: =IF(M17>0,"WARNING: Missing Financial Document","Complete") -> WARNING: Missing Financial Document | N18: =IF(N17>0,"WARNING: Missing Financial Document","Complete") -> WARNING: Missing Financial Document | O18: =IF(O17>0,"WARNING: Missing Financial Document","Complete") -> WARNING: Missing Financial Document | ... Q18: =IF(Q17>0,"WARNING: Missing Financial Document","Complete") -> WARNING: Missing Financial Document

Sheet Valuation_Entity1
A1: VALUATION ANALYSIS - ENTITY 1
A3: SECTION A: WACC INPUTS
A4: Input | B4: Value | C4: Notes
A5: Risk Free Rate | B5: =IF(AND(Entity_Ownership!$F$4<>"",UPPER(Entity_Ownership!$F$4)<>"UNITED STATES",COUNTIFS(Global_Rates!$B$4:$B$73,"Entity 1",Global_Rates!$A$4:$A$73,"Local 10-Year Government Bond Yield",Global_Rates!$F$4:$F$73,"<>")>0),SUMIFS(Global_Rates!$F$4:$F$73,Global_Rates!$B$4:$B$73,"Entity 1",Global_Rates!$A$4:$A$73,"Local 10-Year Government Bond Yield"),IF(COUNTIFS(Global_Rates!$B$4:$B$73,"Entity 1",Global_Rates!$A$4:$A$73,"U.S. 10-Year Treasury",Global_Rates!$F$4:$F$73,"<>")>0,SUMIFS(Global_Rates!$F$4:$F$73,Global_Rates!$B$4:$B$73,"Entity 1",Global_Rates!$A$4:$A$73,"U.S. 10-Year Treasury"),"")) | C5: Rate used for CAPM
A6: Beta | B6: =IF(COUNTIFS(Global_Rates!$B$4:$B$73,"Entity 1",Global_Rates!$A$4:$A$73,"Beta",Global_Rates!$F$4:$F$73,"<>")>0,SUMIFS(Global_Rates!$F$4:$F$73,Global_Rates!$B$4:$B$73,"Entity 1",Global_Rates!$A$4:$A$73,"Beta"),"") | C6: Entity beta
A7: Market Risk Premium | B7: =IF(AND(Entity_Ownership!$F$4<>"",UPPER(Entity_Ownership!$F$4)<>"UNITED STATES",COUNTIFS(Global_Rates!$B$4:$B$73,"Entity 1",Global_Rates!$A$4:$A$73,"Local Market Risk Premium",Global_Rates!$F$4:$F$73,"<>")>0),SUMIFS(Global_Rates!$F$4:$F$73,Global_Rates!$B$4:$B$73,"Entity 1",Global_Rates!$A$4:$A$73,"Local Market Risk Premium"),IF(COUNTIFS(Global_Rates!$B$4:$B$73,"Entity 1",Global_Rates!$A$4:$A$73,"U.S. Market Risk Premium",Global_Rates!$F$4:$F$73,"<>")>0,SUMIFS(Global_Rates!$F$4:$F$73,Global_Rates!$B$4:$B$73,"Entity 1",Global_Rates!$A$4:$A$73,"U.S. Market Risk Premium"),"")) | C7: Rate used for CAPM
A8: Cost of Debt | B8: =IF(AND(Entity_Ownership!$F$4<>"",UPPER(Entity_Ownership!$F$4)<>"UNITED STATES",COUNTIFS(Global_Rates!$B$4:$B$73,"Entity 1",Global_Rates!$A$4:$A$73,"Local Corporate Bond Yield",Global_Rates!$F$4:$F$73,"<>")>0),SUMIFS(Global_Rates!$F$4:$F$73,Global_Rates!$B$4:$B$73,"Entity 1",Global_Rates!$A$4:$A$73,"Local Corporate Bond Yield"),IF(COUNTIFS(Global_Rates!$B$4:$B$73,"Entity 1",Global_Rates!$A$4:$A$73,"U.S. Corporate Bond Yield",Global_Rates!$F$4:$F$73,"<>")>0,SUMIFS(Global_Rates!$F$4:$F$73,Global_Rates!$B$4:$B$73,"Entity 1",Global_Rates!$A$4:$A$73,"U.S. Corporate Bond Yield"),"")) | C8: Pre-tax cost of debt
A9: Tax Rate | B9: =IF(OR(Fin_Inputs_Entity1!F13="",Fin_Inputs_Entity1!F11="",Fin_Inputs_Entity1!F11=0),"",ABS(Fin_Inputs_Entity1!F13/Fin_Inputs_Entity1!F11)) | C9: Taxes / EBIT
A10: Debt Weight | B10: =IF((N(Fin_Inputs_Entity1!F26)+N(Fin_Inputs_Entity1!F27)+N(Fin_Inputs_Entity1!F29))=0,"",(N(Fin_Inputs_Entity1!F26)+N(Fin_Inputs_Entity1!F27))/(N(Fin_Inputs_Entity1!F26)+N(Fin_Inputs_Entity1!F27)+N(Fin_Inputs_Entity1!F29))) | C10: Debt / (Debt + Equity)
A11: Equity Weight | B11: =IF((N(Fin_Inputs_Entity1!F26)+N(Fin_Inputs_Entity1!F27)+N(Fin_Inputs_Entity1!F29))=0,"",N(Fin_Inputs_Entity1!F29)/(N(Fin_Inputs_Entity1!F26)+N(Fin_Inputs_Entity1!F27)+N(Fin_Inputs_Entity1!F29))) | C11: Equity / (Debt + Equity)
A12: Cost of Equity | B12: =IF(COUNT(B5:B7)<3,"",B5+B6*B7) | C12: CAPM
A13: WACC | B13: =IF(COUNT(B8:B12)<5,"",(B11*B12)+(B10*B8*(1-B9))) | C13: Weighted average cost of capital
A14: FX Rate Used | B14: =IF(FX_Rate_Entity1="","",FX_Rate_Entity1) | C14: Previous month-end or override
A15: SECTION B: DCF MODEL
A16: Item
A17: Forecasted FCF | B17: Year 1 | C17: Year 2 | D17: Year 3 | E17: Year 4 | F17: Year 5 | G17: Terminal
A18: Terminal Growth Rate | B18: =IF(OR(Fin_Inputs_Entity1!B37="",B14=""),"",Fin_Inputs_Entity1!B37*B14*(1+N(Scenario_Analysis!$E$4)-N(Scenario_Analysis!$E$6)-N(Scenario_Analysis!$E$7))) | C18: =IF(OR(Fin_Inputs_Entity1!C37="",B14=""),"",Fin_Inputs_Entity1!C37*B14*(1+N(Scenario_Analysis!$E$4)-N(Scenario_Analysis!$E$6)-N(Scenario_Analysis!$E$7))) | D18: =IF(OR(Fin_Inputs_Entity1!D37="",B14=""),"",Fin_Inputs_Entity1!D37*B14*(1+N(Scenario_Analysis!$E$4)-N(Scenario_Analysis!$E$6)-N(Scenario_Analysis!$E$7))) | E18: =IF(OR(Fin_Inputs_Entity1!E37="",B14=""),"",Fin_Inputs_Entity1!E37*B14*(1+N(Scenario_Analysis!$E$4)-N(Scenario_Analysis!$E$6)-N(Scenario_Analysis!$E$7))) | F18: =IF(OR(Fin_Inputs_Entity1!F37="",B14=""),"",Fin_Inputs_Entity1!F37*B14*(1+N(Scenario_Analysis!$E$4)-N(Scenario_Analysis!$E$6)-N(Scenario_Analysis!$E$7)))
A19: Terminal Value | B19: 0.02 | G19: =IF(OR(F18="",B13="",B19="",B13<=B19),"",F18*(1+B19)/(B13-B19))
A20: Discount Factor | B20: =IF(B13="","",1/(1+B13)^1) | C20: =IF(B13="","",1/(1+B13)^2) | D20: =IF(B13="","",1/(1+B13)^3) | E20: =IF(B13="","",1/(1+B13)^4) | F20: =IF(B13="","",1/(1+B13)^5) | G20: =IF(B13="","",1/(1+B13)^5)
A21: PV of Cash Flows | B21: =IF(OR(B18="",B20=""),"",B18*B20) | C21: =IF(OR(C18="",C20=""),"",C18*C20) | D21: =IF(OR(D18="",D20=""),"",D18*D20) | E21: =IF(OR(E18="",E20=""),"",E18*E20) | F21: =IF(OR(F18="",F20=""),"",F18*F20) | G21: =IF(OR(G19="",G20=""),"",G19*G20)
A22: DCF Enterprise Value | B22: =IF(COUNT(B21:G21)=0,"",SUM(B21:G21)) | C22: =IF(OR(C18="",C21=""),"",C18*C21) | D22: =IF(OR(D18="",D21=""),"",D18*D21) | E22: =IF(OR(E18="",E21=""),"",E18*E21) | F22: =IF(OR(F18="",F21=""),"",F18*F21) | G22: =IF(OR(G20="",G21=""),"",G20*G21)
A23: DCF Enterprise Value | B23: =IF(COUNT(B22:G22)=0,"",SUM(B22:G22)) | H23: =IF(OR(F21="",B13="",B22="",B13<=B22),"",F21*(1+B22)/(B13-B22))
A25: Multiple
A26: Multiple | B26: Multiple Value | C26: Metric | D26: Implied EV
A27: EV/EBITDA | B27: 6 | C27: =IF(OR(Fin_Inputs_Entity1!F9="",B14=""),"",Fin_Inputs_Entity1!F9*B14) | D27: =IF(OR(B27="",C27=""),"",B27*C27)
A28: EV/Revenue | B28: 1.5 | C28: =IF(OR(Fin_Inputs_Entity1!F5="",B14=""),"",Fin_Inputs_Entity1!F5*B14) | D28: =IF(OR(B28="",C28=""),"",B28*C28)
A29: P/E | B29: 10 | C29: =IF(OR(Fin_Inputs_Entity1!F14="",B14=""),"",Fin_Inputs_Entity1!F14*B14) | D29: =IF(OR(B29="",C29=""),"",B29*C29)
A30: Average Multiples Value | B30: =IF(COUNT(D27:D29)=0,"",AVERAGE(D27:D29)) | D30: =IF(COUNT(D27:D29)=0,"",AVERAGE(D27:D29))
A31: Warning | B31: =IF(OR(Entity_Ownership!F4="",FX_Conversion!B4=""),"WARNING: Missing Country/Currency Data",IF(OR(B5="",B6="",B7="",B8="",B14=""),"WARNING: Incomplete CAPM / WACC / FX Chain","")) -> WARNING: Missing Country/Currency Data
A33: Item
A34: DCF Value | B34: =B23 | C34: USD pre-ownership
A35: Multiples Value | B35: =B30 | C35: USD pre-ownership
A36: Blended Value | B36: =IF(COUNT(B34:B35)=0,"",AVERAGE(B34:B35)) | C36: USD pre-ownership
A37: Final Valuation | B37: =IF(B36="","",B36*IF(Entity_Ownership!C4="",1,Entity_Ownership!C4)) | C37: USD ownership-adjusted
A39: Sensitivity Table
A40: WACC / g | B40: g -1% | C40: Base g | D40: g +1%
A41: WACC -1.0% | B41: =IF(OR($B$13="",$B$19="",$F$18="",($B$13-0.01)<=($B$19-0.01)),"",SUM($B$21:$F$21)+($F$18*(1+($B$19-0.01))/(($B$13-0.01)-($B$19-0.01)))/(1+($B$13-0.01))^5) -> #VALUE! | C41: =IF(OR($B$13="",$B$19="",$F$18="",($B$13-0.01)<=($B$19)),"",SUM($B$21:$F$21)+($F$18*(1+$B$19)/(($B$13-0.01)-$B$19))/(1+($B$13-0.01))^5) -> #VALUE! | D41: =IF(OR($B$13="",$B$19="",$F$18="",($B$13-0.01)<=($B$19+0.01)),"",SUM($B$21:$F$21)+($F$18*(1+($B$19+0.01))/(($B$13-0.01)-($B$19+0.01)))/(1+($B$13-0.01))^5) -> #VALUE!
A42: Base WACC | B42: =IF(OR($B$13="",$B$19="",$F$18="",($B$13)<=($B$19-0.01)),"",SUM($B$21:$F$21)+($F$18*(1+($B$19-0.01))/($B$13-($B$19-0.01)))/(1+$B$13)^5) | C42: =B22 | D42: =IF(OR($B$13="",$B$19="",$F$18="",($B$13)<=($B$19+0.01)),"",SUM($B$21:$F$21)+($F$18*(1+($B$19+0.01))/($B$13-($B$19+0.01)))/(1+$B$13)^5)
A43: WACC +1.0% | B43: =IF(OR($B$13="",$B$19="",$F$18="",($B$13+0.01)<=($B$19-0.01)),"",SUM($B$21:$F$21)+($F$18*(1+($B$19-0.01))/(($B$13+0.01)-($B$19-0.01)))/(1+($B$13+0.01))^5) -> #VALUE! | C43: =IF(OR($B$13="",$B$19="",$F$18="",($B$13+0.01)<=($B$19)),"",SUM($B$21:$F$21)+($F$18*(1+$B$19)/(($B$13+0.01)-$B$19))/(1+($B$13+0.01))^5) -> #VALUE! | D43: =IF(OR($B$13="",$B$19="",$F$18="",($B$13+0.01)<=($B$19+0.01)),"",SUM($B$21:$F$21)+($F$18*(1+($B$19+0.01))/(($B$13+0.01)-($B$19+0.01)))/(1+($B$13+0.01))^5) -> #VALUE!
A44: Local vs U.S. Override Logic | B44: If country <> USA and local rate exists, use local for Entity 1
A45: Warning | B45: =IF(OR(Entity_Ownership!F4="",Entity_Ownership!G4=""),"WARNING: Missing Country/Currency Data",IF(B13="","WARNING: Incomplete CAPM / WACC Chain","")) -> WARNING: Missing Country/Currency Data

Sheet Valuation_Entity2
A1: VALUATION ANALYSIS - ENTITY 2
A3: SECTION A: WACC INPUTS
A4: Input | B4: Value | C4: Notes
A5: Risk Free Rate | B5: =IF(AND(Entity_Ownership!$F$5<>"",UPPER(Entity_Ownership!$F$5)<>"UNITED STATES",COUNTIFS(Global_Rates!$B$4:$B$73,"Entity 2",Global_Rates!$A$4:$A$73,"Local 10-Year Government Bond Yield",Global_Rates!$F$4:$F$73,"<>")>0),SUMIFS(Global_Rates!$F$4:$F$73,Global_Rates!$B$4:$B$73,"Entity 2",Global_Rates!$A$4:$A$73,"Local 10-Year Government Bond Yield"),IF(COUNTIFS(Global_Rates!$B$4:$B$73,"Entity 2",Global_Rates!$A$4:$A$73,"U.S. 10-Year Treasury",Global_Rates!$F$4:$F$73,"<>")>0,SUMIFS(Global_Rates!$F$4:$F$73,Global_Rates!$B$4:$B$73,"Entity 2",Global_Rates!$A$4:$A$73,"U.S. 10-Year Treasury"),"")) | C5: Rate used for CAPM
A6: Beta | B6: =IF(COUNTIFS(Global_Rates!$B$4:$B$73,"Entity 2",Global_Rates!$A$4:$A$73,"Beta",Global_Rates!$F$4:$F$73,"<>")>0,SUMIFS(Global_Rates!$F$4:$F$73,Global_Rates!$B$4:$B$73,"Entity 2",Global_Rates!$A$4:$A$73,"Beta"),"") | C6: Entity beta
A7: Market Risk Premium | B7: =IF(AND(Entity_Ownership!$F$5<>"",UPPER(Entity_Ownership!$F$5)<>"UNITED STATES",COUNTIFS(Global_Rates!$B$4:$B$73,"Entity 2",Global_Rates!$A$4:$A$73,"Local Market Risk Premium",Global_Rates!$F$4:$F$73,"<>")>0),SUMIFS(Global_Rates!$F$4:$F$73,Global_Rates!$B$4:$B$73,"Entity 2",Global_Rates!$A$4:$A$73,"Local Market Risk Premium"),IF(COUNTIFS(Global_Rates!$B$4:$B$73,"Entity 2",Global_Rates!$A$4:$A$73,"U.S. Market Risk Premium",Global_Rates!$F$4:$F$73,"<>")>0,SUMIFS(Global_Rates!$F$4:$F$73,Global_Rates!$B$4:$B$73,"Entity 2",Global_Rates!$A$4:$A$73,"U.S. Market Risk Premium"),"")) | C7: Rate used for CAPM
A8: Cost of Debt | B8: =IF(AND(Entity_Ownership!$F$5<>"",UPPER(Entity_Ownership!$F$5)<>"UNITED STATES",COUNTIFS(Global_Rates!$B$4:$B$73,"Entity 2",Global_Rates!$A$4:$A$73,"Local Corporate Bond Yield",Global_Rates!$F$4:$F$73,"<>")>0),SUMIFS(Global_Rates!$F$4:$F$73,Global_Rates!$B$4:$B$73,"Entity 2",Global_Rates!$A$4:$A$73,"Local Corporate Bond Yield"),IF(COUNTIFS(Global_Rates!$B$4:$B$73,"Entity 2",Global_Rates!$A$4:$A$73,"U.S. Corporate Bond Yield",Global_Rates!$F$4:$F$73,"<>")>0,SUMIFS(Global_Rates!$F$4:$F$73,Global_Rates!$B$4:$B$73,"Entity 2",Global_Rates!$A$4:$A$73,"U.S. Corporate Bond Yield"),"")) | C8: Pre-tax cost of debt
A9: Tax Rate | B9: =IF(OR(Fin_Inputs_Entity2!F13="",Fin_Inputs_Entity2!F11="",Fin_Inputs_Entity2!F11=0),"",ABS(Fin_Inputs_Entity2!F13/Fin_Inputs_Entity2!F11)) | C9: Taxes / EBIT
A10: Debt Weight | B10: =IF((N(Fin_Inputs_Entity2!F26)+N(Fin_Inputs_Entity2!F27)+N(Fin_Inputs_Entity2!F29))=0,"",(N(Fin_Inputs_Entity2!F26)+N(Fin_Inputs_Entity2!F27))/(N(Fin_Inputs_Entity2!F26)+N(Fin_Inputs_Entity2!F27)+N(Fin_Inputs_Entity2!F29))) | C10: Debt / (Debt + Equity)
A11: Equity Weight | B11: =IF((N(Fin_Inputs_Entity2!F26)+N(Fin_Inputs_Entity2!F27)+N(Fin_Inputs_Entity2!F29))=0,"",N(Fin_Inputs_Entity2!F29)/(N(Fin_Inputs_Entity2!F26)+N(Fin_Inputs_Entity2!F27)+N(Fin_Inputs_Entity2!F29))) | C11: Equity / (Debt + Equity)
A12: Cost of Equity | B12: =IF(COUNT(B5:B7)<3,"",B5+B6*B7) | C12: CAPM
A13: WACC | B13: =IF(COUNT(B8:B12)<5,"",(B11*B12)+(B10*B8*(1-B9))) | C13: Weighted average cost of capital
A14: FX Rate Used | B14: =IF(FX_Rate_Entity2="","",FX_Rate_Entity2) | C14: Previous month-end or override
A15: SECTION B: DCF MODEL
A16: Item
A17: Forecasted FCF | B17: Year 1 | C17: Year 2 | D17: Year 3 | E17: Year 4 | F17: Year 5 | G17: Terminal
A18: Terminal Growth Rate | B18: =IF(OR(Fin_Inputs_Entity2!B37="",B14=""),"",Fin_Inputs_Entity2!B37*B14*(1+N(Scenario_Analysis!$E$4)-N(Scenario_Analysis!$E$6)-N(Scenario_Analysis!$E$7))) | C18: =IF(OR(Fin_Inputs_Entity2!C37="",B14=""),"",Fin_Inputs_Entity2!C37*B14*(1+N(Scenario_Analysis!$E$4)-N(Scenario_Analysis!$E$6)-N(Scenario_Analysis!$E$7))) | D18: =IF(OR(Fin_Inputs_Entity2!D37="",B14=""),"",Fin_Inputs_Entity2!D37*B14*(1+N(Scenario_Analysis!$E$4)-N(Scenario_Analysis!$E$6)-N(Scenario_Analysis!$E$7))) | E18: =IF(OR(Fin_Inputs_Entity2!E37="",B14=""),"",Fin_Inputs_Entity2!E37*B14*(1+N(Scenario_Analysis!$E$4)-N(Scenario_Analysis!$E$6)-N(Scenario_Analysis!$E$7))) | F18: =IF(OR(Fin_Inputs_Entity2!F37="",B14=""),"",Fin_Inputs_Entity2!F37*B14*(1+N(Scenario_Analysis!$E$4)-N(Scenario_Analysis!$E$6)-N(Scenario_Analysis!$E$7)))
A19: Terminal Value | B19: 0.02 | G19: =IF(OR(F18="",B13="",B19="",B13<=B19),"",F18*(1+B19)/(B13-B19))
A20: Discount Factor | B20: =IF(B13="","",1/(1+B13)^1) | C20: =IF(B13="","",1/(1+B13)^2) | D20: =IF(B13="","",1/(1+B13)^3) | E20: =IF(B13="","",1/(1+B13)^4) | F20: =IF(B13="","",1/(1+B13)^5) | G20: =IF(B13="","",1/(1+B13)^5)
A21: PV of Cash Flows | B21: =IF(OR(B18="",B20=""),"",B18*B20) | C21: =IF(OR(C18="",C20=""),"",C18*C20) | D21: =IF(OR(D18="",D20=""),"",D18*D20) | E21: =IF(OR(E18="",E20=""),"",E18*E20) | F21: =IF(OR(F18="",F20=""),"",F18*F20) | G21: =IF(OR(G19="",G20=""),"",G19*G20)
A22: DCF Enterprise Value | B22: =IF(COUNT(B21:G21)=0,"",SUM(B21:G21)) | C22: =IF(OR(C18="",C21=""),"",C18*C21) | D22: =IF(OR(D18="",D21=""),"",D18*D21) | E22: =IF(OR(E18="",E21=""),"",E18*E21) | F22: =IF(OR(F18="",F21=""),"",F18*F21) | G22: =IF(OR(G20="",G21=""),"",G20*G21)
A23: DCF Enterprise Value | B23: =IF(COUNT(B22:G22)=0,"",SUM(B22:G22)) | H23: =IF(OR(F21="",B13="",B22="",B13<=B22),"",F21*(1+B22)/(B13-B22))
A25: Multiple
A26: Multiple | B26: Multiple Value | C26: Metric | D26: Implied EV
A27: EV/EBITDA | B27: 6 | C27: =IF(OR(Fin_Inputs_Entity2!F9="",B14=""),"",Fin_Inputs_Entity2!F9*B14) | D27: =IF(OR(B27="",C27=""),"",B27*C27)
A28: EV/Revenue | B28: 1.5 | C28: =IF(OR(Fin_Inputs_Entity2!F5="",B14=""),"",Fin_Inputs_Entity2!F5*B14) | D28: =IF(OR(B28="",C28=""),"",B28*C28)
A29: P/E | B29: 10 | C29: =IF(OR(Fin_Inputs_Entity2!F14="",B14=""),"",Fin_Inputs_Entity2!F14*B14) | D29: =IF(OR(B29="",C29=""),"",B29*C29)
A30: Average Multiples Value | B30: =IF(COUNT(D27:D29)=0,"",AVERAGE(D27:D29)) | D30: =IF(COUNT(D27:D29)=0,"",AVERAGE(D27:D29))
A31: Warning | B31: =IF(OR(Entity_Ownership!F5="",FX_Conversion!B5=""),"WARNING: Missing Country/Currency Data",IF(OR(B5="",B6="",B7="",B8="",B14=""),"WARNING: Incomplete CAPM / WACC / FX Chain","")) -> WARNING: Missing Country/Currency Data
A33: Item
A34: DCF Value | B34: =B23 | C34: USD pre-ownership
A35: Multiples Value | B35: =B30 | C35: USD pre-ownership
A36: Blended Value | B36: =IF(COUNT(B34:B35)=0,"",AVERAGE(B34:B35)) | C36: USD pre-ownership
A37: Final Valuation | B37: =IF(B36="","",B36*IF(Entity_Ownership!C5="",1,Entity_Ownership!C5)) | C37: USD ownership-adjusted
A39: Sensitivity Table
A40: WACC / g | B40: g -1% | C40: Base g | D40: g +1%
A41: WACC -1.0% | B41: =IF(OR($B$13="",$B$19="",$F$18="",($B$13-0.01)<=($B$19-0.01)),"",SUM($B$21:$F$21)+($F$18*(1+($B$19-0.01))/(($B$13-0.01)-($B$19-0.01)))/(1+($B$13-0.01))^5) -> #VALUE! | C41: =IF(OR($B$13="",$B$19="",$F$18="",($B$13-0.01)<=($B$19)),"",SUM($B$21:$F$21)+($F$18*(1+$B$19)/(($B$13-0.01)-$B$19))/(1+($B$13-0.01))^5) -> #VALUE! | D41: =IF(OR($B$13="",$B$19="",$F$18="",($B$13-0.01)<=($B$19+0.01)),"",SUM($B$21:$F$21)+($F$18*(1+($B$19+0.01))/(($B$13-0.01)-($B$19+0.01)))/(1+($B$13-0.01))^5) -> #VALUE!
A42: Base WACC | B42: =IF(OR($B$13="",$B$19="",$F$18="",($B$13)<=($B$19-0.01)),"",SUM($B$21:$F$21)+($F$18*(1+($B$19-0.01))/($B$13-($B$19-0.01)))/(1+$B$13)^5) | C42: =B22 | D42: =IF(OR($B$13="",$B$19="",$F$18="",($B$13)<=($B$19+0.01)),"",SUM($B$21:$F$21)+($F$18*(1+($B$19+0.01))/($B$13-($B$19+0.01)))/(1+$B$13)^5)
A43: WACC +1.0% | B43: =IF(OR($B$13="",$B$19="",$F$18="",($B$13+0.01)<=($B$19-0.01)),"",SUM($B$21:$F$21)+($F$18*(1+($B$19-0.01))/(($B$13+0.01)-($B$19-0.01)))/(1+($B$13+0.01))^5) -> #VALUE! | C43: =IF(OR($B$13="",$B$19="",$F$18="",($B$13+0.01)<=($B$19)),"",SUM($B$21:$F$21)+($F$18*(1+$B$19)/(($B$13+0.01)-$B$19))/(1+($B$13+0.01))^5) -> #VALUE! | D43: =IF(OR($B$13="",$B$19="",$F$18="",($B$13+0.01)<=($B$19+0.01)),"",SUM($B$21:$F$21)+($F$18*(1+($B$19+0.01))/(($B$13+0.01)-($B$19+0.01)))/(1+($B$13+0.01))^5) -> #VALUE!
A44: Local vs U.S. Override Logic | B44: If country <> USA and local rate exists, use local for Entity 2
A45: Warning | B45: =IF(OR(Entity_Ownership!F5="",Entity_Ownership!G5=""),"WARNING: Missing Country/Currency Data",IF(B13="","WARNING: Incomplete CAPM / WACC Chain","")) -> WARNING: Missing Country/Currency Data

Sheet Valuation_Entity3
A1: VALUATION ANALYSIS - ENTITY 3
A3: SECTION A: WACC INPUTS
A4: Input | B4: Value | C4: Notes
A5: Risk Free Rate | B5: =IF(AND(Entity_Ownership!$F$6<>"",UPPER(Entity_Ownership!$F$6)<>"UNITED STATES",COUNTIFS(Global_Rates!$B$4:$B$73,"Entity 3",Global_Rates!$A$4:$A$73,"Local 10-Year Government Bond Yield",Global_Rates!$F$4:$F$73,"<>")>0),SUMIFS(Global_Rates!$F$4:$F$73,Global_Rates!$B$4:$B$73,"Entity 3",Global_Rates!$A$4:$A$73,"Local 10-Year Government Bond Yield"),IF(COUNTIFS(Global_Rates!$B$4:$B$73,"Entity 3",Global_Rates!$A$4:$A$73,"U.S. 10-Year Treasury",Global_Rates!$F$4:$F$73,"<>")>0,SUMIFS(Global_Rates!$F$4:$F$73,Global_Rates!$B$4:$B$73,"Entity 3",Global_Rates!$A$4:$A$73,"U.S. 10-Year Treasury"),"")) | C5: Rate used for CAPM
A6: Beta | B6: =IF(COUNTIFS(Global_Rates!$B$4:$B$73,"Entity 3",Global_Rates!$A$4:$A$73,"Beta",Global_Rates!$F$4:$F$73,"<>")>0,SUMIFS(Global_Rates!$F$4:$F$73,Global_Rates!$B$4:$B$73,"Entity 3",Global_Rates!$A$4:$A$73,"Beta"),"") | C6: Entity beta
A7: Market Risk Premium | B7: =IF(AND(Entity_Ownership!$F$6<>"",UPPER(Entity_Ownership!$F$6)<>"UNITED STATES",COUNTIFS(Global_Rates!$B$4:$B$73,"Entity 3",Global_Rates!$A$4:$A$73,"Local Market Risk Premium",Global_Rates!$F$4:$F$73,"<>")>0),SUMIFS(Global_Rates!$F$4:$F$73,Global_Rates!$B$4:$B$73,"Entity 3",Global_Rates!$A$4:$A$73,"Local Market Risk Premium"),IF(COUNTIFS(Global_Rates!$B$4:$B$73,"Entity 3",Global_Rates!$A$4:$A$73,"U.S. Market Risk Premium",Global_Rates!$F$4:$F$73,"<>")>0,SUMIFS(Global_Rates!$F$4:$F$73,Global_Rates!$B$4:$B$73,"Entity 3",Global_Rates!$A$4:$A$73,"U.S. Market Risk Premium"),"")) | C7: Rate used for CAPM
A8: Cost of Debt | B8: =IF(AND(Entity_Ownership!$F$6<>"",UPPER(Entity_Ownership!$F$6)<>"UNITED STATES",COUNTIFS(Global_Rates!$B$4:$B$73,"Entity 3",Global_Rates!$A$4:$A$73,"Local Corporate Bond Yield",Global_Rates!$F$4:$F$73,"<>")>0),SUMIFS(Global_Rates!$F$4:$F$73,Global_Rates!$B$4:$B$73,"Entity 3",Global_Rates!$A$4:$A$73,"Local Corporate Bond Yield"),IF(COUNTIFS(Global_Rates!$B$4:$B$73,"Entity 3",Global_Rates!$A$4:$A$73,"U.S. Corporate Bond Yield",Global_Rates!$F$4:$F$73,"<>")>0,SUMIFS(Global_Rates!$F$4:$F$73,Global_Rates!$B$4:$B$73,"Entity 3",Global_Rates!$A$4:$A$73,"U.S. Corporate Bond Yield"),"")) | C8: Pre-tax cost of debt
A9: Tax Rate | B9: =IF(OR(Fin_Inputs_Entity3!F13="",Fin_Inputs_Entity3!F11="",Fin_Inputs_Entity3!F11=0),"",ABS(Fin_Inputs_Entity3!F13/Fin_Inputs_Entity3!F11)) | C9: Taxes / EBIT
A10: Debt Weight | B10: =IF((N(Fin_Inputs_Entity3!F26)+N(Fin_Inputs_Entity3!F27)+N(Fin_Inputs_Entity3!F29))=0,"",(N(Fin_Inputs_Entity3!F26)+N(Fin_Inputs_Entity3!F27))/(N(Fin_Inputs_Entity3!F26)+N(Fin_Inputs_Entity3!F27)+N(Fin_Inputs_Entity3!F29))) | C10: Debt / (Debt + Equity)
A11: Equity Weight | B11: =IF((N(Fin_Inputs_Entity3!F26)+N(Fin_Inputs_Entity3!F27)+N(Fin_Inputs_Entity3!F29))=0,"",N(Fin_Inputs_Entity3!F29)/(N(Fin_Inputs_Entity3!F26)+N(Fin_Inputs_Entity3!F27)+N(Fin_Inputs_Entity3!F29))) | C11: Equity / (Debt + Equity)
A12: Cost of Equity | B12: =IF(COUNT(B5:B7)<3,"",B5+B6*B7) | C12: CAPM
A13: WACC | B13: =IF(COUNT(B8:B12)<5,"",(B11*B12)+(B10*B8*(1-B9))) | C13: Weighted average cost of capital
A14: FX Rate Used | B14: =IF(FX_Rate_Entity3="","",FX_Rate_Entity3) | C14: Previous month-end or override
A15: SECTION B: DCF MODEL
A16: Item
A17: Forecasted FCF | B17: Year 1 | C17: Year 2 | D17: Year 3 | E17: Year 4 | F17: Year 5 | G17: Terminal
A18: Terminal Growth Rate | B18: =IF(OR(Fin_Inputs_Entity3!B37="",B14=""),"",Fin_Inputs_Entity3!B37*B14*(1+N(Scenario_Analysis!$E$4)-N(Scenario_Analysis!$E$6)-N(Scenario_Analysis!$E$7))) | C18: =IF(OR(Fin_Inputs_Entity3!C37="",B14=""),"",Fin_Inputs_Entity3!C37*B14*(1+N(Scenario_Analysis!$E$4)-N(Scenario_Analysis!$E$6)-N(Scenario_Analysis!$E$7))) | D18: =IF(OR(Fin_Inputs_Entity3!D37="",B14=""),"",Fin_Inputs_Entity3!D37*B14*(1+N(Scenario_Analysis!$E$4)-N(Scenario_Analysis!$E$6)-N(Scenario_Analysis!$E$7))) | E18: =IF(OR(Fin_Inputs_Entity3!E37="",B14=""),"",Fin_Inputs_Entity3!E37*B14*(1+N(Scenario_Analysis!$E$4)-N(Scenario_Analysis!$E$6)-N(Scenario_Analysis!$E$7))) | F18: =IF(OR(Fin_Inputs_Entity3!F37="",B14=""),"",Fin_Inputs_Entity3!F37*B14*(1+N(Scenario_Analysis!$E$4)-N(Scenario_Analysis!$E$6)-N(Scenario_Analysis!$E$7)))
A19: Terminal Value | B19: 0.02 | G19: =IF(OR(F18="",B13="",B19="",B13<=B19),"",F18*(1+B19)/(B13-B19))
A20: Discount Factor | B20: =IF(B13="","",1/(1+B13)^1) | C20: =IF(B13="","",1/(1+B13)^2) | D20: =IF(B13="","",1/(1+B13)^3) | E20: =IF(B13="","",1/(1+B13)^4) | F20: =IF(B13="","",1/(1+B13)^5) | G20: =IF(B13="","",1/(1+B13)^5)
A21: PV of Cash Flows | B21: =IF(OR(B18="",B20=""),"",B18*B20) | C21: =IF(OR(C18="",C20=""),"",C18*C20) | D21: =IF(OR(D18="",D20=""),"",D18*D20) | E21: =IF(OR(E18="",E20=""),"",E18*E20) | F21: =IF(OR(F18="",F20=""),"",F18*F20) | G21: =IF(OR(G19="",G20=""),"",G19*G20)
A22: DCF Enterprise Value | B22: =IF(COUNT(B21:G21)=0,"",SUM(B21:G21)) | C22: =IF(OR(C18="",C21=""),"",C18*C21) | D22: =IF(OR(D18="",D21=""),"",D18*D21) | E22: =IF(OR(E18="",E21=""),"",E18*E21) | F22: =IF(OR(F18="",F21=""),"",F18*F21) | G22: =IF(OR(G20="",G21=""),"",G20*G21)
A23: DCF Enterprise Value | B23: =IF(COUNT(B22:G22)=0,"",SUM(B22:G22)) | H23: =IF(OR(F21="",B13="",B22="",B13<=B22),"",F21*(1+B22)/(B13-B22))
A25: Multiple
A26: Multiple | B26: Multiple Value | C26: Metric | D26: Implied EV
A27: EV/EBITDA | B27: 6 | C27: =IF(OR(Fin_Inputs_Entity3!F9="",B14=""),"",Fin_Inputs_Entity3!F9*B14) | D27: =IF(OR(B27="",C27=""),"",B27*C27)
A28: EV/Revenue | B28: 1.5 | C28: =IF(OR(Fin_Inputs_Entity3!F5="",B14=""),"",Fin_Inputs_Entity3!F5*B14) | D28: =IF(OR(B28="",C28=""),"",B28*C28)
A29: P/E | B29: 10 | C29: =IF(OR(Fin_Inputs_Entity3!F14="",B14=""),"",Fin_Inputs_Entity3!F14*B14) | D29: =IF(OR(B29="",C29=""),"",B29*C29)
A30: Average Multiples Value | B30: =IF(COUNT(D27:D29)=0,"",AVERAGE(D27:D29)) | D30: =IF(COUNT(D27:D29)=0,"",AVERAGE(D27:D29))
A31: Warning | B31: =IF(OR(Entity_Ownership!F6="",FX_Conversion!B6=""),"WARNING: Missing Country/Currency Data",IF(OR(B5="",B6="",B7="",B8="",B14=""),"WARNING: Incomplete CAPM / WACC / FX Chain","")) -> WARNING: Missing Country/Currency Data
A33: Item
A34: DCF Value | B34: =B23 | C34: USD pre-ownership
A35: Multiples Value | B35: =B30 | C35: USD pre-ownership
A36: Blended Value | B36: =IF(COUNT(B34:B35)=0,"",AVERAGE(B34:B35)) | C36: USD pre-ownership
A37: Final Valuation | B37: =IF(B36="","",B36*IF(Entity_Ownership!C6="",1,Entity_Ownership!C6)) | C37: USD ownership-adjusted
A39: Sensitivity Table
A40: WACC / g | B40: g -1% | C40: Base g | D40: g +1%
A41: WACC -1.0% | B41: =IF(OR($B$13="",$B$19="",$F$18="",($B$13-0.01)<=($B$19-0.01)),"",SUM($B$21:$F$21)+($F$18*(1+($B$19-0.01))/(($B$13-0.01)-($B$19-0.01)))/(1+($B$13-0.01))^5) -> #VALUE! | C41: =IF(OR($B$13="",$B$19="",$F$18="",($B$13-0.01)<=($B$19)),"",SUM($B$21:$F$21)+($F$18*(1+$B$19)/(($B$13-0.01)-$B$19))/(1+($B$13-0.01))^5) -> #VALUE! | D41: =IF(OR($B$13="",$B$19="",$F$18="",($B$13-0.01)<=($B$19+0.01)),"",SUM($B$21:$F$21)+($F$18*(1+($B$19+0.01))/(($B$13-0.01)-($B$19+0.01)))/(1+($B$13-0.01))^5) -> #VALUE!
A42: Base WACC | B42: =IF(OR($B$13="",$B$19="",$F$18="",($B$13)<=($B$19-0.01)),"",SUM($B$21:$F$21)+($F$18*(1+($B$19-0.01))/($B$13-($B$19-0.01)))/(1+$B$13)^5) | C42: =B22 | D42: =IF(OR($B$13="",$B$19="",$F$18="",($B$13)<=($B$19+0.01)),"",SUM($B$21:$F$21)+($F$18*(1+($B$19+0.01))/($B$13-($B$19+0.01)))/(1+$B$13)^5)
A43: WACC +1.0% | B43: =IF(OR($B$13="",$B$19="",$F$18="",($B$13+0.01)<=($B$19-0.01)),"",SUM($B$21:$F$21)+($F$18*(1+($B$19-0.01))/(($B$13+0.01)-($B$19-0.01)))/(1+($B$13+0.01))^5) -> #VALUE! | C43: =IF(OR($B$13="",$B$19="",$F$18="",($B$13+0.01)<=($B$19)),"",SUM($B$21:$F$21)+($F$18*(1+$B$19)/(($B$13+0.01)-$B$19))/(1+($B$13+0.01))^5) -> #VALUE! | D43: =IF(OR($B$13="",$B$19="",$F$18="",($B$13+0.01)<=($B$19+0.01)),"",SUM($B$21:$F$21)+($F$18*(1+($B$19+0.01))/(($B$13+0.01)-($B$19+0.01)))/(1+($B$13+0.01))^5) -> #VALUE!
A44: Local vs U.S. Override Logic | B44: If country <> USA and local rate exists, use local for Entity 3
A45: Warning | B45: =IF(OR(Entity_Ownership!F6="",Entity_Ownership!G6=""),"WARNING: Missing Country/Currency Data",IF(B13="","WARNING: Incomplete CAPM / WACC Chain","")) -> WARNING: Missing Country/Currency Data

Sheet Valuation_Entity4
A1: VALUATION ANALYSIS - ENTITY 4
A3: SECTION A: WACC INPUTS
A4: Input | B4: Value | C4: Notes
A5: Risk Free Rate | B5: =IF(AND(Entity_Ownership!$F$7<>"",UPPER(Entity_Ownership!$F$7)<>"UNITED STATES",COUNTIFS(Global_Rates!$B$4:$B$73,"Entity 4",Global_Rates!$A$4:$A$73,"Local 10-Year Government Bond Yield",Global_Rates!$F$4:$F$73,"<>")>0),SUMIFS(Global_Rates!$F$4:$F$73,Global_Rates!$B$4:$B$73,"Entity 4",Global_Rates!$A$4:$A$73,"Local 10-Year Government Bond Yield"),IF(COUNTIFS(Global_Rates!$B$4:$B$73,"Entity 4",Global_Rates!$A$4:$A$73,"U.S. 10-Year Treasury",Global_Rates!$F$4:$F$73,"<>")>0,SUMIFS(Global_Rates!$F$4:$F$73,Global_Rates!$B$4:$B$73,"Entity 4",Global_Rates!$A$4:$A$73,"U.S. 10-Year Treasury"),"")) | C5: Rate used for CAPM
A6: Beta | B6: =IF(COUNTIFS(Global_Rates!$B$4:$B$73,"Entity 4",Global_Rates!$A$4:$A$73,"Beta",Global_Rates!$F$4:$F$73,"<>")>0,SUMIFS(Global_Rates!$F$4:$F$73,Global_Rates!$B$4:$B$73,"Entity 4",Global_Rates!$A$4:$A$73,"Beta"),"") | C6: Entity beta
A7: Market Risk Premium | B7: =IF(AND(Entity_Ownership!$F$7<>"",UPPER(Entity_Ownership!$F$7)<>"UNITED STATES",COUNTIFS(Global_Rates!$B$4:$B$73,"Entity 4",Global_Rates!$A$4:$A$73,"Local Market Risk Premium",Global_Rates!$F$4:$F$73,"<>")>0),SUMIFS(Global_Rates!$F$4:$F$73,Global_Rates!$B$4:$B$73,"Entity 4",Global_Rates!$A$4:$A$73,"Local Market Risk Premium"),IF(COUNTIFS(Global_Rates!$B$4:$B$73,"Entity 4",Global_Rates!$A$4:$A$73,"U.S. Market Risk Premium",Global_Rates!$F$4:$F$73,"<>")>0,SUMIFS(Global_Rates!$F$4:$F$73,Global_Rates!$B$4:$B$73,"Entity 4",Global_Rates!$A$4:$A$73,"U.S. Market Risk Premium"),"")) | C7: Rate used for CAPM
A8: Cost of Debt | B8: =IF(AND(Entity_Ownership!$F$7<>"",UPPER(Entity_Ownership!$F$7)<>"UNITED STATES",COUNTIFS(Global_Rates!$B$4:$B$73,"Entity 4",Global_Rates!$A$4:$A$73,"Local Corporate Bond Yield",Global_Rates!$F$4:$F$73,"<>")>0),SUMIFS(Global_Rates!$F$4:$F$73,Global_Rates!$B$4:$B$73,"Entity 4",Global_Rates!$A$4:$A$73,"Local Corporate Bond Yield"),IF(COUNTIFS(Global_Rates!$B$4:$B$73,"Entity 4",Global_Rates!$A$4:$A$73,"U.S. Corporate Bond Yield",Global_Rates!$F$4:$F$73,"<>")>0,SUMIFS(Global_Rates!$F$4:$F$73,Global_Rates!$B$4:$B$73,"Entity 4",Global_Rates!$A$4:$A$73,"U.S. Corporate Bond Yield"),"")) | C8: Pre-tax cost of debt
A9: Tax Rate | B9: =IF(OR(Fin_Inputs_Entity4!F13="",Fin_Inputs_Entity4!F11="",Fin_Inputs_Entity4!F11=0),"",ABS(Fin_Inputs_Entity4!F13/Fin_Inputs_Entity4!F11)) | C9: Taxes / EBIT
A10: Debt Weight | B10: =IF((N(Fin_Inputs_Entity4!F26)+N(Fin_Inputs_Entity4!F27)+N(Fin_Inputs_Entity4!F29))=0,"",(N(Fin_Inputs_Entity4!F26)+N(Fin_Inputs_Entity4!F27))/(N(Fin_Inputs_Entity4!F26)+N(Fin_Inputs_Entity4!F27)+N(Fin_Inputs_Entity4!F29))) | C10: Debt / (Debt + Equity)
A11: Equity Weight | B11: =IF((N(Fin_Inputs_Entity4!F26)+N(Fin_Inputs_Entity4!F27)+N(Fin_Inputs_Entity4!F29))=0,"",N(Fin_Inputs_Entity4!F29)/(N(Fin_Inputs_Entity4!F26)+N(Fin_Inputs_Entity4!F27)+N(Fin_Inputs_Entity4!F29))) | C11: Equity / (Debt + Equity)
A12: Cost of Equity | B12: =IF(COUNT(B5:B7)<3,"",B5+B6*B7) | C12: CAPM
A13: WACC | B13: =IF(COUNT(B8:B12)<5,"",(B11*B12)+(B10*B8*(1-B9))) | C13: Weighted average cost of capital
A14: FX Rate Used | B14: =IF(FX_Rate_Entity4="","",FX_Rate_Entity4) | C14: Previous month-end or override
A15: SECTION B: DCF MODEL
A16: Item
A17: Forecasted FCF | B17: Year 1 | C17: Year 2 | D17: Year 3 | E17: Year 4 | F17: Year 5 | G17: Terminal
A18: Terminal Growth Rate | B18: =IF(OR(Fin_Inputs_Entity4!B37="",B14=""),"",Fin_Inputs_Entity4!B37*B14*(1+N(Scenario_Analysis!$E$4)-N(Scenario_Analysis!$E$6)-N(Scenario_Analysis!$E$7))) | C18: =IF(OR(Fin_Inputs_Entity4!C37="",B14=""),"",Fin_Inputs_Entity4!C37*B14*(1+N(Scenario_Analysis!$E$4)-N(Scenario_Analysis!$E$6)-N(Scenario_Analysis!$E$7))) | D18: =IF(OR(Fin_Inputs_Entity4!D37="",B14=""),"",Fin_Inputs_Entity4!D37*B14*(1+N(Scenario_Analysis!$E$4)-N(Scenario_Analysis!$E$6)-N(Scenario_Analysis!$E$7))) | E18: =IF(OR(Fin_Inputs_Entity4!E37="",B14=""),"",Fin_Inputs_Entity4!E37*B14*(1+N(Scenario_Analysis!$E$4)-N(Scenario_Analysis!$E$6)-N(Scenario_Analysis!$E$7))) | F18: =IF(OR(Fin_Inputs_Entity4!F37="",B14=""),"",Fin_Inputs_Entity4!F37*B14*(1+N(Scenario_Analysis!$E$4)-N(Scenario_Analysis!$E$6)-N(Scenario_Analysis!$E$7)))
A19: Terminal Value | B19: 0.02 | G19: =IF(OR(F18="",B13="",B19="",B13<=B19),"",F18*(1+B19)/(B13-B19))
A20: Discount Factor | B20: =IF(B13="","",1/(1+B13)^1) | C20: =IF(B13="","",1/(1+B13)^2) | D20: =IF(B13="","",1/(1+B13)^3) | E20: =IF(B13="","",1/(1+B13)^4) | F20: =IF(B13="","",1/(1+B13)^5) | G20: =IF(B13="","",1/(1+B13)^5)
A21: PV of Cash Flows | B21: =IF(OR(B18="",B20=""),"",B18*B20) | C21: =IF(OR(C18="",C20=""),"",C18*C20) | D21: =IF(OR(D18="",D20=""),"",D18*D20) | E21: =IF(OR(E18="",E20=""),"",E18*E20) | F21: =IF(OR(F18="",F20=""),"",F18*F20) | G21: =IF(OR(G19="",G20=""),"",G19*G20)
A22: DCF Enterprise Value | B22: =IF(COUNT(B21:G21)=0,"",SUM(B21:G21)) | C22: =IF(OR(C18="",C21=""),"",C18*C21) | D22: =IF(OR(D18="",D21=""),"",D18*D21) | E22: =IF(OR(E18="",E21=""),"",E18*E21) | F22: =IF(OR(F18="",F21=""),"",F18*F21) | G22: =IF(OR(G20="",G21=""),"",G20*G21)
A23: DCF Enterprise Value | B23: =IF(COUNT(B22:G22)=0,"",SUM(B22:G22)) | H23: =IF(OR(F21="",B13="",B22="",B13<=B22),"",F21*(1+B22)/(B13-B22))
A25: Multiple
A26: Multiple | B26: Multiple Value | C26: Metric | D26: Implied EV
A27: EV/EBITDA | B27: 6 | C27: =IF(OR(Fin_Inputs_Entity4!F9="",B14=""),"",Fin_Inputs_Entity4!F9*B14) | D27: =IF(OR(B27="",C27=""),"",B27*C27)
A28: EV/Revenue | B28: 1.5 | C28: =IF(OR(Fin_Inputs_Entity4!F5="",B14=""),"",Fin_Inputs_Entity4!F5*B14) | D28: =IF(OR(B28="",C28=""),"",B28*C28)
A29: P/E | B29: 10 | C29: =IF(OR(Fin_Inputs_Entity4!F14="",B14=""),"",Fin_Inputs_Entity4!F14*B14) | D29: =IF(OR(B29="",C29=""),"",B29*C29)
A30: Average Multiples Value | B30: =IF(COUNT(D27:D29)=0,"",AVERAGE(D27:D29)) | D30: =IF(COUNT(D27:D29)=0,"",AVERAGE(D27:D29))
A31: Warning | B31: =IF(OR(Entity_Ownership!F7="",FX_Conversion!B7=""),"WARNING: Missing Country/Currency Data",IF(OR(B5="",B6="",B7="",B8="",B14=""),"WARNING: Incomplete CAPM / WACC / FX Chain","")) -> WARNING: Missing Country/Currency Data
A33: Item
A34: DCF Value | B34: =B23 | C34: USD pre-ownership
A35: Multiples Value | B35: =B30 | C35: USD pre-ownership
A36: Blended Value | B36: =IF(COUNT(B34:B35)=0,"",AVERAGE(B34:B35)) | C36: USD pre-ownership
A37: Final Valuation | B37: =IF(B36="","",B36*IF(Entity_Ownership!C7="",1,Entity_Ownership!C7)) | C37: USD ownership-adjusted
A39: Sensitivity Table
A40: WACC / g | B40: g -1% | C40: Base g | D40: g +1%
A41: WACC -1.0% | B41: =IF(OR($B$13="",$B$19="",$F$18="",($B$13-0.01)<=($B$19-0.01)),"",SUM($B$21:$F$21)+($F$18*(1+($B$19-0.01))/(($B$13-0.01)-($B$19-0.01)))/(1+($B$13-0.01))^5) -> #VALUE! | C41: =IF(OR($B$13="",$B$19="",$F$18="",($B$13-0.01)<=($B$19)),"",SUM($B$21:$F$21)+($F$18*(1+$B$19)/(($B$13-0.01)-$B$19))/(1+($B$13-0.01))^5) -> #VALUE! | D41: =IF(OR($B$13="",$B$19="",$F$18="",($B$13-0.01)<=($B$19+0.01)),"",SUM($B$21:$F$21)+($F$18*(1+($B$19+0.01))/(($B$13-0.01)-($B$19+0.01)))/(1+($B$13-0.01))^5) -> #VALUE!
A42: Base WACC | B42: =IF(OR($B$13="",$B$19="",$F$18="",($B$13)<=($B$19-0.01)),"",SUM($B$21:$F$21)+($F$18*(1+($B$19-0.01))/($B$13-($B$19-0.01)))/(1+$B$13)^5) | C42: =B22 | D42: =IF(OR($B$13="",$B$19="",$F$18="",($B$13)<=($B$19+0.01)),"",SUM($B$21:$F$21)+($F$18*(1+($B$19+0.01))/($B$13-($B$19+0.01)))/(1+$B$13)^5)
A43: WACC +1.0% | B43: =IF(OR($B$13="",$B$19="",$F$18="",($B$13+0.01)<=($B$19-0.01)),"",SUM($B$21:$F$21)+($F$18*(1+($B$19-0.01))/(($B$13+0.01)-($B$19-0.01)))/(1+($B$13+0.01))^5) -> #VALUE! | C43: =IF(OR($B$13="",$B$19="",$F$18="",($B$13+0.01)<=($B$19)),"",SUM($B$21:$F$21)+($F$18*(1+$B$19)/(($B$13+0.01)-$B$19))/(1+($B$13+0.01))^5) -> #VALUE! | D43: =IF(OR($B$13="",$B$19="",$F$18="",($B$13+0.01)<=($B$19+0.01)),"",SUM($B$21:$F$21)+($F$18*(1+($B$19+0.01))/(($B$13+0.01)-($B$19+0.01)))/(1+($B$13+0.01))^5) -> #VALUE!
A44: Local vs U.S. Override Logic | B44: If country <> USA and local rate exists, use local for Entity 4
A45: Warning | B45: =IF(OR(Entity_Ownership!F7="",Entity_Ownership!G7=""),"WARNING: Missing Country/Currency Data",IF(B13="","WARNING: Incomplete CAPM / WACC Chain","")) -> WARNING: Missing Country/Currency Data

Sheet Valuation_Entity5
A1: VALUATION ANALYSIS - ENTITY 5
A3: SECTION A: WACC INPUTS
A4: Input | B4: Value | C4: Notes
A5: Risk Free Rate | B5: =IF(AND(Entity_Ownership!$F$8<>"",UPPER(Entity_Ownership!$F$8)<>"UNITED STATES",COUNTIFS(Global_Rates!$B$4:$B$73,"Entity 5",Global_Rates!$A$4:$A$73,"Local 10-Year Government Bond Yield",Global_Rates!$F$4:$F$73,"<>")>0),SUMIFS(Global_Rates!$F$4:$F$73,Global_Rates!$B$4:$B$73,"Entity 5",Global_Rates!$A$4:$A$73,"Local 10-Year Government Bond Yield"),IF(COUNTIFS(Global_Rates!$B$4:$B$73,"Entity 5",Global_Rates!$A$4:$A$73,"U.S. 10-Year Treasury",Global_Rates!$F$4:$F$73,"<>")>0,SUMIFS(Global_Rates!$F$4:$F$73,Global_Rates!$B$4:$B$73,"Entity 5",Global_Rates!$A$4:$A$73,"U.S. 10-Year Treasury"),"")) | C5: Rate used for CAPM
A6: Beta | B6: =IF(COUNTIFS(Global_Rates!$B$4:$B$73,"Entity 5",Global_Rates!$A$4:$A$73,"Beta",Global_Rates!$F$4:$F$73,"<>")>0,SUMIFS(Global_Rates!$F$4:$F$73,Global_Rates!$B$4:$B$73,"Entity 5",Global_Rates!$A$4:$A$73,"Beta"),"") | C6: Entity beta
A7: Market Risk Premium | B7: =IF(AND(Entity_Ownership!$F$8<>"",UPPER(Entity_Ownership!$F$8)<>"UNITED STATES",COUNTIFS(Global_Rates!$B$4:$B$73,"Entity 5",Global_Rates!$A$4:$A$73,"Local Market Risk Premium",Global_Rates!$F$4:$F$73,"<>")>0),SUMIFS(Global_Rates!$F$4:$F$73,Global_Rates!$B$4:$B$73,"Entity 5",Global_Rates!$A$4:$A$73,"Local Market Risk Premium"),IF(COUNTIFS(Global_Rates!$B$4:$B$73,"Entity 5",Global_Rates!$A$4:$A$73,"U.S. Market Risk Premium",Global_Rates!$F$4:$F$73,"<>")>0,SUMIFS(Global_Rates!$F$4:$F$73,Global_Rates!$B$4:$B$73,"Entity 5",Global_Rates!$A$4:$A$73,"U.S. Market Risk Premium"),"")) | C7: Rate used for CAPM
A8: Cost of Debt | B8: =IF(AND(Entity_Ownership!$F$8<>"",UPPER(Entity_Ownership!$F$8)<>"UNITED STATES",COUNTIFS(Global_Rates!$B$4:$B$73,"Entity 5",Global_Rates!$A$4:$A$73,"Local Corporate Bond Yield",Global_Rates!$F$4:$F$73,"<>")>0),SUMIFS(Global_Rates!$F$4:$F$73,Global_Rates!$B$4:$B$73,"Entity 5",Global_Rates!$A$4:$A$73,"Local Corporate Bond Yield"),IF(COUNTIFS(Global_Rates!$B$4:$B$73,"Entity 5",Global_Rates!$A$4:$A$73,"U.S. Corporate Bond Yield",Global_Rates!$F$4:$F$73,"<>")>0,SUMIFS(Global_Rates!$F$4:$F$73,Global_Rates!$B$4:$B$73,"Entity 5",Global_Rates!$A$4:$A$73,"U.S. Corporate Bond Yield"),"")) | C8: Pre-tax cost of debt
A9: Tax Rate | B9: =IF(OR(Fin_Inputs_Entity5!F13="",Fin_Inputs_Entity5!F11="",Fin_Inputs_Entity5!F11=0),"",ABS(Fin_Inputs_Entity5!F13/Fin_Inputs_Entity5!F11)) | C9: Taxes / EBIT
A10: Debt Weight | B10: =IF((N(Fin_Inputs_Entity5!F26)+N(Fin_Inputs_Entity5!F27)+N(Fin_Inputs_Entity5!F29))=0,"",(N(Fin_Inputs_Entity5!F26)+N(Fin_Inputs_Entity5!F27))/(N(Fin_Inputs_Entity5!F26)+N(Fin_Inputs_Entity5!F27)+N(Fin_Inputs_Entity5!F29))) | C10: Debt / (Debt + Equity)
A11: Equity Weight | B11: =IF((N(Fin_Inputs_Entity5!F26)+N(Fin_Inputs_Entity5!F27)+N(Fin_Inputs_Entity5!F29))=0,"",N(Fin_Inputs_Entity5!F29)/(N(Fin_Inputs_Entity5!F26)+N(Fin_Inputs_Entity5!F27)+N(Fin_Inputs_Entity5!F29))) | C11: Equity / (Debt + Equity)
A12: Cost of Equity | B12: =IF(COUNT(B5:B7)<3,"",B5+B6*B7) | C12: CAPM
A13: WACC | B13: =IF(COUNT(B8:B12)<5,"",(B11*B12)+(B10*B8*(1-B9))) | C13: Weighted average cost of capital
A14: FX Rate Used | B14: =IF(FX_Rate_Entity5="","",FX_Rate_Entity5) | C14: Previous month-end or override
A15: SECTION B: DCF MODEL
A16: Item
A17: Forecasted FCF | B17: Year 1 | C17: Year 2 | D17: Year 3 | E17: Year 4 | F17: Year 5 | G17: Terminal
A18: Terminal Growth Rate | B18: =IF(OR(Fin_Inputs_Entity5!B37="",B14=""),"",Fin_Inputs_Entity5!B37*B14*(1+N(Scenario_Analysis!$E$4)-N(Scenario_Analysis!$E$6)-N(Scenario_Analysis!$E$7))) | C18: =IF(OR(Fin_Inputs_Entity5!C37="",B14=""),"",Fin_Inputs_Entity5!C37*B14*(1+N(Scenario_Analysis!$E$4)-N(Scenario_Analysis!$E$6)-N(Scenario_Analysis!$E$7))) | D18: =IF(OR(Fin_Inputs_Entity5!D37="",B14=""),"",Fin_Inputs_Entity5!D37*B14*(1+N(Scenario_Analysis!$E$4)-N(Scenario_Analysis!$E$6)-N(Scenario_Analysis!$E$7))) | E18: =IF(OR(Fin_Inputs_Entity5!E37="",B14=""),"",Fin_Inputs_Entity5!E37*B14*(1+N(Scenario_Analysis!$E$4)-N(Scenario_Analysis!$E$6)-N(Scenario_Analysis!$E$7))) | F18: =IF(OR(Fin_Inputs_Entity5!F37="",B14=""),"",Fin_Inputs_Entity5!F37*B14*(1+N(Scenario_Analysis!$E$4)-N(Scenario_Analysis!$E$6)-N(Scenario_Analysis!$E$7)))
A19: Terminal Value | B19: 0.02 | G19: =IF(OR(F18="",B13="",B19="",B13<=B19),"",F18*(1+B19)/(B13-B19))
A20: Discount Factor | B20: =IF(B13="","",1/(1+B13)^1) | C20: =IF(B13="","",1/(1+B13)^2) | D20: =IF(B13="","",1/(1+B13)^3) | E20: =IF(B13="","",1/(1+B13)^4) | F20: =IF(B13="","",1/(1+B13)^5) | G20: =IF(B13="","",1/(1+B13)^5)
A21: PV of Cash Flows | B21: =IF(OR(B18="",B20=""),"",B18*B20) | C21: =IF(OR(C18="",C20=""),"",C18*C20) | D21: =IF(OR(D18="",D20=""),"",D18*D20) | E21: =IF(OR(E18="",E20=""),"",E18*E20) | F21: =IF(OR(F18="",F20=""),"",F18*F20) | G21: =IF(OR(G19="",G20=""),"",G19*G20)
A22: DCF Enterprise Value | B22: =IF(COUNT(B21:G21)=0,"",SUM(B21:G21)) | C22: =IF(OR(C18="",C21=""),"",C18*C21) | D22: =IF(OR(D18="",D21=""),"",D18*D21) | E22: =IF(OR(E18="",E21=""),"",E18*E21) | F22: =IF(OR(F18="",F21=""),"",F18*F21) | G22: =IF(OR(G20="",G21=""),"",G20*G21)
A23: DCF Enterprise Value | B23: =IF(COUNT(B22:G22)=0,"",SUM(B22:G22)) | H23: =IF(OR(F21="",B13="",B22="",B13<=B22),"",F21*(1+B22)/(B13-B22))
A25: Multiple
A26: Multiple | B26: Multiple Value | C26: Metric | D26: Implied EV
A27: EV/EBITDA | B27: 6 | C27: =IF(OR(Fin_Inputs_Entity5!F9="",B14=""),"",Fin_Inputs_Entity5!F9*B14) | D27: =IF(OR(B27="",C27=""),"",B27*C27)
A28: EV/Revenue | B28: 1.5 | C28: =IF(OR(Fin_Inputs_Entity5!F5="",B14=""),"",Fin_Inputs_Entity5!F5*B14) | D28: =IF(OR(B28="",C28=""),"",B28*C28)
A29: P/E | B29: 10 | C29: =IF(OR(Fin_Inputs_Entity5!F14="",B14=""),"",Fin_Inputs_Entity5!F14*B14) | D29: =IF(OR(B29="",C29=""),"",B29*C29)
A30: Average Multiples Value | B30: =IF(COUNT(D27:D29)=0,"",AVERAGE(D27:D29)) | D30: =IF(COUNT(D27:D29)=0,"",AVERAGE(D27:D29))
A31: Warning | B31: =IF(OR(Entity_Ownership!F8="",FX_Conversion!B8=""),"WARNING: Missing Country/Currency Data",IF(OR(B5="",B6="",B7="",B8="",B14=""),"WARNING: Incomplete CAPM / WACC / FX Chain","")) -> WARNING: Missing Country/Currency Data
A33: Item
A34: DCF Value | B34: =B23 | C34: USD pre-ownership
A35: Multiples Value | B35: =B30 | C35: USD pre-ownership
A36: Blended Value | B36: =IF(COUNT(B34:B35)=0,"",AVERAGE(B34:B35)) | C36: USD pre-ownership
A37: Final Valuation | B37: =IF(B36="","",B36*IF(Entity_Ownership!C8="",1,Entity_Ownership!C8)) | C37: USD ownership-adjusted
A39: Sensitivity Table
A40: WACC / g | B40: g -1% | C40: Base g | D40: g +1%
A41: WACC -1.0% | B41: =IF(OR($B$13="",$B$19="",$F$18="",($B$13-0.01)<=($B$19-0.01)),"",SUM($B$21:$F$21)+($F$18*(1+($B$19-0.01))/(($B$13-0.01)-($B$19-0.01)))/(1+($B$13-0.01))^5) -> #VALUE! | C41: =IF(OR($B$13="",$B$19="",$F$18="",($B$13-0.01)<=($B$19)),"",SUM($B$21:$F$21)+($F$18*(1+$B$19)/(($B$13-0.01)-$B$19))/(1+($B$13-0.01))^5) -> #VALUE! | D41: =IF(OR($B$13="",$B$19="",$F$18="",($B$13-0.01)<=($B$19+0.01)),"",SUM($B$21:$F$21)+($F$18*(1+($B$19+0.01))/(($B$13-0.01)-($B$19+0.01)))/(1+($B$13-0.01))^5) -> #VALUE!
A42: Base WACC | B42: =IF(OR($B$13="",$B$19="",$F$18="",($B$13)<=($B$19-0.01)),"",SUM($B$21:$F$21)+($F$18*(1+($B$19-0.01))/($B$13-($B$19-0.01)))/(1+$B$13)^5) | C42: =B22 | D42: =IF(OR($B$13="",$B$19="",$F$18="",($B$13)<=($B$19+0.01)),"",SUM($B$21:$F$21)+($F$18*(1+($B$19+0.01))/($B$13-($B$19+0.01)))/(1+$B$13)^5)
A43: WACC +1.0% | B43: =IF(OR($B$13="",$B$19="",$F$18="",($B$13+0.01)<=($B$19-0.01)),"",SUM($B$21:$F$21)+($F$18*(1+($B$19-0.01))/(($B$13+0.01)-($B$19-0.01)))/(1+($B$13+0.01))^5) -> #VALUE! | C43: =IF(OR($B$13="",$B$19="",$F$18="",($B$13+0.01)<=($B$19)),"",SUM($B$21:$F$21)+($F$18*(1+$B$19)/(($B$13+0.01)-$B$19))/(1+($B$13+0.01))^5) -> #VALUE! | D43: =IF(OR($B$13="",$B$19="",$F$18="",($B$13+0.01)<=($B$19+0.01)),"",SUM($B$21:$F$21)+($F$18*(1+($B$19+0.01))/(($B$13+0.01)-($B$19+0.01)))/(1+($B$13+0.01))^5) -> #VALUE!
A44: Local vs U.S. Override Logic | B44: If country <> USA and local rate exists, use local for Entity 5
A45: Warning | B45: =IF(OR(Entity_Ownership!F8="",Entity_Ownership!G8=""),"WARNING: Missing Country/Currency Data",IF(B13="","WARNING: Incomplete CAPM / WACC Chain","")) -> WARNING: Missing Country/Currency Data

Sheet Valuation_Entity6
A1: VALUATION ANALYSIS - ENTITY 6
A3: SECTION A: WACC INPUTS
A4: Input | B4: Value | C4: Notes
A5: Risk Free Rate | B5: =IF(AND(Entity_Ownership!$F$9<>"",UPPER(Entity_Ownership!$F$9)<>"UNITED STATES",COUNTIFS(Global_Rates!$B$4:$B$73,"Entity 6",Global_Rates!$A$4:$A$73,"Local 10-Year Government Bond Yield",Global_Rates!$F$4:$F$73,"<>")>0),SUMIFS(Global_Rates!$F$4:$F$73,Global_Rates!$B$4:$B$73,"Entity 6",Global_Rates!$A$4:$A$73,"Local 10-Year Government Bond Yield"),IF(COUNTIFS(Global_Rates!$B$4:$B$73,"Entity 6",Global_Rates!$A$4:$A$73,"U.S. 10-Year Treasury",Global_Rates!$F$4:$F$73,"<>")>0,SUMIFS(Global_Rates!$F$4:$F$73,Global_Rates!$B$4:$B$73,"Entity 6",Global_Rates!$A$4:$A$73,"U.S. 10-Year Treasury"),"")) | C5: Rate used for CAPM
A6: Beta | B6: =IF(COUNTIFS(Global_Rates!$B$4:$B$73,"Entity 6",Global_Rates!$A$4:$A$73,"Beta",Global_Rates!$F$4:$F$73,"<>")>0,SUMIFS(Global_Rates!$F$4:$F$73,Global_Rates!$B$4:$B$73,"Entity 6",Global_Rates!$A$4:$A$73,"Beta"),"") | C6: Entity beta
A7: Market Risk Premium | B7: =IF(AND(Entity_Ownership!$F$9<>"",UPPER(Entity_Ownership!$F$9)<>"UNITED STATES",COUNTIFS(Global_Rates!$B$4:$B$73,"Entity 6",Global_Rates!$A$4:$A$73,"Local Market Risk Premium",Global_Rates!$F$4:$F$73,"<>")>0),SUMIFS(Global_Rates!$F$4:$F$73,Global_Rates!$B$4:$B$73,"Entity 6",Global_Rates!$A$4:$A$73,"Local Market Risk Premium"),IF(COUNTIFS(Global_Rates!$B$4:$B$73,"Entity 6",Global_Rates!$A$4:$A$73,"U.S. Market Risk Premium",Global_Rates!$F$4:$F$73,"<>")>0,SUMIFS(Global_Rates!$F$4:$F$73,Global_Rates!$B$4:$B$73,"Entity 6",Global_Rates!$A$4:$A$73,"U.S. Market Risk Premium"),"")) | C7: Rate used for CAPM
A8: Cost of Debt | B8: =IF(AND(Entity_Ownership!$F$9<>"",UPPER(Entity_Ownership!$F$9)<>"UNITED STATES",COUNTIFS(Global_Rates!$B$4:$B$73,"Entity 6",Global_Rates!$A$4:$A$73,"Local Corporate Bond Yield",Global_Rates!$F$4:$F$73,"<>")>0),SUMIFS(Global_Rates!$F$4:$F$73,Global_Rates!$B$4:$B$73,"Entity 6",Global_Rates!$A$4:$A$73,"Local Corporate Bond Yield"),IF(COUNTIFS(Global_Rates!$B$4:$B$73,"Entity 6",Global_Rates!$A$4:$A$73,"U.S. Corporate Bond Yield",Global_Rates!$F$4:$F$73,"<>")>0,SUMIFS(Global_Rates!$F$4:$F$73,Global_Rates!$B$4:$B$73,"Entity 6",Global_Rates!$A$4:$A$73,"U.S. Corporate Bond Yield"),"")) | C8: Pre-tax cost of debt
A9: Tax Rate | B9: =IF(OR(Fin_Inputs_Entity6!F13="",Fin_Inputs_Entity6!F11="",Fin_Inputs_Entity6!F11=0),"",ABS(Fin_Inputs_Entity6!F13/Fin_Inputs_Entity6!F11)) | C9: Taxes / EBIT
A10: Debt Weight | B10: =IF((N(Fin_Inputs_Entity6!F26)+N(Fin_Inputs_Entity6!F27)+N(Fin_Inputs_Entity6!F29))=0,"",(N(Fin_Inputs_Entity6!F26)+N(Fin_Inputs_Entity6!F27))/(N(Fin_Inputs_Entity6!F26)+N(Fin_Inputs_Entity6!F27)+N(Fin_Inputs_Entity6!F29))) | C10: Debt / (Debt + Equity)
A11: Equity Weight | B11: =IF((N(Fin_Inputs_Entity6!F26)+N(Fin_Inputs_Entity6!F27)+N(Fin_Inputs_Entity6!F29))=0,"",N(Fin_Inputs_Entity6!F29)/(N(Fin_Inputs_Entity6!F26)+N(Fin_Inputs_Entity6!F27)+N(Fin_Inputs_Entity6!F29))) | C11: Equity / (Debt + Equity)
A12: Cost of Equity | B12: =IF(COUNT(B5:B7)<3,"",B5+B6*B7) | C12: CAPM
A13: WACC | B13: =IF(COUNT(B8:B12)<5,"",(B11*B12)+(B10*B8*(1-B9))) | C13: Weighted average cost of capital
A14: FX Rate Used | B14: =IF(FX_Rate_Entity6="","",FX_Rate_Entity6) | C14: Previous month-end or override
A15: SECTION B: DCF MODEL
A16: Item
A17: Forecasted FCF | B17: Year 1 | C17: Year 2 | D17: Year 3 | E17: Year 4 | F17: Year 5 | G17: Terminal
A18: Terminal Growth Rate | B18: =IF(OR(Fin_Inputs_Entity6!B37="",B14=""),"",Fin_Inputs_Entity6!B37*B14*(1+N(Scenario_Analysis!$E$4)-N(Scenario_Analysis!$E$6)-N(Scenario_Analysis!$E$7))) | C18: =IF(OR(Fin_Inputs_Entity6!C37="",B14=""),"",Fin_Inputs_Entity6!C37*B14*(1+N(Scenario_Analysis!$E$4)-N(Scenario_Analysis!$E$6)-N(Scenario_Analysis!$E$7))) | D18: =IF(OR(Fin_Inputs_Entity6!D37="",B14=""),"",Fin_Inputs_Entity6!D37*B14*(1+N(Scenario_Analysis!$E$4)-N(Scenario_Analysis!$E$6)-N(Scenario_Analysis!$E$7))) | E18: =IF(OR(Fin_Inputs_Entity6!E37="",B14=""),"",Fin_Inputs_Entity6!E37*B14*(1+N(Scenario_Analysis!$E$4)-N(Scenario_Analysis!$E$6)-N(Scenario_Analysis!$E$7))) | F18: =IF(OR(Fin_Inputs_Entity6!F37="",B14=""),"",Fin_Inputs_Entity6!F37*B14*(1+N(Scenario_Analysis!$E$4)-N(Scenario_Analysis!$E$6)-N(Scenario_Analysis!$E$7)))
A19: Terminal Value | B19: 0.02 | G19: =IF(OR(F18="",B13="",B19="",B13<=B19),"",F18*(1+B19)/(B13-B19))
A20: Discount Factor | B20: =IF(B13="","",1/(1+B13)^1) | C20: =IF(B13="","",1/(1+B13)^2) | D20: =IF(B13="","",1/(1+B13)^3) | E20: =IF(B13="","",1/(1+B13)^4) | F20: =IF(B13="","",1/(1+B13)^5) | G20: =IF(B13="","",1/(1+B13)^5)
A21: PV of Cash Flows | B21: =IF(OR(B18="",B20=""),"",B18*B20) | C21: =IF(OR(C18="",C20=""),"",C18*C20) | D21: =IF(OR(D18="",D20=""),"",D18*D20) | E21: =IF(OR(E18="",E20=""),"",E18*E20) | F21: =IF(OR(F18="",F20=""),"",F18*F20) | G21: =IF(OR(G19="",G20=""),"",G19*G20)
A22: DCF Enterprise Value | B22: =IF(COUNT(B21:G21)=0,"",SUM(B21:G21)) | C22: =IF(OR(C18="",C21=""),"",C18*C21) | D22: =IF(OR(D18="",D21=""),"",D18*D21) | E22: =IF(OR(E18="",E21=""),"",E18*E21) | F22: =IF(OR(F18="",F21=""),"",F18*F21) | G22: =IF(OR(G20="",G21=""),"",G20*G21)
A23: DCF Enterprise Value | B23: =IF(COUNT(B22:G22)=0,"",SUM(B22:G22)) | H23: =IF(OR(F21="",B13="",B22="",B13<=B22),"",F21*(1+B22)/(B13-B22))
A25: Multiple
A26: Multiple | B26: Multiple Value | C26: Metric | D26: Implied EV
A27: EV/EBITDA | B27: 6 | C27: =IF(OR(Fin_Inputs_Entity6!F9="",B14=""),"",Fin_Inputs_Entity6!F9*B14) | D27: =IF(OR(B27="",C27=""),"",B27*C27)
A28: EV/Revenue | B28: 1.5 | C28: =IF(OR(Fin_Inputs_Entity6!F5="",B14=""),"",Fin_Inputs_Entity6!F5*B14) | D28: =IF(OR(B28="",C28=""),"",B28*C28)
A29: P/E | B29: 10 | C29: =IF(OR(Fin_Inputs_Entity6!F14="",B14=""),"",Fin_Inputs_Entity6!F14*B14) | D29: =IF(OR(B29="",C29=""),"",B29*C29)
A30: Average Multiples Value | B30: =IF(COUNT(D27:D29)=0,"",AVERAGE(D27:D29)) | D30: =IF(COUNT(D27:D29)=0,"",AVERAGE(D27:D29))
A31: Warning | B31: =IF(OR(Entity_Ownership!F9="",FX_Conversion!B9=""),"WARNING: Missing Country/Currency Data",IF(OR(B5="",B6="",B7="",B8="",B14=""),"WARNING: Incomplete CAPM / WACC / FX Chain","")) -> WARNING: Missing Country/Currency Data
A33: Item
A34: DCF Value | B34: =B23 | C34: USD pre-ownership
A35: Multiples Value | B35: =B30 | C35: USD pre-ownership
A36: Blended Value | B36: =IF(COUNT(B34:B35)=0,"",AVERAGE(B34:B35)) | C36: USD pre-ownership
A37: Final Valuation | B37: =IF(B36="","",B36*IF(Entity_Ownership!C9="",1,Entity_Ownership!C9)) | C37: USD ownership-adjusted
A39: Sensitivity Table
A40: WACC / g | B40: g -1% | C40: Base g | D40: g +1%
A41: WACC -1.0% | B41: =IF(OR($B$13="",$B$19="",$F$18="",($B$13-0.01)<=($B$19-0.01)),"",SUM($B$21:$F$21)+($F$18*(1+($B$19-0.01))/(($B$13-0.01)-($B$19-0.01)))/(1+($B$13-0.01))^5) -> #VALUE! | C41: =IF(OR($B$13="",$B$19="",$F$18="",($B$13-0.01)<=($B$19)),"",SUM($B$21:$F$21)+($F$18*(1+$B$19)/(($B$13-0.01)-$B$19))/(1+($B$13-0.01))^5) -> #VALUE! | D41: =IF(OR($B$13="",$B$19="",$F$18="",($B$13-0.01)<=($B$19+0.01)),"",SUM($B$21:$F$21)+($F$18*(1+($B$19+0.01))/(($B$13-0.01)-($B$19+0.01)))/(1+($B$13-0.01))^5) -> #VALUE!
A42: Base WACC | B42: =IF(OR($B$13="",$B$19="",$F$18="",($B$13)<=($B$19-0.01)),"",SUM($B$21:$F$21)+($F$18*(1+($B$19-0.01))/($B$13-($B$19-0.01)))/(1+$B$13)^5) | C42: =B22 | D42: =IF(OR($B$13="",$B$19="",$F$18="",($B$13)<=($B$19+0.01)),"",SUM($B$21:$F$21)+($F$18*(1+($B$19+0.01))/($B$13-($B$19+0.01)))/(1+$B$13)^5)
A43: WACC +1.0% | B43: =IF(OR($B$13="",$B$19="",$F$18="",($B$13+0.01)<=($B$19-0.01)),"",SUM($B$21:$F$21)+($F$18*(1+($B$19-0.01))/(($B$13+0.01)-($B$19-0.01)))/(1+($B$13+0.01))^5) -> #VALUE! | C43: =IF(OR($B$13="",$B$19="",$F$18="",($B$13+0.01)<=($B$19)),"",SUM($B$21:$F$21)+($F$18*(1+$B$19)/(($B$13+0.01)-$B$19))/(1+($B$13+0.01))^5) -> #VALUE! | D43: =IF(OR($B$13="",$B$19="",$F$18="",($B$13+0.01)<=($B$19+0.01)),"",SUM($B$21:$F$21)+($F$18*(1+($B$19+0.01))/(($B$13+0.01)-($B$19+0.01)))/(1+($B$13+0.01))^5) -> #VALUE!
A44: Local vs U.S. Override Logic | B44: If country <> USA and local rate exists, use local for Entity 6
A45: Warning | B45: =IF(OR(Entity_Ownership!F9="",Entity_Ownership!G9=""),"WARNING: Missing Country/Currency Data",IF(B13="","WARNING: Incomplete CAPM / WACC Chain","")) -> WARNING: Missing Country/Currency Data

Sheet Valuation_Entity7
A1: VALUATION ANALYSIS - ENTITY 7
A3: SECTION A: WACC INPUTS
A4: Input | B4: Value | C4: Notes
A5: Risk Free Rate | B5: =IF(AND(Entity_Ownership!$F$10<>"",UPPER(Entity_Ownership!$F$10)<>"UNITED STATES",COUNTIFS(Global_Rates!$B$4:$B$73,"Entity 7",Global_Rates!$A$4:$A$73,"Local 10-Year Government Bond Yield",Global_Rates!$F$4:$F$73,"<>")>0),SUMIFS(Global_Rates!$F$4:$F$73,Global_Rates!$B$4:$B$73,"Entity 7",Global_Rates!$A$4:$A$73,"Local 10-Year Government Bond Yield"),IF(COUNTIFS(Global_Rates!$B$4:$B$73,"Entity 7",Global_Rates!$A$4:$A$73,"U.S. 10-Year Treasury",Global_Rates!$F$4:$F$73,"<>")>0,SUMIFS(Global_Rates!$F$4:$F$73,Global_Rates!$B$4:$B$73,"Entity 7",Global_Rates!$A$4:$A$73,"U.S. 10-Year Treasury"),"")) | C5: Rate used for CAPM
A6: Beta | B6: =IF(COUNTIFS(Global_Rates!$B$4:$B$73,"Entity 7",Global_Rates!$A$4:$A$73,"Beta",Global_Rates!$F$4:$F$73,"<>")>0,SUMIFS(Global_Rates!$F$4:$F$73,Global_Rates!$B$4:$B$73,"Entity 7",Global_Rates!$A$4:$A$73,"Beta"),"") | C6: Entity beta
A7: Market Risk Premium | B7: =IF(AND(Entity_Ownership!$F$10<>"",UPPER(Entity_Ownership!$F$10)<>"UNITED STATES",COUNTIFS(Global_Rates!$B$4:$B$73,"Entity 7",Global_Rates!$A$4:$A$73,"Local Market Risk Premium",Global_Rates!$F$4:$F$73,"<>")>0),SUMIFS(Global_Rates!$F$4:$F$73,Global_Rates!$B$4:$B$73,"Entity 7",Global_Rates!$A$4:$A$73,"Local Market Risk Premium"),IF(COUNTIFS(Global_Rates!$B$4:$B$73,"Entity 7",Global_Rates!$A$4:$A$73,"U.S. Market Risk Premium",Global_Rates!$F$4:$F$73,"<>")>0,SUMIFS(Global_Rates!$F$4:$F$73,Global_Rates!$B$4:$B$73,"Entity 7",Global_Rates!$A$4:$A$73,"U.S. Market Risk Premium"),"")) | C7: Rate used for CAPM
A8: Cost of Debt | B8: =IF(AND(Entity_Ownership!$F$10<>"",UPPER(Entity_Ownership!$F$10)<>"UNITED STATES",COUNTIFS(Global_Rates!$B$4:$B$73,"Entity 7",Global_Rates!$A$4:$A$73,"Local Corporate Bond Yield",Global_Rates!$F$4:$F$73,"<>")>0),SUMIFS(Global_Rates!$F$4:$F$73,Global_Rates!$B$4:$B$73,"Entity 7",Global_Rates!$A$4:$A$73,"Local Corporate Bond Yield"),IF(COUNTIFS(Global_Rates!$B$4:$B$73,"Entity 7",Global_Rates!$A$4:$A$73,"U.S. Corporate Bond Yield",Global_Rates!$F$4:$F$73,"<>")>0,SUMIFS(Global_Rates!$F$4:$F$73,Global_Rates!$B$4:$B$73,"Entity 7",Global_Rates!$A$4:$A$73,"U.S. Corporate Bond Yield"),"")) | C8: Pre-tax cost of debt
A9: Tax Rate | B9: =IF(OR(Fin_Inputs_Entity7!F13="",Fin_Inputs_Entity7!F11="",Fin_Inputs_Entity7!F11=0),"",ABS(Fin_Inputs_Entity7!F13/Fin_Inputs_Entity7!F11)) | C9: Taxes / EBIT
A10: Debt Weight | B10: =IF((N(Fin_Inputs_Entity7!F26)+N(Fin_Inputs_Entity7!F27)+N(Fin_Inputs_Entity7!F29))=0,"",(N(Fin_Inputs_Entity7!F26)+N(Fin_Inputs_Entity7!F27))/(N(Fin_Inputs_Entity7!F26)+N(Fin_Inputs_Entity7!F27)+N(Fin_Inputs_Entity7!F29))) | C10: Debt / (Debt + Equity)
A11: Equity Weight | B11: =IF((N(Fin_Inputs_Entity7!F26)+N(Fin_Inputs_Entity7!F27)+N(Fin_Inputs_Entity7!F29))=0,"",N(Fin_Inputs_Entity7!F29)/(N(Fin_Inputs_Entity7!F26)+N(Fin_Inputs_Entity7!F27)+N(Fin_Inputs_Entity7!F29))) | C11: Equity / (Debt + Equity)
A12: Cost of Equity | B12: =IF(COUNT(B5:B7)<3,"",B5+B6*B7) | C12: CAPM
A13: WACC | B13: =IF(COUNT(B8:B12)<5,"",(B11*B12)+(B10*B8*(1-B9))) | C13: Weighted average cost of capital
A14: FX Rate Used | B14: =IF(FX_Rate_Entity7="","",FX_Rate_Entity7) | C14: Previous month-end or override
A15: SECTION B: DCF MODEL
A16: Item
A17: Forecasted FCF | B17: Year 1 | C17: Year 2 | D17: Year 3 | E17: Year 4 | F17: Year 5 | G17: Terminal
A18: Terminal Growth Rate | B18: =IF(OR(Fin_Inputs_Entity7!B37="",B14=""),"",Fin_Inputs_Entity7!B37*B14*(1+N(Scenario_Analysis!$E$4)-N(Scenario_Analysis!$E$6)-N(Scenario_Analysis!$E$7))) | C18: =IF(OR(Fin_Inputs_Entity7!C37="",B14=""),"",Fin_Inputs_Entity7!C37*B14*(1+N(Scenario_Analysis!$E$4)-N(Scenario_Analysis!$E$6)-N(Scenario_Analysis!$E$7))) | D18: =IF(OR(Fin_Inputs_Entity7!D37="",B14=""),"",Fin_Inputs_Entity7!D37*B14*(1+N(Scenario_Analysis!$E$4)-N(Scenario_Analysis!$E$6)-N(Scenario_Analysis!$E$7))) | E18: =IF(OR(Fin_Inputs_Entity7!E37="",B14=""),"",Fin_Inputs_Entity7!E37*B14*(1+N(Scenario_Analysis!$E$4)-N(Scenario_Analysis!$E$6)-N(Scenario_Analysis!$E$7))) | F18: =IF(OR(Fin_Inputs_Entity7!F37="",B14=""),"",Fin_Inputs_Entity7!F37*B14*(1+N(Scenario_Analysis!$E$4)-N(Scenario_Analysis!$E$6)-N(Scenario_Analysis!$E$7)))
A19: Terminal Value | B19: 0.02 | G19: =IF(OR(F18="",B13="",B19="",B13<=B19),"",F18*(1+B19)/(B13-B19))
A20: Discount Factor | B20: =IF(B13="","",1/(1+B13)^1) | C20: =IF(B13="","",1/(1+B13)^2) | D20: =IF(B13="","",1/(1+B13)^3) | E20: =IF(B13="","",1/(1+B13)^4) | F20: =IF(B13="","",1/(1+B13)^5) | G20: =IF(B13="","",1/(1+B13)^5)
A21: PV of Cash Flows | B21: =IF(OR(B18="",B20=""),"",B18*B20) | C21: =IF(OR(C18="",C20=""),"",C18*C20) | D21: =IF(OR(D18="",D20=""),"",D18*D20) | E21: =IF(OR(E18="",E20=""),"",E18*E20) | F21: =IF(OR(F18="",F20=""),"",F18*F20) | G21: =IF(OR(G19="",G20=""),"",G19*G20)
A22: DCF Enterprise Value | B22: =IF(COUNT(B21:G21)=0,"",SUM(B21:G21)) | C22: =IF(OR(C18="",C21=""),"",C18*C21) | D22: =IF(OR(D18="",D21=""),"",D18*D21) | E22: =IF(OR(E18="",E21=""),"",E18*E21) | F22: =IF(OR(F18="",F21=""),"",F18*F21) | G22: =IF(OR(G20="",G21=""),"",G20*G21)
A23: DCF Enterprise Value | B23: =IF(COUNT(B22:G22)=0,"",SUM(B22:G22)) | H23: =IF(OR(F21="",B13="",B22="",B13<=B22),"",F21*(1+B22)/(B13-B22))
A25: Multiple
A26: Multiple | B26: Multiple Value | C26: Metric | D26: Implied EV
A27: EV/EBITDA | B27: 6 | C27: =IF(OR(Fin_Inputs_Entity7!F9="",B14=""),"",Fin_Inputs_Entity7!F9*B14) | D27: =IF(OR(B27="",C27=""),"",B27*C27)
A28: EV/Revenue | B28: 1.5 | C28: =IF(OR(Fin_Inputs_Entity7!F5="",B14=""),"",Fin_Inputs_Entity7!F5*B14) | D28: =IF(OR(B28="",C28=""),"",B28*C28)
A29: P/E | B29: 10 | C29: =IF(OR(Fin_Inputs_Entity7!F14="",B14=""),"",Fin_Inputs_Entity7!F14*B14) | D29: =IF(OR(B29="",C29=""),"",B29*C29)
A30: Average Multiples Value | B30: =IF(COUNT(D27:D29)=0,"",AVERAGE(D27:D29)) | D30: =IF(COUNT(D27:D29)=0,"",AVERAGE(D27:D29))
A31: Warning | B31: =IF(OR(Entity_Ownership!F10="",FX_Conversion!B10=""),"WARNING: Missing Country/Currency Data",IF(OR(B5="",B6="",B7="",B8="",B14=""),"WARNING: Incomplete CAPM / WACC / FX Chain","")) -> WARNING: Missing Country/Currency Data
A33: Item
A34: DCF Value | B34: =B23 | C34: USD pre-ownership
A35: Multiples Value | B35: =B30 | C35: USD pre-ownership
A36: Blended Value | B36: =IF(COUNT(B34:B35)=0,"",AVERAGE(B34:B35)) | C36: USD pre-ownership
A37: Final Valuation | B37: =IF(B36="","",B36*IF(Entity_Ownership!C10="",1,Entity_Ownership!C10)) | C37: USD ownership-adjusted
A39: Sensitivity Table
A40: WACC / g | B40: g -1% | C40: Base g | D40: g +1%
A41: WACC -1.0% | B41: =IF(OR($B$13="",$B$19="",$F$18="",($B$13-0.01)<=($B$19-0.01)),"",SUM($B$21:$F$21)+($F$18*(1+($B$19-0.01))/(($B$13-0.01)-($B$19-0.01)))/(1+($B$13-0.01))^5) -> #VALUE! | C41: =IF(OR($B$13="",$B$19="",$F$18="",($B$13-0.01)<=($B$19)),"",SUM($B$21:$F$21)+($F$18*(1+$B$19)/(($B$13-0.01)-$B$19))/(1+($B$13-0.01))^5) -> #VALUE! | D41: =IF(OR($B$13="",$B$19="",$F$18="",($B$13-0.01)<=($B$19+0.01)),"",SUM($B$21:$F$21)+($F$18*(1+($B$19+0.01))/(($B$13-0.01)-($B$19+0.01)))/(1+($B$13-0.01))^5) -> #VALUE!
A42: Base WACC | B42: =IF(OR($B$13="",$B$19="",$F$18="",($B$13)<=($B$19-0.01)),"",SUM($B$21:$F$21)+($F$18*(1+($B$19-0.01))/($B$13-($B$19-0.01)))/(1+$B$13)^5) | C42: =B22 | D42: =IF(OR($B$13="",$B$19="",$F$18="",($B$13)<=($B$19+0.01)),"",SUM($B$21:$F$21)+($F$18*(1+($B$19+0.01))/($B$13-($B$19+0.01)))/(1+$B$13)^5)
